Workbook
Name A.TH.ER: #REF!
Name A.TH.ER: #REF!
Name A.TH.ER: #REF!
Name A.TH.ER: #REF!
Name A.TH.IN: #REF!
Name A.TH.IN: #REF!
Name A.TH.IN: #REF!
Name A.TH.IN: #REF!
Name A.TH.NT: #REF!
Name A.TH.NT: #REF!
Name A.TH.NT: #REF!
Name A.TH.NT: #REF!
Name A.TH.SR: #REF!
Name A.TH.SR: #REF!
Name A.TH.SR: #REF!
Name A.TH.SR: #REF!
Name A.TH.WA: #REF!
Name A.TH.WA: #REF!
Name A.TH.WA: #REF!
Name A.TH.WA: #REF!
Name C.TH.ER: #REF!
Name C.TH.ER: #REF!
Name C.TH.ER: #REF!
Name C.TH.ER: #REF!
Name C.TH.IN: #REF!
Name C.TH.IN: #REF!
Name C.TH.IN: #REF!
Name C.TH.IN: #REF!
Name C.TH.NT: #REF!
Name C.TH.NT: #REF!
Name C.TH.NT: #REF!
Name C.TH.NT: #REF!
Name C.TH.SR: #REF!
Name C.TH.SR: #REF!
Name C.TH.SR: #REF!
Name C.TH.SR: #REF!
Name C.TH.WA: #REF!
Name C.TH.WA: #REF!
Name C.TH.WA: #REF!
Name C.TH.WA: #REF!
Name Function: "RAaux. primary-supporting!$A1:$A5"
Name group.1: [0]!Function:GenBIATable
Name group.1: [0]!Function:GenBIATable
Name group.1: [0]!Function:GenBIATable
Name group.1: [0]!Function:GenBIATable
Name group.1: [0]!Function:GenBIATable
Name group.1: [0]!Function:GenBIATable
Name group.1: [0]!Function:GenBIATable
Name group.2: [0]!Function:GenBIATable
Name group.2: [0]!Function:GenBIATable
Name group.2: [0]!Function:GenBIATable
Name group.2: [0]!Function:GenBIATable
Name group.2: [0]!Function:GenBIATable
Name group.2: [0]!Function:GenBIATable
Name group.2: [0]!Function:GenBIATable
Name group.3: [0]!Function:GenBIATable
Name group.3: [0]!Function:GenBIATable
Name group.3: [0]!Function:GenBIATable
Name group.3: [0]!Function:GenBIATable
Name group.3: [0]!Function:GenBIATable

Sheet Threats catalogue
L2: Services | Q2: Software | Z2: Hardware | AG2: People | AJ2: Location
E3: Security Dimensions | H3: Source | J3: Likelihood | L3: SaaS | M3: IaaS | N3: PaaS | O3: Other | P3: Network | Q3: Firmware | R3: Middleware | X3: End user application | Z3: Processin/Storage | AF3: Portable | AG3: Decision maker | AH3: Normal User | AI3: Privileged user | AJ3: Physical Location | AK3: Utilities
B4: Type of threat | C4: ID | D4: Threat | E4: C | F4: I | G4: A | H4: D | I4: A | J4: E | K4: F | R4: Operating systems | S4: Web server | T4: Virtualisation layer | U4: Network stack | V4: Application server | W4: DBMS server | X4: In house developed | Y4: COTS | Z4: User device (portable) | AA4: User device (fixed) | AB4: Shared device (fixed) | AC4: Network equipment | AD4: Wired media | AE4: Wireless media
B5: Physical damage | C5: 1 | D5: Fire | F5: X | G5: X | H5: X | I5: X | J5: 4 | K5: 2 | O5: X | AA5: X | AB5: X | AC5: X | AD5: X | AF5: X | AJ5: X | AK5: X
C6: 2 | D6: Water damage | F6: X | G6: X | H6: X | I6: X | J6: 4 | K6: 2 | O6: X | AA6: X | AB6: X | AC6: X | AD6: X | AF6: X | AJ6: X | AK6: X
C7: 3 | D7: Pollution | F7: X | G7: X | I7: X | K7: 2 | O7: X | AA7: X | AB7: X | AC7: X | AF7: X | AK7: X
C8: 4 | D8: Major accident | F8: X | G8: X | H8: X | I8: X | J8: 2 | K8: 3 | O8: X | AA8: X | AB8: X | AC8: X | AD8: X | AF8: X | AJ8: X | AK8: X
C9: 5 | D9: Destruction of equipment or media | F9: X | G9: X | H9: X | I9: X | J9: 3 | K9: 3 | O9: X | Z9: X | AA9: X | AB9: X | AC9: X | AD9: X | AF9: X | AK9: X
C10: 6 | D10: Dust, corrosion, freezing | F10: X | G10: X | I10: X | K10: 2 | O10: X | Z10: X | AA10: X | AB10: X | AC10: X | AD10: X | AF10: X | AK10: X
B11: Natural events | C11: 7 | D11: Climatic phenomenon | F11: X | G11: X | I11: X | K11: 1 | O11: X | Z11: X | AA11: X | AB11: X | AC11: X | AD11: X | AF11: X | AJ11: X | AK11: X
C12: 8 | D12: Seismic phenomenon | F12: X | G12: X | I12: X | K12: 1 | Z12: X | AA12: X | AB12: X | AC12: X | AD12: X | AJ12: X | AK12: X
C13: 9 | D13: Volcanic phenomenon | F13: X | G13: X | I13: X | K13: 1 | Z13: X | AA13: X | AB13: X | AC13: X | AD13: X | AJ13: X | AK13: X
C14: 10 | D14: Meteorological phenomenon | F14: X | G14: X | I14: X | K14: 2 | AA14: X | AB14: X | AC14: X | AD14: X | AJ14: X | AK14: X
C15: 11 | D15: Flood | F15: X | G15: X | I15: X | K15: 1 | AA15: X | AB15: X | AC15: X | AJ15: X | AK15: X
B16: Loss of esential services | C16: 12 | D16: Failure of air-conditioning or water supply system | G16: X | H16: X | I16: X | J16: 3 | K16: 2 | AB16: X | AC16: X | AJ16: X | AK16: X
C17: 13 | D17: Loss of power supply | G17: X | I17: X | K17: 2 | AA17: X | AB17: X | AC17: X | AJ17: X | AK17: X
C18: 14 | D18: Failure of telecommunication equipment | G18: X | I18: X | K18: 2 | P18: X | AC18: X | AD18: x | AE18: x
B19: Disturbance due to radiation | C19: 15 | D19: Electromagnetion radiation | F19: X | G19: X | H19: X | I19: X | J19: 1 | K19: 1 | Z19: X | AA19: X | AB19: X | AC19: X | AD19: X | AE19: X | AK19: X
C20: 16 | D20: Thermal radiation | F20: X | G20: X | H20: X | I20: X | J20: 1 | K20: 1 | Z20: X | AA20: X | AB20: X | AC20: X | AK20: X
C21: 17 | D21: Electromagnetic pulses | F21: X | G21: X | H21: X | I21: X | J21: 2 | K21: 1 | AK21: X
B22: Compromise of information | C22: 18 | D22: Interception of compromising interface signals | E22: X | H22: X | J22: 2 | U22: X | Z22: X | AC22: X | AE22: X | AF22: X
C23: 19 | D23: Remote spying | E23: X | F23: X | G23: X | H23: X | J23: 2 | Z23: X | AA23: X | AG23: X | AH23: X | AI23: X
C24: 20 | D24: Eavesdropping | E24: X | H24: X | J24: 1 | P24: X | U24: X | Z24: X | AA24: X | AB24: X | AC24: X | AD24: X | AE24: X
C25: 21 | D25: Theft of media or documents | E25: X | H25: X | J25: 5 | Z25: X | AA25: X | AF25: X
C26: 22 | D26: Theft of equipment | E26: X | G26: X | H26: X | J26: 5 | Z26: X | AA26: X | AB26: X | AC26: X
C27: 23 | D27: Retrieval of recycled or discarded media | E27: X | H27: X | J27: 5 | Z27: X | AA27: X | AB27: X | AF27: X
C28: 24 | D28: Disclosure | E28: X | H28: X | I28: X | J28: 5 | K28: 3 | AG28: X | AH28: X | AI28: X
C29: 25 | D29: Data from untrustworthy sources | F29: X | G29: X | H29: X | I29: X | J29: 4 | K29: 4 | AG29: X | AH29: X | AI29: X
C30: 26 | D30: Tampering with hardware | E30: X | H30: X | J30: 3 | Z30: X | AA30: X | AB30: X
C31: 27 | D31: Tampering with software | E31: X | F31: X | G31: X | H31: X | I31: X | J31: 3 | K31: 4 | Q31: X | R31: X | S31: X | T31: X | V31: X | W31: X | X31: X | Y31: X
C32: 28 | D32: Position detection | E32: X | H32: X | J32: 2 | Z32: X
C33: 29 | D33: Advanced persistant threat | E33: X | F33: X | G33: X | H33: X | J33: 1 | Q33: X | R33: X | S33: X | T33: X | U33: X | V33: X | W33: X | X33: X | Y33: X | Z33: X | AA33: X | AB33: X | AC33: X | AD33: X | AE33: X | AG33: X | AH33: X | AI33: X
C34: 30 | D34: Social engineering | E34: X | G34: X | H34: X | J34: 3 | AG34: X | AH34: X | AI34: X
B35: Technical failures | C35: 31 | D35: Equipment failure | G35: X | I35: X | K35: 2 | Z35: X | AA35: X | AB35: X | AC35: X
C36: 32 | D36: Equipment malfunction | G36: X | I36: X | K36: 3
C37: 33 | D37: Saturation of the information system | G37: X | H37: X | J37: 4 | K37: 2 | P37: X | Q37: X | R37: X | S37: X | T37: X | U37: X | V37: X | W37: X | X37: X | Y37: X | Z37: X | AA37: X | AB37: X | AC37: X
C38: 34 | D38: Software malfunction | F38: X | G38: X | I38: X | K38: 3 | R38: X | S38: X | T38: X | V38: X | W38: X | X38: X | Y38: X | AG38: X | AH38: X | AI38: X
C39: 35 | D39: Breach of information system maintainability | G39: X | H39: X | I39: X | J39: 5 | K39: 2 | P39: X | Q39: X | R39: X | S39: X | T39: X | U39: X | V39: X | W39: X | X39: X | Y39: X | Z39: X | AA39: X | AB39: X | AC39: X | AD39: X | AF39: X
B40: Unauthorised Actions | C40: 36 | D40: Unauthorised use of equipment | E40: X | F40: X | G40: X | H40: X | J40: 3 | Q40: X | R40: X | S40: X | T40: X | V40: X | W40: X | X40: X | Y40: X | Z40: X | AA40: X | AB40: X | AC40: X
C41: 37 | D41: Fraudulent copying of software | E41: X | H41: X | J41: 4 | X41: X | Y41: X | AG41: X | AH41: X | AI41: X
C42: 38 | D42: Use of counterfeit or copied software | G42: X | H42: X | I42: X | J42: 4 | K42: 4 | R42: X | S42: X | T42: X | V42: X | W42: X | AG42: X | AH42: X | AI42: X
C43: 39 | D43: Corruption of data | E43: X | F43: X | H43: X | J43: 4 | U43: X | AC43: X | AD43: X | AE43: X
C44: 40 | D44: Illegal processing of data | E44: X | H44: X | J44: 4 | AG44: X | AH44: X | AI44: X
B45: Compromise of functions | C45: 41 | D45: Error in use | E45: X | F45: X | G45: X | I45: X | K45: 4 | Q45: X | R45: X | S45: X | T45: X | U45: X | V45: X | W45: X | X45: X | Y45: X | Z45: X | AA45: X | AB45: X | AC45: X | AG45: X | AH45: X | AI45: X
C46: 42 | D46: Abuse of rights | E46: X | F46: X | G46: X | H46: X | I46: X | J46: 4 | K46: 2 | Q46: X | R46: X | S46: X | T46: X | U46: X | V46: X | W46: X | X46: X | Y46: X | Z46: X | AA46: X | AB46: X | AC46: X
C47: 43 | D47: Forging of rights | E47: X | F47: X | G47: X | H47: X | J47: 3 | Q47: X | R47: X | S47: X | T47: X | V47: X | W47: X | X47: X | Y47: X | AG47: X | AH47: X | AI47: X
C48: 44 | D48: Denial of actions | F48: X | H48: X | J48: 5
C49: 45 | D49: Breach of personnel availability | G49: X | H49: X | I49: X | J49: 5 | K49: 2 | AG49: X | AH49: X | AI49: X
B50: Cloud | C50: 46 | D50: Loss of governance | E50: X | F50: X | G50: X | I50: X | K50: 4 | L50: X | M50: X | N50: X
C51: 47 | D51: Collateral consequencues due to co-tenant activities | E51: X | F51: X | G51: X | I51: X | K51: 3 | L51: X | M51: X | N51: X
C52: 48 | D52: Security failure in the cloud services | E52: X | F52: X | G52: X | I52: X | K52: 3 | L52: X | M52: X | N52: X
C53: 49 | D53: Service failure in the cloud services | E53: X | F53: X | G53: X | I53: X | K53: 3 | L53: X | M53: X | N53: X
C54: 50 | D54: Termination in the cloud services | G54: X | I54: X | K54: 4 | L54: X | M54: X | N54: X
C55: 51 | D55: Insufficiente due diligence | E55: X | F55: X | G55: X | I55: X | K55: 4 | L55: X | M55: X | N55: X

Sheet Threats agent catalogue
A1: Type | B1: Subtype | C1: Description | D1: Power value
A2: External | B2: Nation States | C2: State-sponsored espionage activities related with intelligence or military groups. | D2: 5
B3: Cybercriminals | C3: Organised groups that commit illegal activities involving a computer or network-connected device, e.g.: crimes in which the computing device is the target; crimes in which the computer is used as a weapon. | D3: 4
B4: Cyber terrorism | C4: Hacker groups that, acting with terrorist objectives (ISIS cyber terrorist), use available anonymous tools and techniques or other illicit resources for communicating purposes, such as the deep web. | D4: 3
B5: Corporations | C5: Corporate-sponsored espionage activities. | D5: 3
B6: Hacktivists | C6: People that use the same tools and techniques as a hacker with the intention of disrupting services and bringing attention to a political or social cause. | D6: 2
B7: Script Kiddies | C7: Group of TA with technical knowledge but no financial, personal or ideological aspirations. They normally act as a consequence of their curiosity. | D7: 1
A8: Internal | B8: Partner/Contractor | C8: Organisation or individual (with no direct contractual link) that provides services to the target organisation. This may be a hosting facility, cloud provider, or any other service provider. | D8: 5
B9: Privileged insider | C9: Current employee with limited knowledge about system misuses or safeguards but with privileged access to sensitive information. | D9: 5
B10: Insider | C10: Current employee with limited knowledge about system misuses or safeguards and limited access to sensitive information. | D10: 3

Sheet SA types catalogue
A1: First level | B1: Second level | C1: Third level | D1: Examples
A2: Services | B2: IaaS | C2: N/A | D2: GoDaddy, DigitalOcean, Amazon Web Services, Google Cloud Platform, Microsoft Azure
B4: PaaS | C4: N/A | D4: GoDaddy, Amazon Web Services, Google Cloud Platform, Microsoft Azure
A6: Combination of supporting assets, including HW, SW and people that provide a service to the organisation for the same business objective or activity. | B6: SaaS | C6: N/A
B8: Network | C8: N/A | D8: ADSL, RDSI
B10: Third system | C10: N/A
A12: Software | B12: Firmware | C12: N/A | D12: EBIOS, UEFI
B14: Middleware | C14: Operating systems | D14: Windows, Mac OS, Linux
C16: Web server | D16: Tomcat
C18: Virtualisation layer | D18: VMware
C19: Network stack | D19: Open SSL, TCP IP
A20: Programmes and applications of the target system related to the processing, transmission and storage of primary assets. | C20: Application server | D20: PHP server, net server mobile application server, J2EE, WebSphere Application Server (WAS)
C22: DBMS server | D22: Oracle MySQL SQL
B24: End-user | C24: In house developed
B25: Application
C26: COTS | D26: Outlook, SAP,
A27: Hardware | B27: Processing/ | C27: User device (portable) | D27: Laptop, netbook, tablet, smartphone, smartcard, token
B28: Storage
C29: User device (fixed) | D29: Desktop, workstation
A31: Physical elements part of the Target System used for the processing, transmission and storage of primary assets (data and functions/services). | C31: Shared device (fixed) | D31: Server, Multi-purpose Device (networked printer/copier/scanner with storage)
B33: Network | C33: Network equipment | D33: Repeater, hub, bridge, switch, router, Wifi Access Point, Firewall, Firewall IDS, IPS Antivirus
C38: Wired media | D38: PSTN twisted pair, copper cable, UTP, coaxial cable, fibre optic
C40: Wireless Media | D40: Wifi 802.11, BlueTooth, IR, Radio, satellite, ADSL
B42: Portable | C42: N/A
A44: People | B44: Decision maker | C44: N/A | D44: Project Manager
A45: People and roles that use the target system or are involved in the processing, transmission and storage of primary assets.
B46: Normal user | C46: N/A | D46: Final user
B48: Privileged user | C48: N/A | D48: Database operator, system administrator,
B50: Physical location | C50: N/A | D50: Offices, premises, secure zone, administrative zone, computer room
A51: Location
A54: Infrastructures, offices and other premises related to the geographical location of the hardware and software managed by the organisation. | B54: Utilities | C54: N/A | D54: Power supply, Water supply, HVAC, Waste disposal, light, Furniture, Equipment

Sheet HOME
D5: INDEX
D6: Process 1 | E6: System Security Characterisation
D7: Process 2 | E7: Primary asset identification
E8: Asset valuation (BIA)
D9: Process 3 | E9: Supporting assets
D10: Process 4 | E10: System modelling
D11: Processes 5-6-7 | E11: Risk calculation
D12: Aux | E12: AuxThreats
E13: Likelihood-Frequency tables
E14: Measures cat
E15: Measures Register
E16: Mitigation factors table
E17: Security measures catalogue
B21: Disclaimer:
B22: The information found on this spreadsheet is intended to be used as a tool to facilitate the Risk Assessment process
B23: using the IT Risk Management Methodology (ITSRM2).
B25: Cells in gray are computed fields, therefore, they should not be modified
B26: Aux tables are used for filtering/sort and they feed other sheets, so, they should not be modified
B27: Adding rows or columns to the tables could modified the computing of the next steps into the process, for this reason
B28: it is not recommended to do so.

Sheet P1-System
B8: Organisation description
C10: Organisation name | D10: Ministry of Interior, MS A
C11: Business Objective | D11: To provide and efficient data access services for authorized government agencies (G2G),ensuring availability,confeditiality,integrity of citizens' records for critical e-gov services
B14: System description
C16: System name | D16: Citizen Data Registry Access Service
C17: Main purpose / function | D17: Provide read access to citizen data records for authorised government agencies via secure web services
C18: Information handled | D18: Citizen records including Name,Surname, ID Number,Contact Details etc.
C19: Users population | D19: Authorised government agencies in Member State A
B22: Identification of relevant constraints
C24: Constraints for the risk treatment
C25: Time | D25: Six Months
C26: Financial
C27: Technical | D27: Deployment of dedicated application server for web services
C28: Environmental
C29: Legal | D29: Comply with GDPR and National data protection laws
C30: Ease of use
C31: Other
C32: Constraints for the organization
C33: Political nature
C34: Strategic nature
C35: Budgetary
C36: Technical
C37: Other
B40: Specific regulations
C42: GDPR/Commission Decision 45/2001 Personally identifiable information (PII) | D42: Yes
C43: GDPR/Commission Decision 45/2001 Sensitive personal information | D43: No
C44: EUCI Top secret, secret, confidential, restricted | D44: No
B47: Identification of roles
C49: System owner | D49: Directorate-General of Public Service
C50: Data owner | D50: Directorate-General of Digital Society
C51: Information Security Officer | D51: Advises on IT security measures and monitors compliance
C52: DPC | D52: Handles Data protection compliance and audits
C53: Other | D53: System Manager,System Supplier, IT Service Provider
B56: Other stakeholders
C58: User Group 1
C59: User Group 2
C60: User Group 3
C61: User Group 4
B64: Identification of Mandatory Security Measures
C66: Security Policies and Standards | D66: The ministry adheres to general information security policies to ensure confeditiality,intergrity and availability of data. These include access control,data encryption and monitoring in alignment with established security frameworks suchs as ISO/IEC 27001
C67: Applicable legislation on processing of Personal Data | D67: GDPR and Commision Decision 45/2001 govern the handling of personal data in the system,ensuring compliance with regulation on data protection, access control and secure processing
C68: Applicable legislation on processing of Classified Information

Sheet P2-Primary Assets
B4: Primary asset inventory
C6: ID | D6: Primary asset | E6: Type | F6: Description | G6: Owner | H6: Comments
C7: =IF(D7<>"",ROW()-6,"") -> 1 | D7: Citizen Data | E7: Data | F7: This dataset contains personal identifiable information (PII) of citizens | G7: Directorate-General of Digital Society
C8: =IF(D8<>"",ROW()-6,"") -> 2 | D8: Statistical Data | E8: Data | F8: Aggregated and anonymized demographic data derived from citizen records | G8: Directorate-General of Digital Society
C9: =IF(D9<>"",ROW()-6,"") -> 3 | D9: Read Access to Citizen Data | E9: Function | F9: This function enables authorized government agencies (G2G) to securely access individual citizen records as required by law. It ensures that access is limited to entities with proper authorization and safeguards the data's confidentiality, integrity, and availability | G9: Directorate-General of Public Services
C10: =IF(D10<>"",ROW()-6,"") -> 4 | D10: Provision of Statistical Data | E10: Function | F10: This function involves generating and delivering anonymized statistical data to the public (G2C) and businesses (G2B). It leverages citizen data to provide insights while protecting individual identities. | G10: Directorate-General of Public Services
C11: =IF(D11<>"",ROW()-6,"") -> 5 | D11: Access for Static information | E11: Function | F11: Public access to the Web Server for some static information - (G2C) | G11: Directorate-General of Public Services
C12: =IF(D12<>"",ROW()-6,"") -> 6 | D12: Read Access to Statistical Demographic Data | E12: Function | F12: Read access to statistical data provided only to authorized government agencies (required by law) - (G2G). | G12: Directorate-General of Digital Society
C13: =IF(D13<>"",ROW()-6,"")
C14: =IF(D14<>"",ROW()-6,"")
C15: =IF(D15<>"",ROW()-6,"")
C16: =IF(D16<>"",ROW()-6,"")
C17: =IF(D17<>"",ROW()-6,"")
C18: =IF(D18<>"",ROW()-6,"")
C19: =IF(D19<>"",ROW()-6,"")
C20: =IF(D20<>"",ROW()-6,"")
C21: =IF(D21<>"",ROW()-6,"")
C22: =IF(D22<>"",ROW()-6,"")
C23: =IF(D23<>"",ROW()-6,"")
C24: =IF(D24<>"",ROW()-6,"")
... C1004: =IF(D1004<>"",ROW()-6,"")

Sheet P2-Asset Valuation
G1: to fill
A4: Impact scenario | B4: Asset valuation: Business impact assessment (BIA)
C6: ID | D6: Impact scenario description | E6: Primary asset | F6: Dimension | G6: Impact type | H6: Effect | I6: Asset Value | J6: Code | K6: Value | L6: Potential adversary (Threat agent) | M6: Identified Potential Adversary | N6: Power | O6: Interest level | P6: Interest | Q6: Attractiveness | R6: Comments
C7: =IF(E7<>"",CONCATENATE("Bav",TEXT(ROW()-6,"000"),""),"") -> Bav001 | E7: Citizens' data | F7: Confidentiality | G7: Infringement of Laws and regulation | H7: Internal legal consequences that include fines and economic penalties for the EC | I7: =K7 -> 4 | J7: =IFERROR(VLOOKUP(G7,'Auxiliary data'!$B$96:$C$107,2,0),"") -> IT.LawReg | K7: =IFERROR(VLOOKUP(H7,'Auxiliary data'!$B$111:$C$212,2,0),"") -> 4 | L7: Cybercriminals | N7: =IFERROR(VLOOKUP(L7,'Auxiliary data'!$B$216:$C$224,2,0),"") -> 4 | O7: Low | P7: =IFERROR(VLOOKUP(O7,'Auxiliary data'!$B$228:$C$230,2,0),"") -> 1 | Q7: =IFERROR(N7+P7,"") -> 5
C8: =IF(E8<>"",CONCATENATE("Bav",TEXT(ROW()-6,"000"),""),"") -> Bav002 | E8: Providing citizen's data to third parties | F8: Availability | G8: Disruption of activities | H8: Is likely to cause disruption to activities within the EC and with impact on other organisations | I8: =K8 -> 5 | J8: =IFERROR(VLOOKUP(G8,'Auxiliary data'!$B$96:$C$107,2,0),"") -> IT.DisAct | K8: =IFERROR(VLOOKUP(H8,'Auxiliary data'!$B$111:$C$212,2,0),"") -> 5 | L8: Hacktivists | N8: =IFERROR(VLOOKUP(L8,'Auxiliary data'!$B$216:$C$224,2,0),"") -> 2 | O8: Medium | P8: =IFERROR(VLOOKUP(O8,'Auxiliary data'!$B$228:$C$230,2,0),"") -> 3 | Q8: =IFERROR(N8+P8,"") -> 5
C9: =IF(E9<>"",CONCATENATE("Bav",TEXT(ROW()-6,"000"),""),"") -> Bav003 | E9: TEst3 | I9: =K9 | J9: =IFERROR(VLOOKUP(G9,'Auxiliary data'!$B$96:$C$107,2,0),"") | K9: =IFERROR(VLOOKUP(H9,'Auxiliary data'!$B$111:$C$212,2,0),"") | N9: =IFERROR(VLOOKUP(L9,'Auxiliary data'!$B$216:$C$224,2,0),"") | P9: =IFERROR(VLOOKUP(O9,'Auxiliary data'!$B$228:$C$230,2,0),"") | Q9: =IFERROR(N9+P9,"")
C10: =IF(E10<>"",CONCATENATE("Bav",TEXT(ROW()-6,"000"),""),"") | I10: =K10 | J10: =IFERROR(VLOOKUP(G10,'Auxiliary data'!$B$96:$C$107,2,0),"") | K10: =IFERROR(VLOOKUP(H10,'Auxiliary data'!$B$111:$C$212,2,0),"") | N10: =IFERROR(VLOOKUP(L10,'Auxiliary data'!$B$216:$C$224,2,0),"") | P10: =IFERROR(VLOOKUP(O10,'Auxiliary data'!$B$228:$C$230,2,0),"") | Q10: =IFERROR(N10+P10,"")
C11: =IF(E11<>"",CONCATENATE("Bav",TEXT(ROW()-6,"000"),""),"") | I11: =K11 | J11: =IFERROR(VLOOKUP(G11,'Auxiliary data'!$B$96:$C$107,2,0),"") | K11: =IFERROR(VLOOKUP(H11,'Auxiliary data'!$B$111:$C$212,2,0),"") | N11: =IFERROR(VLOOKUP(L11,'Auxiliary data'!$B$216:$C$224,2,0),"") | P11: =IFERROR(VLOOKUP(O11,'Auxiliary data'!$B$228:$C$230,2,0),"") | Q11: =IFERROR(N11+P11,"")
C12: =IF(E12<>"",CONCATENATE("Bav",TEXT(ROW()-6,"000"),""),"") | I12: =K12 | J12: =IFERROR(VLOOKUP(G12,'Auxiliary data'!$B$96:$C$107,2,0),"") | K12: =IFERROR(VLOOKUP(H12,'Auxiliary data'!$B$111:$C$212,2,0),"") | N12: =IFERROR(VLOOKUP(L12,'Auxiliary data'!$B$216:$C$224,2,0),"") | P12: =IFERROR(VLOOKUP(O12,'Auxiliary data'!$B$228:$C$230,2,0),"") | Q12: =IFERROR(N12+P12,"")
C13: =IF(E13<>"",CONCATENATE("Bav",TEXT(ROW()-6,"000"),""),"") | I13: =K13 | J13: =IFERROR(VLOOKUP(G13,'Auxiliary data'!$B$96:$C$107,2,0),"") | K13: =IFERROR(VLOOKUP(H13,'Auxiliary data'!$B$111:$C$212,2,0),"") | N13: =IFERROR(VLOOKUP(L13,'Auxiliary data'!$B$216:$C$224,2,0),"") | P13: =IFERROR(VLOOKUP(O13,'Auxiliary data'!$B$228:$C$230,2,0),"") | Q13: =IFERROR(N13+P13,"")
C14: =IF(E14<>"",CONCATENATE("Bav",TEXT(ROW()-6,"000"),""),"") | I14: =K14 | J14: =IFERROR(VLOOKUP(G14,'Auxiliary data'!$B$96:$C$107,2,0),"") | K14: =IFERROR(VLOOKUP(H14,'Auxiliary data'!$B$111:$C$212,2,0),"") | N14: =IFERROR(VLOOKUP(L14,'Auxiliary data'!$B$216:$C$224,2,0),"") | P14: =IFERROR(VLOOKUP(O14,'Auxiliary data'!$B$228:$C$230,2,0),"") | Q14: =IFERROR(N14+P14,"")
C15: =IF(E15<>"",CONCATENATE("Bav",TEXT(ROW()-6,"000"),""),"") | I15: =K15 | J15: =IFERROR(VLOOKUP(G15,'Auxiliary data'!$B$96:$C$107,2,0),"") | K15: =IFERROR(VLOOKUP(H15,'Auxiliary data'!$B$111:$C$212,2,0),"") | N15: =IFERROR(VLOOKUP(L15,'Auxiliary data'!$B$216:$C$224,2,0),"") | P15: =IFERROR(VLOOKUP(O15,'Auxiliary data'!$B$228:$C$230,2,0),"") | Q15: =IFERROR(N15+P15,"")
C16: =IF(E16<>"",CONCATENATE("Bav",TEXT(ROW()-6,"000"),""),"") | I16: =K16 | J16: =IFERROR(VLOOKUP(G16,'Auxiliary data'!$B$96:$C$107,2,0),"") | K16: =IFERROR(VLOOKUP(H16,'Auxiliary data'!$B$111:$C$212,2,0),"") | N16: =IFERROR(VLOOKUP(L16,'Auxiliary data'!$B$216:$C$224,2,0),"") | P16: =IFERROR(VLOOKUP(O16,'Auxiliary data'!$B$228:$C$230,2,0),"") | Q16: =IFERROR(N16+P16,"")
C17: =IF(E17<>"",CONCATENATE("Bav",TEXT(ROW()-6,"000"),""),"") | I17: =K17 | J17: =IFERROR(VLOOKUP(G17,'Auxiliary data'!$B$96:$C$107,2,0),"") | K17: =IFERROR(VLOOKUP(H17,'Auxiliary data'!$B$111:$C$212,2,0),"") | N17: =IFERROR(VLOOKUP(L17,'Auxiliary data'!$B$216:$C$224,2,0),"") | P17: =IFERROR(VLOOKUP(O17,'Auxiliary data'!$B$228:$C$230,2,0),"") | Q17: =IFERROR(N17+P17,"")
C18: =IF(E18<>"",CONCATENATE("Bav",TEXT(ROW()-6,"000"),""),"") | I18: =K18 | J18: =IFERROR(VLOOKUP(G18,'Auxiliary data'!$B$96:$C$107,2,0),"") | K18: =IFERROR(VLOOKUP(H18,'Auxiliary data'!$B$111:$C$212,2,0),"") | N18: =IFERROR(VLOOKUP(L18,'Auxiliary data'!$B$216:$C$224,2,0),"") | P18: =IFERROR(VLOOKUP(O18,'Auxiliary data'!$B$228:$C$230,2,0),"") | Q18: =IFERROR(N18+P18,"")
C19: =IF(E19<>"",CONCATENATE("Bav",TEXT(ROW()-6,"000"),""),"") | I19: =K19 | J19: =IFERROR(VLOOKUP(G19,'Auxiliary data'!$B$96:$C$107,2,0),"") | K19: =IFERROR(VLOOKUP(H19,'Auxiliary data'!$B$111:$C$212,2,0),"") | N19: =IFERROR(VLOOKUP(L19,'Auxiliary data'!$B$216:$C$224,2,0),"") | P19: =IFERROR(VLOOKUP(O19,'Auxiliary data'!$B$228:$C$230,2,0),"") | Q19: =IFERROR(N19+P19,"")
C20: =IF(E20<>"",CONCATENATE("Bav",TEXT(ROW()-6,"000"),""),"") | I20: =K20 | J20: =IFERROR(VLOOKUP(G20,'Auxiliary data'!$B$96:$C$107,2,0),"") | K20: =IFERROR(VLOOKUP(H20,'Auxiliary data'!$B$111:$C$212,2,0),"") | N20: =IFERROR(VLOOKUP(L20,'Auxiliary data'!$B$216:$C$224,2,0),"") | P20: =IFERROR(VLOOKUP(O20,'Auxiliary data'!$B$228:$C$230,2,0),"") | Q20: =IFERROR(N20+P20,"")
C21: =IF(E21<>"",CONCATENATE("Bav",TEXT(ROW()-6,"000"),""),"") | I21: =K21 | J21: =IFERROR(VLOOKUP(G21,'Auxiliary data'!$B$96:$C$107,2,0),"") | K21: =IFERROR(VLOOKUP(H21,'Auxiliary data'!$B$111:$C$212,2,0),"") | N21: =IFERROR(VLOOKUP(L21,'Auxiliary data'!$B$216:$C$224,2,0),"") | P21: =IFERROR(VLOOKUP(O21,'Auxiliary data'!$B$228:$C$230,2,0),"") | Q21: =IFERROR(N21+P21,"")
... C1006: =IF(E1006<>"",CONCATENATE("Bav",TEXT(ROW()-6,"000"),""),"") | I1006: =K1006 | J1006: =IFERROR(VLOOKUP(G1006,'Auxiliary data'!$B$96:$C$107,2,0),"") | K1006: =IFERROR(VLOOKUP(H1006,'Auxiliary data'!$B$111:$C$212,2,0),"") | N1006: =IFERROR(VLOOKUP(L1006,'Auxiliary data'!$B$216:$C$224,2,0),"") | P1006: =IFERROR(VLOOKUP(O1006,'Auxiliary data'!$B$228:$C$230,2,0),"") | Q1006: =IFERROR(N1006+P1006,"")

Sheet P2-Asset Valuation (Manual)
B4: Asset valuation: Manual
C6: ID | D6: Description | E6: Primary asset | F6: Dimension | G6: Asset value
C7: =IF(E7<>"",CONCATENATE("Mav",TEXT(ROW()-6,"000"),""),"") -> Mav001 | E7: Citizen Data | F7: Confidentiality | G7: High
C8: =IF(E8<>"",CONCATENATE("Mav",TEXT(ROW()-6,"000"),""),"") -> Mav002 | E8: Citizen Data | F8: Integrity | G8: High
C9: =IF(E9<>"",CONCATENATE("Mav",TEXT(ROW()-6,"000"),""),"") -> Mav003 | E9: Citizen Data | F9: Availability | G9: High
C10: =IF(E10<>"",CONCATENATE("Mav",TEXT(ROW()-6,"000"),""),"") -> Mav004 | E10: Statistical Data | F10: Confidentiality | G10: Medium
C11: =IF(E11<>"",CONCATENATE("Mav",TEXT(ROW()-6,"000"),""),"") -> Mav005 | E11: Statistical Data | F11: Integrity | G11: Medium
C12: =IF(E12<>"",CONCATENATE("Mav",TEXT(ROW()-6,"000"),""),"") -> Mav006 | E12: Statistical Data | F12: Availability | G12: Medium
C13: =IF(E13<>"",CONCATENATE("Mav",TEXT(ROW()-6,"000"),""),"") -> Mav007 | E13: Read Access to Citizen Data | F13: Confidentiality | G13: High
C14: =IF(E14<>"",CONCATENATE("Mav",TEXT(ROW()-6,"000"),""),"") -> Mav008 | E14: Read Access to Citizen Data | F14: Integrity | G14: High
C15: =IF(E15<>"",CONCATENATE("Mav",TEXT(ROW()-6,"000"),""),"") -> Mav009 | E15: Read Access to Citizen Data | F15: Availability | G15: High
C16: =IF(E16<>"",CONCATENATE("Mav",TEXT(ROW()-6,"000"),""),"") -> Mav010 | E16: Provision of Statistical Data | F16: Confidentiality | G16: Low
C17: =IF(E17<>"",CONCATENATE("Mav",TEXT(ROW()-6,"000"),""),"") -> Mav011 | E17: Provision of Statistical Data | F17: Integrity | G17: Medium
C18: =IF(E18<>"",CONCATENATE("Mav",TEXT(ROW()-6,"000"),""),"") -> Mav012 | E18: Provision of Statistical Data | F18: Availability | G18: Medium
... C24: =IF(E24<>"",CONCATENATE("Mav",TEXT(ROW()-6,"000"),""),"") -> Mav018 | E24: Read Access to Statistical Demographic Data | F24: Availability | G24: Low
C25: =IF(E25<>"",CONCATENATE("Mav",TEXT(ROW()-6,"000"),""),"")
C26: =IF(E26<>"",CONCATENATE("Mav",TEXT(ROW()-6,"000"),""),"")
C27: =IF(E27<>"",CONCATENATE("Mav",TEXT(ROW()-6,"000"),""),"")
C28: =IF(E28<>"",CONCATENATE("Mav",TEXT(ROW()-6,"000"),""),"")
C29: =IF(E29<>"",CONCATENATE("Mav",TEXT(ROW()-6,"000"),""),"")
C30: =IF(E30<>"",CONCATENATE("Mav",TEXT(ROW()-6,"000"),""),"")
C31: =IF(E31<>"",CONCATENATE("Mav",TEXT(ROW()-6,"000"),""),"")
C32: =IF(E32<>"",CONCATENATE("Mav",TEXT(ROW()-6,"000"),""),"")
C33: =IF(E33<>"",CONCATENATE("Mav",TEXT(ROW()-6,"000"),""),"")
C34: =IF(E34<>"",CONCATENATE("Mav",TEXT(ROW()-6,"000"),""),"")
C35: =IF(E35<>"",CONCATENATE("Mav",TEXT(ROW()-6,"000"),""),"")
C36: =IF(E36<>"",CONCATENATE("Mav",TEXT(ROW()-6,"000"),""),"")
... C1007: =IF(E1007<>"",CONCATENATE("Mav",TEXT(ROW()-6,"000"),""),"")

Sheet P2-PA Attractiveness
B4: PA Attractiveness: Interest scenarios
C6: ID | D6: Description | E6: Primary asset | F6: Dimension | G6: Interest level | H6: Potential adversary (Threat agent) | I6: Power | J6: Atractiveness | K6: Interest level value
C7: =IF(E7<>"",CONCATENATE("Att",TEXT(ROW()-6,"000"),""),"") -> Att001 | E7: Citizen Data | F7: Confidentiality | G7: High | H7: Cybercriminals | I7: =IFERROR(VLOOKUP(H7,'Auxiliary data'!$B$216:$C$224,2,0),"") -> 4 | J7: =IFERROR(IF(AND(K7<>"",I7<>""),SUM(I7,K7),""),"") -> 9 | K7: =IFERROR(VLOOKUP(G7,'Auxiliary data'!$B$228:$C$230,2,0),"") -> 5
C8: =IF(E8<>"",CONCATENATE("Att",TEXT(ROW()-6,"000"),""),"") -> Att002 | E8: Citizen Data | F8: Confidentiality | G8: High | H8: Partner / Contractor | I8: =IFERROR(VLOOKUP(H8,'Auxiliary data'!$B$216:$C$224,2,0),"") -> 5 | J8: =IFERROR(IF(AND(K8<>"",I8<>""),SUM(I8,K8),""),"") -> 10 | K8: =IFERROR(VLOOKUP(G8,'Auxiliary data'!$B$228:$C$230,2,0),"") -> 5
C9: =IF(E9<>"",CONCATENATE("Att",TEXT(ROW()-6,"000"),""),"") -> Att003 | E9: Citizen Data | F9: Integrity | G9: High | H9: Privileged insider | I9: =IFERROR(VLOOKUP(H9,'Auxiliary data'!$B$216:$C$224,2,0),"") -> 5 | J9: =IFERROR(IF(AND(K9<>"",I9<>""),SUM(I9,K9),""),"") -> 10 | K9: =IFERROR(VLOOKUP(G9,'Auxiliary data'!$B$228:$C$230,2,0),"") -> 5
C10: =IF(E10<>"",CONCATENATE("Att",TEXT(ROW()-6,"000"),""),"") -> Att004 | E10: Citizen Data | F10: Availability | G10: High | H10: Privileged insider | I10: =IFERROR(VLOOKUP(H10,'Auxiliary data'!$B$216:$C$224,2,0),"") -> 5 | J10: =IFERROR(IF(AND(K10<>"",I10<>""),SUM(I10,K10),""),"") -> 10 | K10: =IFERROR(VLOOKUP(G10,'Auxiliary data'!$B$228:$C$230,2,0),"") -> 5
C11: =IF(E11<>"",CONCATENATE("Att",TEXT(ROW()-6,"000"),""),"") -> Att005 | E11: Statistical Data | F11: Confidentiality | G11: Medium | H11: Privileged insider | I11: =IFERROR(VLOOKUP(H11,'Auxiliary data'!$B$216:$C$224,2,0),"") -> 5 | J11: =IFERROR(IF(AND(K11<>"",I11<>""),SUM(I11,K11),""),"") -> 8 | K11: =IFERROR(VLOOKUP(G11,'Auxiliary data'!$B$228:$C$230,2,0),"") -> 3
C12: =IF(E12<>"",CONCATENATE("Att",TEXT(ROW()-6,"000"),""),"") -> Att006 | E12: Statistical Data | F12: Confidentiality | G12: Medium | H12: Hacktivists | I12: =IFERROR(VLOOKUP(H12,'Auxiliary data'!$B$216:$C$224,2,0),"") -> 2 | J12: =IFERROR(IF(AND(K12<>"",I12<>""),SUM(I12,K12),""),"") -> 5 | K12: =IFERROR(VLOOKUP(G12,'Auxiliary data'!$B$228:$C$230,2,0),"") -> 3
C13: =IF(E13<>"",CONCATENATE("Att",TEXT(ROW()-6,"000"),""),"") -> Att007 | E13: Statistical Data | F13: Confidentiality | G13: Medium | H13: Cybercriminals | I13: =IFERROR(VLOOKUP(H13,'Auxiliary data'!$B$216:$C$224,2,0),"") -> 4 | J13: =IFERROR(IF(AND(K13<>"",I13<>""),SUM(I13,K13),""),"") -> 7 | K13: =IFERROR(VLOOKUP(G13,'Auxiliary data'!$B$228:$C$230,2,0),"") -> 3
C14: =IF(E14<>"",CONCATENATE("Att",TEXT(ROW()-6,"000"),""),"") -> Att008 | E14: Statistical Data | F14: Integrity | G14: Medium | H14: Hacktivists | I14: =IFERROR(VLOOKUP(H14,'Auxiliary data'!$B$216:$C$224,2,0),"") -> 2 | J14: =IFERROR(IF(AND(K14<>"",I14<>""),SUM(I14,K14),""),"") -> 5 | K14: =IFERROR(VLOOKUP(G14,'Auxiliary data'!$B$228:$C$230,2,0),"") -> 3
C15: =IF(E15<>"",CONCATENATE("Att",TEXT(ROW()-6,"000"),""),"") -> Att009 | E15: Statistical Data | F15: Availability | G15: Medium | H15: Cybercriminals | I15: =IFERROR(VLOOKUP(H15,'Auxiliary data'!$B$216:$C$224,2,0),"") -> 4 | J15: =IFERROR(IF(AND(K15<>"",I15<>""),SUM(I15,K15),""),"") -> 7 | K15: =IFERROR(VLOOKUP(G15,'Auxiliary data'!$B$228:$C$230,2,0),"") -> 3
C16: =IF(E16<>"",CONCATENATE("Att",TEXT(ROW()-6,"000"),""),"") -> Att010 | E16: Read Access to Citizen Data | F16: Confidentiality | G16: High | H16: Privileged insider | I16: =IFERROR(VLOOKUP(H16,'Auxiliary data'!$B$216:$C$224,2,0),"") -> 5 | J16: =IFERROR(IF(AND(K16<>"",I16<>""),SUM(I16,K16),""),"") -> 10 | K16: =IFERROR(VLOOKUP(G16,'Auxiliary data'!$B$228:$C$230,2,0),"") -> 5
C17: =IF(E17<>"",CONCATENATE("Att",TEXT(ROW()-6,"000"),""),"") -> Att011 | E17: Read Access to Citizen Data | F17: Integrity | G17: Medium | H17: Privileged insider | I17: =IFERROR(VLOOKUP(H17,'Auxiliary data'!$B$216:$C$224,2,0),"") -> 5 | J17: =IFERROR(IF(AND(K17<>"",I17<>""),SUM(I17,K17),""),"") -> 8 | K17: =IFERROR(VLOOKUP(G17,'Auxiliary data'!$B$228:$C$230,2,0),"") -> 3
C18: =IF(E18<>"",CONCATENATE("Att",TEXT(ROW()-6,"000"),""),"") -> Att012 | E18: Read Access to Citizen Data | F18: Availability | G18: High | H18: Privileged insider | I18: =IFERROR(VLOOKUP(H18,'Auxiliary data'!$B$216:$C$224,2,0),"") -> 5 | J18: =IFERROR(IF(AND(K18<>"",I18<>""),SUM(I18,K18),""),"") -> 10 | K18: =IFERROR(VLOOKUP(G18,'Auxiliary data'!$B$228:$C$230,2,0),"") -> 5
... C32: =IF(E32<>"",CONCATENATE("Att",TEXT(ROW()-6,"000"),""),"") -> Att026 | E32: Read Access to Statistical Demographic Data | F32: Availability | G32: Medium | H32: Cybercriminals | I32: =IFERROR(VLOOKUP(H32,'Auxiliary data'!$B$216:$C$224,2,0),"") -> 4 | J32: =IFERROR(IF(AND(K32<>"",I32<>""),SUM(I32,K32),""),"") -> 7 | K32: =IFERROR(VLOOKUP(G32,'Auxiliary data'!$B$228:$C$230,2,0),"") -> 3
C33: =IF(E33<>"",CONCATENATE("Att",TEXT(ROW()-6,"000"),""),"") | I33: =IFERROR(VLOOKUP(H33,'Auxiliary data'!$B$216:$C$224,2,0),"") | J33: =IFERROR(IF(AND(K33<>"",I33<>""),SUM(I33,K33),""),"") | K33: =IFERROR(VLOOKUP(G33,'Auxiliary data'!$B$228:$C$230,2,0),"")
C34: =IF(E34<>"",CONCATENATE("Att",TEXT(ROW()-6,"000"),""),"") | I34: =IFERROR(VLOOKUP(H34,'Auxiliary data'!$B$216:$C$224,2,0),"") | J34: =IFERROR(IF(AND(K34<>"",I34<>""),SUM(I34,K34),""),"") | K34: =IFERROR(VLOOKUP(G34,'Auxiliary data'!$B$228:$C$230,2,0),"")
C35: =IF(E35<>"",CONCATENATE("Att",TEXT(ROW()-6,"000"),""),"") | I35: =IFERROR(VLOOKUP(H35,'Auxiliary data'!$B$216:$C$224,2,0),"") | J35: =IFERROR(IF(AND(K35<>"",I35<>""),SUM(I35,K35),""),"") | K35: =IFERROR(VLOOKUP(G35,'Auxiliary data'!$B$228:$C$230,2,0),"")
C36: =IF(E36<>"",CONCATENATE("Att",TEXT(ROW()-6,"000"),""),"") | I36: =IFERROR(VLOOKUP(H36,'Auxiliary data'!$B$216:$C$224,2,0),"") | J36: =IFERROR(IF(AND(K36<>"",I36<>""),SUM(I36,K36),""),"") | K36: =IFERROR(VLOOKUP(G36,'Auxiliary data'!$B$228:$C$230,2,0),"")
C37: =IF(E37<>"",CONCATENATE("Att",TEXT(ROW()-6,"000"),""),"") | I37: =IFERROR(VLOOKUP(H37,'Auxiliary data'!$B$216:$C$224,2,0),"") | J37: =IFERROR(IF(AND(K37<>"",I37<>""),SUM(I37,K37),""),"") | K37: =IFERROR(VLOOKUP(G37,'Auxiliary data'!$B$228:$C$230,2,0),"")
C38: =IF(E38<>"",CONCATENATE("Att",TEXT(ROW()-6,"000"),""),"") | I38: =IFERROR(VLOOKUP(H38,'Auxiliary data'!$B$216:$C$224,2,0),"") | J38: =IFERROR(IF(AND(K38<>"",I38<>""),SUM(I38,K38),""),"") | K38: =IFERROR(VLOOKUP(G38,'Auxiliary data'!$B$228:$C$230,2,0),"")
C39: =IF(E39<>"",CONCATENATE("Att",TEXT(ROW()-6,"000"),""),"") | I39: =IFERROR(VLOOKUP(H39,'Auxiliary data'!$B$216:$C$224,2,0),"") | J39: =IFERROR(IF(AND(K39<>"",I39<>""),SUM(I39,K39),""),"") | K39: =IFERROR(VLOOKUP(G39,'Auxiliary data'!$B$228:$C$230,2,0),"")
C40: =IF(E40<>"",CONCATENATE("Att",TEXT(ROW()-6,"000"),""),"") | I40: =IFERROR(VLOOKUP(H40,'Auxiliary data'!$B$216:$C$224,2,0),"") | J40: =IFERROR(IF(AND(K40<>"",I40<>""),SUM(I40,K40),""),"") | K40: =IFERROR(VLOOKUP(G40,'Auxiliary data'!$B$228:$C$230,2,0),"")
C41: =IF(E41<>"",CONCATENATE("Att",TEXT(ROW()-6,"000"),""),"") | I41: =IFERROR(VLOOKUP(H41,'Auxiliary data'!$B$216:$C$224,2,0),"") | J41: =IFERROR(IF(AND(K41<>"",I41<>""),SUM(I41,K41),""),"") | K41: =IFERROR(VLOOKUP(G41,'Auxiliary data'!$B$228:$C$230,2,0),"")
C42: =IF(E42<>"",CONCATENATE("Att",TEXT(ROW()-6,"000"),""),"") | I42: =IFERROR(VLOOKUP(H42,'Auxiliary data'!$B$216:$C$224,2,0),"") | J42: =IFERROR(IF(AND(K42<>"",I42<>""),SUM(I42,K42),""),"") | K42: =IFERROR(VLOOKUP(G42,'Auxiliary data'!$B$228:$C$230,2,0),"")
C43: =IF(E43<>"",CONCATENATE("Att",TEXT(ROW()-6,"000"),""),"") | I43: =IFERROR(VLOOKUP(H43,'Auxiliary data'!$B$216:$C$224,2,0),"") | J43: =IFERROR(IF(AND(K43<>"",I43<>""),SUM(I43,K43),""),"") | K43: =IFERROR(VLOOKUP(G43,'Auxiliary data'!$B$228:$C$230,2,0),"")
C44: =IF(E44<>"",CONCATENATE("Att",TEXT(ROW()-6,"000"),""),"") | I44: =IFERROR(VLOOKUP(H44,'Auxiliary data'!$B$216:$C$224,2,0),"") | J44: =IFERROR(IF(AND(K44<>"",I44<>""),SUM(I44,K44),""),"") | K44: =IFERROR(VLOOKUP(G44,'Auxiliary data'!$B$228:$C$230,2,0),"")
... C1001: =IF(E1001<>"",CONCATENATE("Att",TEXT(ROW()-6,"000"),""),"") | I1001: =IFERROR(VLOOKUP(H1001,'Auxiliary data'!$B$216:$C$224,2,0),"") | J1001: =IFERROR(IF(AND(K1001<>"",I1001<>""),SUM(I1001,K1001),""),"") | K1001: =IFERROR(VLOOKUP(G1001,'Auxiliary data'!$B$228:$C$230,2,0),"")
C1002: =IF(E1002<>"",CONCATENATE("Att",TEXT(ROW()-6,"000"),""),"") | I1002: =IFERROR(VLOOKUP(H1002,'Auxiliary data'!$B$216:$C$224,2,0),"") | J1002: =IFERROR(IF(AND(K1002<>"",I1002<>""),AVERAGE(I1002,K1002),""),"") | K1002: =IFERROR(VLOOKUP(G1002,'Auxiliary data'!$B$228:$C$230,2,0),"")

Sheet P2-Primary asset summary
B4: Primary Asset Summary
C6: ID | D6: Primary | E6: Dimension | F6: Asset value | G6: Method | H6: Attractiveness
C7: =IF(D7<>"",CONCATENATE("Pas",TEXT(ROW()-6,"000"),""),"") -> Pas001 | D7: Sensitive information | E7: Confidentiality | G7: BIA asset valuation
C8: =IF(D8<>"",CONCATENATE("Pas",TEXT(ROW()-6,"000"),""),"")
C9: =IF(D9<>"",CONCATENATE("Pas",TEXT(ROW()-6,"000"),""),"")
C10: =IF(D10<>"",CONCATENATE("Pas",TEXT(ROW()-6,"000"),""),"")
C11: =IF(D11<>"",CONCATENATE("Pas",TEXT(ROW()-6,"000"),""),"")
C12: =IF(D12<>"",CONCATENATE("Pas",TEXT(ROW()-6,"000"),""),"")
C13: =IF(D13<>"",CONCATENATE("Pas",TEXT(ROW()-6,"000"),""),"")
C14: =IF(D14<>"",CONCATENATE("Pas",TEXT(ROW()-6,"000"),""),"")
C15: =IF(D15<>"",CONCATENATE("Pas",TEXT(ROW()-6,"000"),""),"")
C16: =IF(D16<>"",CONCATENATE("Pas",TEXT(ROW()-6,"000"),""),"")
C17: =IF(D17<>"",CONCATENATE("Pas",TEXT(ROW()-6,"000"),""),"")
C18: =IF(D18<>"",CONCATENATE("Pas",TEXT(ROW()-6,"000"),""),"")
C19: =IF(D19<>"",CONCATENATE("Pas",TEXT(ROW()-6,"000"),""),"")
... C1007: =IF(D1007<>"",CONCATENATE("Pas",TEXT(ROW()-6,"000"),""),"")

Sheet Auxiliary data
B4: Aux Table 1
B5: Value | C5: Label
B6: 1 | C6: Very Low
B7: 2 | C7: Low
B8: 3 | C8: Medium
B9: 4 | C9: High
B10: 5 | C10: Very High
B12: Aux Table 2
B13: Label | C13: Value
B14: Very Low | C14: 1
B15: Low | C15: 2
B16: Medium | C16: 3
B17: High | C17: 4
B18: Very High | C18: 5
B20: Aux Table 3
B21: P.A. type
B22: Data
B23: Function
B25: Aux Table 4
B26: PA-SA Relation
B27: Store
B28: Process
B29: Transmit
B94: Aux table 8
B95: Impact type | C95: Code
B96: Financial loss (in %age of EC budget) | C96: IT.FinLoss | D96: < 0.001% | E96: 0.001% to 0.01% | F96: 0.01% to 0.05% | G96: 0.05% to 0.5% | H96: 0.5% to 2% | I96: 2% to 5% | J96: 5% to 30% | K96: 30% to 200% | L96: 200% to 1000% | M96: > 1000%
B97: Financial loss (based on 3.5G€ functioning budget of the EC) | C97: IT.FinLossEC | D97: < 50.000€ | E97: 50.000€ to 500.000€ | F97: 500.000€ to 2M€ | G97: 2M€ to 20M€ | H97: 20M€ to 100M€ | I97: 100M€ to 250M€ | J97: 250M€ to 1.5G€ | K97: 1.5G€ to 10G€ | L97: 10G€ to 50G€ | M97: > 50G€
B98: Delay in political decision / execution | C98: IT.DelPol | D98: One week or negligible delay | E98: Two weeks delay | F98: One month or moderate delay | G98: Two months delay | H98: 4 months delay | I98: Six months or significant delay | J98: One year delay | K98: Two years delay | L98: Four years delay | M98: Abandoned execution
B99: Damage political relations | C99: IT.DamPol | D99: Negligible damage to relations with Commission's partners. | E99: Moderate damage to relations with Commission's partners | F99: Consequential damage to political relation with Commission's partners | G99: Significant damages adversely affecting relations with Commission's partners | H99: Serious damages to relations with Commission's partners | I99: Significant damages affecting political relations in Member States | J99: Serious; raise tension or formal protest in some Member States | K99: Serious; raise tension or formal protest in several Member States | L99: Exceptionally grave; raise tension or formal protest in the EU and with others countries. | M99: would result in termination of relations between EU commission and member state or strategic alliance partner
B100: Result in critical intervention at political level (Council/Parliament) regarding the Commission's performance | C100: IT.PolInt | D100: Minimum intervention | E100: Minimum intervention with some resolution via alternative routine operations | F100: Moderate intervention | G100: Moderate intervention with substantial resolution via alternative routine operations | H100: Consequential, affects execution of political decisions | I100: Significant or impede important executions | J100: Serious, disrupt execution(s) | K100: Serious, disrupt execution(s) with disablement of execution of political decisions | L100: Exceptionally grave, abort critical execution(s) | M100: Stopping significant number of execution(s) with disablement of execution of political decisions
B101: Degradation of the Commission services (delayed delivery, %age of expected time) | C101: IT.DegServ | D101: 1% delay | E101: 10% delay | F101: 25% delay | G101: 50% delay
B102: Disruption of activities | C102: IT.DisAct | D102: Could cause disruption to activities within the EC | E102: Is likely to cause disruption to activities within the EC | F102: Is likely to cause disruption to activities within the EC and with impact on other organisations | G102: Is likely to have some impact to other organizations | H102: Is likely to cause major impact on other organisations | I102: Is likely to cause a serious impact on other organizations
B103: Damage to health and safety | C103: IT.HealSafe | D103: Minor injury(ies) to one individual | E103: Minor injury(ies) to some individuals | F103: More than minor injuries to several individuals | G103: Injuries to several individuals | H103: Major injuries or widespread injuries | I103: Life of individual(s) threatened | J103: Death of one individual | K103: Death of several individuals | L103: Permanent incapacitating injury or illness to many individuals that may lead to widespread loss of life | M103: Widespread loss of life
B104: Damage to Staff morale and productivity | C104: IT.MorProd | D104: Negligible damage to staff morale and productivity | E104: Minimum | F104: Moderate | G104: Consequential | H104: Significant | I104: Adversely affected | J104: Serious loss | K104: Complete loss
B105: Damage Organisation image and reputation | C105: IT.ImaRep | D105: Negligible damage to image and reputation | E105: Moderate negative publicity, limited to local/specific public | F105: Consequential, limited to local/specific public | G105: Moderate negative publicity, to public | H105: Consequential or limited to 3 EU countries | I105: Significant or limited to 5 EU countries | J105: More than serious, Europe wide or worldwide negative publ.
B106: Damage to Public Order | C106: IT.PubOrd | D106: negligible impact to public order, no disruption to community | E106: Limited or very localised protest | F106: Some alteration to public order | G106: Limited or very localised protest, endangering individual security or liberty | H106: Consequential, region wide protest, lightly injured people | I106: Demonstrations national effects or injured people | J106: Threaten stability | K106: Serious prejudice public order/extensive disruptions on national level | L106: Serious prejudice public order/extensive disruptions on several national levels | M106: widespread effects/ individual or loss of lifes
B107: Infringement of Laws and regulation | C107: IT.LawReg | D107: No relevant legal consequences for the EC | E107: No relevant legal consequences for the EC or third parties. | F107: Internal legal consequences for the EC | G107: Internal legal consequences that include fines and economic penalties for the EC | H107: Legal consequences that include sentences of imprisonment fo members of the EC | I107: Legal consequences that affect the formal constitution of the EC
B109: Aux table 9
B110: Description | C110: Value
B111: =D96 -> < 0.001% | C111: 1
B112: =E96 -> 0.001% to 0.01% | C112: 2
B113: =F96 -> 0.01% to 0.05% | C113: 3
B114: =G96 -> 0.05% to 0.5% | C114: 4
B115: =H96 -> 0.5% to 2% | C115: 5
B116: =I96 -> 2% to 5% | C116: 6
B117: =J96 -> 5% to 30% | C117: 7
B118: =K96 -> 30% to 200% | C118: 8
B119: =L96 -> 200% to 1000% | C119: 9
B120: =M96 -> > 1000% | C120: 10
B121: < 50.000€ | C121: 1
B122: 50.000€ to 500.000€ | C122: 2
B123: 500.000€ to 2M€ | C123: 3
B124: 2M€ to 20M€ | C124: 4
B125: 20M€ to 100M€ | C125: 5
B126: 100M€ to 250M€ | C126: 6
B127: 250M€ to 1.5G€ | C127: 7
B128: 1.5G€ to 10G€ | C128: 8
B129: 10G€ to 50G€ | C129: 9
B130: > 50G€ | C130: 10
B131: One week or negligible delay | C131: 1
B132: Two weeks delay | C132: 2
... B166: Is likely to cause disruption to activities within the EC | C166: 3
C167: 4
B168: Is likely to cause disruption to activities within the EC and with impact on other organisations | C168: 5
B169: Is likely to have some impact to other organizations | C169: 6
B170: Is likely to cause major impact on other organisations | C170: 7
B171: Is likely to cause a serious impact on other organizations | C171: 8
B172: Minor injury(ies) to one individual | C172: 1
B173: Minor injury(ies) to some individuals | C173: 2
B174: More than minor injuries to several individuals | C174: 3
B175: Injuries to several individuals | C175: 4
B176: Major injuries or widespread injuries | C176: 5
B177: Life of individual(s) threatened | C177: 6
B178: Death of one individual | C178: 7
B179: Death of several individuals | C179: 8
... B206: widespread effects/ individual or loss of lifes | C206: 10
B207: =D107 -> No relevant legal consequences for the EC | C207: 1
B208: =E107 -> No relevant legal consequences for the EC or third parties. | C208: 2
B209: =F107 -> Internal legal consequences for the EC | C209: 3
B210: =G107 -> Internal legal consequences that include fines and economic penalties for the EC | C210: 4
B211: =H107 -> Legal consequences that include sentences of imprisonment fo members of the EC | C211: 6
B212: =I107 -> Legal consequences that affect the formal constitution of the EC | C212: 7
B214: Aux table X
B215: Threat agents | C215: Power
B216: Nation States | C216: 5
B217: Cybercriminals | C217: 4
B218: Cyber terrorist | C218: 3
B219: Coorporations | C219: 3
B220: Hacktivists | C220: 2
B221: Script Kiddies | C221: 1
B222: Partner / Contractor | C222: 5
B223: Privileged insider | C223: 5
B224: Insider | C224: 3
B226: Aux table 10
B227: Motivation | C227: Value
B228: High | C228: 5
B229: Medium | C229: 3
B230: Low | C230: 1
B232: Aux table 11
B233: Relation | C233: Value
...

Sheet AuxSA
B5: Aux table 5
B6: Supporting assets | C6: Level 1
B7: Software | C7: SA1.SW
B8: Software Data | C8: SA1.SWD
B9: Hardware | C9: SA1.HW
B10: Personnel | C10: SA1.PEO
B11: IT Service | C11: SA1.Services
B12: Location /Installation | C12: SA1.FAC
B14: Aux table 6
B15: Supporting assets | C15: Level 2 | D15: Level 1
B16: Data Center | C16: SA2.DC | D16: IT Service
B17: Network services | C17: SA2.ServNet
B18: Cloud services | C18: SA2.Cloud
B19: Standard service | C19: SA2.Stand
B20: User defined service | C20: SA2.UserDef
B21: Data container | C21: SA2.DatCon | D21: Software Data
B22: Application data | C22: SA2.AppDat
B23: Security data | C23: SA2.SecDat
B24: Firmware | C24: SA2.Firm | D24: Software
B25: Middleware | C25: SA2.Middle
B26: End-user application | C26: SA2.EUAPP
B27: End-point | C27: SA2.EP | D27: Hardware
B28: Server | C28: SA2.Svr
B29: Network node | C29: SA2.NetNode
B30: Network media | C30: SA2.NetMed
B31: Data media | C31: SA2.DatMed
B32: Peripherals | C32: SA2.Per
B33: Service provider | C33: SA2.SerProv | D33: Personnel
B34: Normal user | C34: SA2.NormUs
B35: Priviliged user / Manager | C35: SA2.PriUs
B36: System supplier | C36: SA2.SysSup
B37: Area | C37: SA2.Area | D37: Location /Installation
B38: Building | C38: SA2.Buil
B39: Room | C39: SA2.Room
B40: Container | C40: SA2.Cont
B41: Mobile platform | C41: SA2.MobPla
B43: Aux table 7
B44: Supporting assets | C44: Level 2 | D44: Level 1
B45: Hosting | C45: Data Center | D45: =D16 -> IT Service
B46: Housing
B47: N/A | C47: Network services
B48: IaaS | C48: Cloud services
B49: PaaS
B50: SaaS
B51: N/A | C51: Standard service
B52: N/A | C52: User defined service
B53: N/A | C53: Firmware | D53: Software
B54: Web Browser | C54: Middleware
B55: Web Server
B56: Application server
B57: DB Server
B58: Network Stack
B59: Operating System
B60: Hypervisor
B61: N/A | C61: End-user application
B62: N/A | C62: Data container | D62: =D21 -> Software Data
B63: N/A | C63: Application data
B64: N/A | C64: Security data
B65: Portable | C65: =B27 -> End-point | D65: Hardware
B66: Fixed
B67: N/A | C67: =B28 -> Server
B68: N/A | C68: =B29 -> Network node
B69: Wired | C69: =B30 -> Network media
B70: Wireless
B71: Digital | C71: =B31 -> Data media
B72: Non-digital
B73: N/A | C73: =B32 -> Peripherals
B74: N/A | C74: =B33 -> Service provider | D74: =D33 -> Personnel
B75: N/A | C75: =B34 -> Normal user
B76: N/A | C76: =B35 -> Priviliged user / Manager
B77: N/A | C77: =B36 -> System supplier
B78: N/A | C78: =B37 -> Area | D78: =D37 -> Location /Installation
B79: N/A | C79: =B38 -> Building
B80: N/A | C80: =B39 -> Room
B81: N/A | C81: =B40 -> Container
B82: N/A | C82: =B41 -> Mobile platform

Sheet P3-Supporting assets
D2: Number of primary assets
B3: Supporting assets Inventory
C5: ID | D5: Supporting asset | E5: Type | H5: Description | I5: Owner | L5: Comments
E6: Level 1 | F6: Level 2 | G6: Level 3 | J6: L2-code | K6: L3-code
C7: =IF(D7<>"",ROW()-6,"") -> 1 | D7: New Web Server | E7: Hardware | F7: Server | G7: N/A | J7: =VLOOKUP(E7,SAlevel1map,2,0) -> SA1.HW | K7: =VLOOKUP(F7,SALevel2map,2,0) -> SA2.Svr
C8: =IF(D8<>"",ROW()-6,"") -> 2 | D8: Application Server | E8: Hardware | F8: Server | G8: N/A | J8: =VLOOKUP(E8,SAlevel1map,2,0) -> SA1.HW | K8: =VLOOKUP(F8,SALevel2map,2,0) -> SA2.Svr
C9: =IF(D9<>"",ROW()-6,"") -> 3 | D9: New Database Server | E9: Hardware | F9: Server | G9: N/A | J9: =VLOOKUP(E9,SAlevel1map,2,0) -> SA1.HW | K9: =VLOOKUP(F9,SALevel2map,2,0) -> SA2.Svr
C10: =IF(D10<>"",ROW()-6,"") -> 4 | D10: Router | E10: Hardware | F10: Network node | G10: N/A | J10: =VLOOKUP(E10,SAlevel1map,2,0) -> SA1.HW | K10: =VLOOKUP(F10,SALevel2map,2,0) -> SA2.NetNode
C11: =IF(D11<>"",ROW()-6,"") -> 5 | D11: External Firewall | E11: Hardware | F11: Network node | G11: N/A | J11: =VLOOKUP(E11,SAlevel1map,2,0) -> SA1.HW | K11: =VLOOKUP(F11,SALevel2map,2,0) -> SA2.NetNode
C12: =IF(D12<>"",ROW()-6,"") -> 6 | D12: Core Switch | E12: Hardware | F12: Network node | G12: N/A | J12: =VLOOKUP(E12,SAlevel1map,2,0) -> SA1.HW | K12: =VLOOKUP(F12,SALevel2map,2,0) -> SA2.NetNode
C13: =IF(D13<>"",ROW()-6,"") -> 7 | D13: New Web Server | E13: Software | F13: Middleware | G13: Web Server | J13: =VLOOKUP(E13,SAlevel1map,2,0) -> SA1.SW | K13: =VLOOKUP(F13,SALevel2map,2,0) -> SA2.Middle
C14: =IF(D14<>"",ROW()-6,"") -> 8 | D14: Application Server | E14: Software | F14: Middleware | G14: Application server | J14: =VLOOKUP(E14,SAlevel1map,2,0) -> SA1.SW | K14: =VLOOKUP(F14,SALevel2map,2,0) -> SA2.Middle
C15: =IF(D15<>"",ROW()-6,"") -> 9 | D15: New Database Server | E15: Software | F15: Middleware | G15: DB Server | J15: =VLOOKUP(E15,SAlevel1map,2,0) -> SA1.SW | K15: =VLOOKUP(F15,SALevel2map,2,0) -> SA2.Middle
C16: =IF(D16<>"",ROW()-6,"") -> 10 | D16: Router | E16: IT Service | F16: Network services | G16: N/A | J16: =VLOOKUP(E16,SAlevel1map,2,0) -> SA1.Services | K16: =VLOOKUP(F16,SALevel2map,2,0) -> SA2.ServNet
C17: =IF(D17<>"",ROW()-6,"") -> 11 | D17: New Database Server | E17: Software Data | F17: Data container | G17: N/A | J17: =VLOOKUP(E17,SAlevel1map,2,0) -> SA1.SWD | K17: =VLOOKUP(F17,SALevel2map,2,0) -> SA2.DatCon
C18: =IF(D18<>"",ROW()-6,"") -> 12 | D18: Application Server | E18: Software Data | F18: Application data | G18: N/A | J18: =VLOOKUP(E18,SAlevel1map,2,0) -> SA1.SWD | K18: =VLOOKUP(F18,SALevel2map,2,0) -> SA2.AppDat
... C24: =IF(D24<>"",ROW()-6,"") -> 18 | D24: Statistical Data Provision Service | E24: IT Service | F24: User defined service | G24: N/A | J24: =VLOOKUP(E24,SAlevel1map,2,0) -> SA1.Services | K24: =VLOOKUP(F24,SALevel2map,2,0) -> SA2.UserDef
C25: =IF(D25<>"",ROW()-6,"") | J25: =VLOOKUP(E25,SAlevel1map,2,0) -> #N/A | K25: =VLOOKUP(F25,SALevel2map,2,0) -> #N/A
C26: =IF(D26<>"",ROW()-6,"") | J26: =VLOOKUP(E26,SAlevel1map,2,0) -> #N/A | K26: =VLOOKUP(F26,SALevel2map,2,0) -> #N/A
C27: =IF(D27<>"",ROW()-6,"") | J27: =VLOOKUP(E27,SAlevel1map,2,0) -> #N/A | K27: =VLOOKUP(F27,SALevel2map,2,0) -> #N/A
C28: =IF(D28<>"",ROW()-6,"") | J28: =VLOOKUP(E28,SAlevel1map,2,0) -> #N/A | K28: =VLOOKUP(F28,SALevel2map,2,0) -> #N/A
C29: =IF(D29<>"",ROW()-6,"") | J29: =VLOOKUP(E29,SAlevel1map,2,0) -> #N/A | K29: =VLOOKUP(F29,SALevel2map,2,0) -> #N/A
C30: =IF(D30<>"",ROW()-6,"") | J30: =VLOOKUP(E30,SAlevel1map,2,0) -> #N/A | K30: =VLOOKUP(F30,SALevel2map,2,0) -> #N/A
C31: =IF(D31<>"",ROW()-6,"") | J31: =VLOOKUP(E31,SAlevel1map,2,0) -> #N/A | K31: =VLOOKUP(F31,SALevel2map,2,0) -> #N/A
C32: =IF(D32<>"",ROW()-6,"") | J32: =VLOOKUP(E32,SAlevel1map,2,0) -> #N/A | K32: =VLOOKUP(F32,SALevel2map,2,0) -> #N/A
C33: =IF(D33<>"",ROW()-6,"") | J33: =VLOOKUP(E33,SAlevel1map,2,0) -> #N/A | K33: =VLOOKUP(F33,SALevel2map,2,0) -> #N/A
C34: =IF(D34<>"",ROW()-6,"") | J34: =VLOOKUP(E34,SAlevel1map,2,0) -> #N/A | K34: =VLOOKUP(F34,SALevel2map,2,0) -> #N/A
C35: =IF(D35<>"",ROW()-6,"") | J35: =VLOOKUP(E35,SAlevel1map,2,0) -> #N/A | K35: =VLOOKUP(F35,SALevel2map,2,0) -> #N/A
C36: =IF(D36<>"",ROW()-6,"") | J36: =VLOOKUP(E36,SAlevel1map,2,0) -> #N/A | K36: =VLOOKUP(F36,SALevel2map,2,0) -> #N/A
... C1006: =IF(D1006<>"",ROW()-6,"") | J1006: =VLOOKUP(E1006,SAlevel1map,2,0) -> #N/A | K1006: =VLOOKUP(F1006,SALevel2map,2,0) -> #N/A

Sheet P4-System Modelling
B4: Supporting asset - Primary asset relation
B6: Supporting | Primary | C6: Citizen Data | D6: Statistical Data | E6: Read Access to Citizen Data | F6: Provision of Statistical Data | G6: Access for Static information | H6: Read Access to Statistical Demographic Data | M6: Comments
B7: New Web Server | C7: X | D7: X | G7: X
B8: Application Server | C8: X | D8: X | H8: X
B9: New Database Server | C9: X | D9: X | E9: X | F9: X | H9: X
B10: Router | E10: X | F10: X | G10: X | H10: X
B11: External Firewall | E11: X | F11: X | G11: X | H11: X
B12: Core Switch | E12: X | F12: X | G12: X | H12: X
B13: Web Hosting Services | C13: X | D13: X | E13: X | F13: X | G13: X | H13: X
B14: Citizen Data Provision Service | C14: X | E14: X
B15: Internet Service | C15: X | D15: X | E15: X | F15: X | G15: X | H15: X
B16: Statistical Data Provision Service | D16: X | F16: X | H16: X

Sheet P4-System Modelling Values
B4: Supporting asset - Primary asset relation
B6: Supporting | Primary | D6: Prim1 | E6: Prim2 | F6: Prim3 | G6: Prim4 | H6: Prim5 | I6: Prim6 | J6: Prim7 | K6: Prim8 | L6: Prim9 | M6: Prim10 | N6: Accumulated value | P6: Comments
B7: SUP1 | C7: Dimension | D7: X | H7: X | I7: X | J7: X | N7: Dimension | O7: Value
C8: C | D8: {=IF(D7<>"",MAX(IF('P2-Asset Valuation'!$E$7:$E$1006=$D$6,IF('P2-Asset Valuation'!$F$7:$F$1006="Confidentiality",'P2-Asset Valuation'!$I$7:$I$1006))),"")} -> 0 | E8: {=IF(E7<>"",MAX(IF('P2-Asset Valuation'!$E$7:$E$1006=$E$6,IF('P2-Asset Valuation'!$F$7:$F$1006="Confidentiality",'P2-Asset Valuation'!$I$7:$I$1006))),"")} | F8: {=IF(F7<>"",MAX(IF('P2-Asset Valuation'!$E$7:$E$1006=$F$6,IF('P2-Asset Valuation'!$F$7:$F$1006="Confidentiality",'P2-Asset Valuation'!$I$7:$I$1006))),"")} | G8: {=IF(G7<>"",MAX(IF('P2-Asset Valuation'!$E$7:$E$1006=$G$6,IF('P2-Asset Valuation'!$F$7:$F$1006="Confidentiality",'P2-Asset Valuation'!$I$7:$I$1006))),"")} | H8: {=IF(H7<>"",MAX(IF('P2-Asset Valuation'!$E$7:$E$1006=$H$6,IF('P2-Asset Valuation'!$F$7:$F$1006="Confidentiality",'P2-Asset Valuation'!$I$7:$I$1006))),"")} -> 0 | I8: {=IF(I7<>"",MAX(IF('P2-Asset Valuation'!$E$7:$E$1006=$I$6,IF('P2-Asset Valuation'!$F$7:$F$1006="Confidentiality",'P2-Asset Valuation'!$I$7:$I$1006))),"")} -> 0 | J8: {=IF(J7<>"",MAX(IF('P2-Asset Valuation'!$E$7:$E$1006=$J$6,IF('P2-Asset Valuation'!$F$7:$F$1006="Confidentiality",'P2-Asset Valuation'!$I$7:$I$1006))),"")} -> 0 | K8: {=IF(K7<>"",MAX(IF('P2-Asset Valuation'!$E$7:$E$1006=$K$6,IF('P2-Asset Valuation'!$F$7:$F$1006="Confidentiality",'P2-Asset Valuation'!$I$7:$I$1006))),"")} | L8: {=IF(L7<>"",MAX(IF('P2-Asset Valuation'!$E$7:$E$1006=$L$6,IF('P2-Asset Valuation'!$F$7:$F$1006="Confidentiality",'P2-Asset Valuation'!$I$7:$I$1006))),"")} | M8: {=IF(M7<>"",MAX(IF('P2-Asset Valuation'!$E$7:$E$1006=$M$6,IF('P2-Asset Valuation'!$F$7:$F$1006="Confidentiality",'P2-Asset Valuation'!$I$7:$I$1006))),"")} | N8: C | O8: =SUM(D8:M8) -> 0
C9: I | D9: {=IF(D7<>"",MAX(IF('P2-Asset Valuation'!$E$7:$E$1006=$D$6,IF('P2-Asset Valuation'!$F$7:$F$1006="Integrity",'P2-Asset Valuation'!$I$7:$I$1006))),"")} -> 0 | E9: {=IF(E7<>"",MAX(IF('P2-Asset Valuation'!$E$7:$E$1006=$E$6,IF('P2-Asset Valuation'!$F$7:$F$1006="Integrity",'P2-Asset Valuation'!$I$7:$I$1006))),"")} | F9: {=IF(F7<>"",MAX(IF('P2-Asset Valuation'!$E$7:$E$1006=$F$6,IF('P2-Asset Valuation'!$F$7:$F$1006="Integrity",'P2-Asset Valuation'!$I$7:$I$1006))),"")} | G9: {=IF(G7<>"",MAX(IF('P2-Asset Valuation'!$E$7:$E$1006=$G$6,IF('P2-Asset Valuation'!$F$7:$F$1006="Integrity",'P2-Asset Valuation'!$I$7:$I$1006))),"")} | H9: {=IF(H7<>"",MAX(IF('P2-Asset Valuation'!$E$7:$E$1006=$H$6,IF('P2-Asset Valuation'!$F$7:$F$1006="Integrity",'P2-Asset Valuation'!$I$7:$I$1006))),"")} -> 0 | I9: {=IF(I7<>"",MAX(IF('P2-Asset Valuation'!$E$7:$E$1006=$I$6,IF('P2-Asset Valuation'!$F$7:$F$1006="Integrity",'P2-Asset Valuation'!$I$7:$I$1006))),"")} -> 0 | J9: {=IF(J7<>"",MAX(IF('P2-Asset Valuation'!$E$7:$E$1006=$J$6,IF('P2-Asset Valuation'!$F$7:$F$1006="Integrity",'P2-Asset Valuation'!$I$7:$I$1006))),"")} -> 0 | K9: {=IF(K7<>"",MAX(IF('P2-Asset Valuation'!$E$7:$E$1006=$K$6,IF('P2-Asset Valuation'!$F$7:$F$1006="Integrity",'P2-Asset Valuation'!$I$7:$I$1006))),"")} | L9: {=IF(L7<>"",MAX(IF('P2-Asset Valuation'!$E$7:$E$1006=$L$6,IF('P2-Asset Valuation'!$F$7:$F$1006="Integrity",'P2-Asset Valuation'!$I$7:$I$1006))),"")} | M9: {=IF(M7<>"",MAX(IF('P2-Asset Valuation'!$E$7:$E$1006=$M$6,IF('P2-Asset Valuation'!$F$7:$F$1006="Integrity",'P2-Asset Valuation'!$I$7:$I$1006))),"")} | N9: I | O9: =SUM(D9:M9) -> 0
C10: A | D10: {=IF(D7<>"",MAX(IF('P2-Asset Valuation'!$E$7:$E$1006=$D$6,IF('P2-Asset Valuation'!$F$7:$F$1006="Availability",'P2-Asset Valuation'!$I$7:$I$1006))),"")} -> 0 | E10: {=IF(E7<>"",MAX(IF('P2-Asset Valuation'!$E$7:$E$1006=$E$6,IF('P2-Asset Valuation'!$F$7:$F$1006="Availability",'P2-Asset Valuation'!$I$7:$I$1006))),"")} | F10: {=IF(F7<>"",MAX(IF('P2-Asset Valuation'!$E$7:$E$1006=$F$6,IF('P2-Asset Valuation'!$F$7:$F$1006="Availability",'P2-Asset Valuation'!$I$7:$I$1006))),"")} | G10: {=IF(G7<>"",MAX(IF('P2-Asset Valuation'!$E$7:$E$1006=$G$6,IF('P2-Asset Valuation'!$F$7:$F$1006="Availability",'P2-Asset Valuation'!$I$7:$I$1006))),"")} | H10: {=IF(H7<>"",MAX(IF('P2-Asset Valuation'!$E$7:$E$1006=$H$6,IF('P2-Asset Valuation'!$F$7:$F$1006="Availability",'P2-Asset Valuation'!$I$7:$I$1006))),"")} -> 0 | I10: {=IF(I7<>"",MAX(IF('P2-Asset Valuation'!$E$7:$E$1006=$I$6,IF('P2-Asset Valuation'!$F$7:$F$1006="Availability",'P2-Asset Valuation'!$I$7:$I$1006))),"")} -> 0 | J10: {=IF(J7<>"",MAX(IF('P2-Asset Valuation'!$E$7:$E$1006=$J$6,IF('P2-Asset Valuation'!$F$7:$F$1006="Availability",'P2-Asset Valuation'!$I$7:$I$1006))),"")} -> 0 | K10: {=IF(K7<>"",MAX(IF('P2-Asset Valuation'!$E$7:$E$1006=$K$6,IF('P2-Asset Valuation'!$F$7:$F$1006="Availability",'P2-Asset Valuation'!$I$7:$I$1006))),"")} | L10: {=IF(L7<>"",MAX(IF('P2-Asset Valuation'!$E$7:$E$1006=$L$6,IF('P2-Asset Valuation'!$F$7:$F$1006="Availability",'P2-Asset Valuation'!$I$7:$I$1006))),"")} | M10: {=IF(M7<>"",MAX(IF('P2-Asset Valuation'!$E$7:$E$1006=$M$6,IF('P2-Asset Valuation'!$F$7:$F$1006="Availability",'P2-Asset Valuation'!$I$7:$I$1006))),"")} | N10: A | O10: =SUM(D10:M10) -> 0
B11: Sup2 | C11: Dimension | E11: X | K11: X | L11: X | N11: Dimension | O11: Value
C12: C | D12: {=IF(D11<>"",MAX(IF('P2-Asset Valuation'!$E$7:$E$1006=$D$6,IF('P2-Asset Valuation'!$F$7:$F$1006="Confidentiality",'P2-Asset Valuation'!$I$7:$I$1006))),"")} | E12: {=IF(E11<>"",MAX(IF('P2-Asset Valuation'!$E$7:$E$1006=$E$6,IF('P2-Asset Valuation'!$F$7:$F$1006="Confidentiality",'P2-Asset Valuation'!$I$7:$I$1006))),"")} -> 0 | F12: {=IF(F11<>"",MAX(IF('P2-Asset Valuation'!$E$7:$E$1006=$F$6,IF('P2-Asset Valuation'!$F$7:$F$1006="Confidentiality",'P2-Asset Valuation'!$I$7:$I$1006))),"")} | G12: {=IF(G11<>"",MAX(IF('P2-Asset Valuation'!$E$7:$E$1006=$G$6,IF('P2-Asset Valuation'!$F$7:$F$1006="Confidentiality",'P2-Asset Valuation'!$I$7:$I$1006))),"")} | H12: {=IF(H11<>"",MAX(IF('P2-Asset Valuation'!$E$7:$E$1006=$H$6,IF('P2-Asset Valuation'!$F$7:$F$1006="Confidentiality",'P2-Asset Valuation'!$I$7:$I$1006))),"")} | I12: {=IF(I11<>"",MAX(IF('P2-Asset Valuation'!$E$7:$E$1006=$I$6,IF('P2-Asset Valuation'!$F$7:$F$1006="Confidentiality",'P2-Asset Valuation'!$I$7:$I$1006))),"")} | J12: {=IF(J11<>"",MAX(IF('P2-Asset Valuation'!$E$7:$E$1006=$J$6,IF('P2-Asset Valuation'!$F$7:$F$1006="Confidentiality",'P2-Asset Valuation'!$I$7:$I$1006))),"")} | K12: {=IF(K11<>"",MAX(IF('P2-Asset Valuation'!$E$7:$E$1006=$K$6,IF('P2-Asset Valuation'!$F$7:$F$1006="Confidentiality",'P2-Asset Valuation'!$I$7:$I$1006))),"")} -> 0 | L12: {=IF(L11<>"",MAX(IF('P2-Asset Valuation'!$E$7:$E$1006=$L$6,IF('P2-Asset Valuation'!$F$7:$F$1006="Confidentiality",'P2-Asset Valuation'!$I$7:$I$1006))),"")} -> 0 | M12: {=IF(M11<>"",MAX(IF('P2-Asset Valuation'!$E$7:$E$1006=$M$6,IF('P2-Asset Valuation'!$F$7:$F$1006="Confidentiality",'P2-Asset Valuation'!$I$7:$I$1006))),"")} | N12: C | O12: =SUM(D12:M12) -> 0
C13: I | D13: {=IF(D11<>"",MAX(IF('P2-Asset Valuation'!$E$7:$E$1006=$D$6,IF('P2-Asset Valuation'!$F$7:$F$1006="Integrity",'P2-Asset Valuation'!$I$7:$I$1006))),"")} | E13: {=IF(E11<>"",MAX(IF('P2-Asset Valuation'!$E$7:$E$1006=$E$6,IF('P2-Asset Valuation'!$F$7:$F$1006="Integrity",'P2-Asset Valuation'!$I$7:$I$1006))),"")} -> 0 | F13: {=IF(F11<>"",MAX(IF('P2-Asset Valuation'!$E$7:$E$1006=$F$6,IF('P2-Asset Valuation'!$F$7:$F$1006="Integrity",'P2-Asset Valuation'!$I$7:$I$1006))),"")} | G13: {=IF(G11<>"",MAX(IF('P2-Asset Valuation'!$E$7:$E$1006=$G$6,IF('P2-Asset Valuation'!$F$7:$F$1006="Integrity",'P2-Asset Valuation'!$I$7:$I$1006))),"")} | H13: {=IF(H11<>"",MAX(IF('P2-Asset Valuation'!$E$7:$E$1006=$H$6,IF('P2-Asset Valuation'!$F$7:$F$1006="Integrity",'P2-Asset Valuation'!$I$7:$I$1006))),"")} | I13: {=IF(I11<>"",MAX(IF('P2-Asset Valuation'!$E$7:$E$1006=$I$6,IF('P2-Asset Valuation'!$F$7:$F$1006="Integrity",'P2-Asset Valuation'!$I$7:$I$1006))),"")} | J13: {=IF(J11<>"",MAX(IF('P2-Asset Valuation'!$E$7:$E$1006=$J$6,IF('P2-Asset Valuation'!$F$7:$F$1006="Integrity",'P2-Asset Valuation'!$I$7:$I$1006))),"")} | K13: {=IF(K11<>"",MAX(IF('P2-Asset Valuation'!$E$7:$E$1006=$K$6,IF('P2-Asset Valuation'!$F$7:$F$1006="Integrity",'P2-Asset Valuation'!$I$7:$I$1006))),"")} -> 0 | L13: {=IF(L11<>"",MAX(IF('P2-Asset Valuation'!$E$7:$E$1006=$L$6,IF('P2-Asset Valuation'!$F$7:$F$1006="Integrity",'P2-Asset Valuation'!$I$7:$I$1006))),"")} -> 0 | M13: {=IF(M11<>"",MAX(IF('P2-Asset Valuation'!$E$7:$E$1006=$M$6,IF('P2-Asset Valuation'!$F$7:$F$1006="Integrity",'P2-Asset Valuation'!$I$7:$I$1006))),"")} | N13: I | O13: =SUM(D13:M13) -> 0
C14: A | D14: {=IF(D11<>"",MAX(IF('P2-Asset Valuation'!$E$7:$E$1006=$D$6,IF('P2-Asset Valuation'!$F$7:$F$1006="Availability",'P2-Asset Valuation'!$I$7:$I$1006))),"")} | E14: {=IF(E11<>"",MAX(IF('P2-Asset Valuation'!$E$7:$E$1006=$E$6,IF('P2-Asset Valuation'!$F$7:$F$1006="Availability",'P2-Asset Valuation'!$I$7:$I$1006))),"")} -> 0 | F14: {=IF(F11<>"",MAX(IF('P2-Asset Valuation'!$E$7:$E$1006=$F$6,IF('P2-Asset Valuation'!$F$7:$F$1006="Availability",'P2-Asset Valuation'!$I$7:$I$1006))),"")} | G14: {=IF(G11<>"",MAX(IF('P2-Asset Valuation'!$E$7:$E$1006=$G$6,IF('P2-Asset Valuation'!$F$7:$F$1006="Availability",'P2-Asset Valuation'!$I$7:$I$1006))),"")} | H14: {=IF(H11<>"",MAX(IF('P2-Asset Valuation'!$E$7:$E$1006=$H$6,IF('P2-Asset Valuation'!$F$7:$F$1006="Availability",'P2-Asset Valuation'!$I$7:$I$1006))),"")} | I14: {=IF(I11<>"",MAX(IF('P2-Asset Valuation'!$E$7:$E$1006=$I$6,IF('P2-Asset Valuation'!$F$7:$F$1006="Availability",'P2-Asset Valuation'!$I$7:$I$1006))),"")} | J14: {=IF(J11<>"",MAX(IF('P2-Asset Valuation'!$E$7:$E$1006=$J$6,IF('P2-Asset Valuation'!$F$7:$F$1006="Availability",'P2-Asset Valuation'!$I$7:$I$1006))),"")} | K14: {=IF(K11<>"",MAX(IF('P2-Asset Valuation'!$E$7:$E$1006=$K$6,IF('P2-Asset Valuation'!$F$7:$F$1006="Availability",'P2-Asset Valuation'!$I$7:$I$1006))),"")} -> 0 | L14: {=IF(L11<>"",MAX(IF('P2-Asset Valuation'!$E$7:$E$1006=$L$6,IF('P2-Asset Valuation'!$F$7:$F$1006="Availability",'P2-Asset Valuation'!$I$7:$I$1006))),"")} -> 0 | M14: {=IF(M11<>"",MAX(IF('P2-Asset Valuation'!$E$7:$E$1006=$M$6,IF('P2-Asset Valuation'!$F$7:$F$1006="Availability",'P2-Asset Valuation'!$I$7:$I$1006))),"")} | N14: A | O14: =SUM(D14:M14) -> 0
B15: Sup3 | C15: Dimension | M15: X | N15: Dimension | O15: Value
C16: C | D16: {=IF(D15<>"",MAX(IF('P2-Asset Valuation'!$E$7:$E$1006=$D$6,IF('P2-Asset Valuation'!$F$7:$F$1006="Confidentiality",'P2-Asset Valuation'!$I$7:$I$1006))),"")} | E16: {=IF(E15<>"",MAX(IF('P2-Asset Valuation'!$E$7:$E$1006=$E$6,IF('P2-Asset Valuation'!$F$7:$F$1006="Confidentiality",'P2-Asset Valuation'!$I$7:$I$1006))),"")} | F16: {=IF(F15<>"",MAX(IF('P2-Asset Valuation'!$E$7:$E$1006=$F$6,IF('P2-Asset Valuation'!$F$7:$F$1006="Confidentiality",'P2-Asset Valuation'!$I$7:$I$1006))),"")} | G16: {=IF(G15<>"",MAX(IF('P2-Asset Valuation'!$E$7:$E$1006=$G$6,IF('P2-Asset Valuation'!$F$7:$F$1006="Confidentiality",'P2-Asset Valuation'!$I$7:$I$1006))),"")} | H16: {=IF(H15<>"",MAX(IF('P2-Asset Valuation'!$E$7:$E$1006=$H$6,IF('P2-Asset Valuation'!$F$7:$F$1006="Confidentiality",'P2-Asset Valuation'!$I$7:$I$1006))),"")} | I16: {=IF(I15<>"",MAX(IF('P2-Asset Valuation'!$E$7:$E$1006=$I$6,IF('P2-Asset Valuation'!$F$7:$F$1006="Confidentiality",'P2-Asset Valuation'!$I$7:$I$1006))),"")} | J16: {=IF(J15<>"",MAX(IF('P2-Asset Valuation'!$E$7:$E$1006=$J$6,IF('P2-Asset Valuation'!$F$7:$F$1006="Confidentiality",'P2-Asset Valuation'!$I$7:$I$1006))),"")} | K16: {=IF(K15<>"",MAX(IF('P2-Asset Valuation'!$E$7:$E$1006=$K$6,IF('P2-Asset Valuation'!$F$7:$F$1006="Confidentiality",'P2-Asset Valuation'!$I$7:$I$1006))),"")} | L16: {=IF(L15<>"",MAX(IF('P2-Asset Valuation'!$E$7:$E$1006=$L$6,IF('P2-Asset Valuation'!$F$7:$F$1006="Confidentiality",'P2-Asset Valuation'!$I$7:$I$1006))),"")} | M16: {=IF(M15<>"",MAX(IF('P2-Asset Valuation'!$E$7:$E$1006=$M$6,IF('P2-Asset Valuation'!$F$7:$F$1006="Confidentiality",'P2-Asset Valuation'!$I$7:$I$1006))),"")} -> 0 | N16: C | O16: =SUM(D16:M16) -> 0
C17: I | D17: {=IF(D15<>"",MAX(IF('P2-Asset Valuation'!$E$7:$E$1006=$D$6,IF('P2-Asset Valuation'!$F$7:$F$1006="Integrity",'P2-Asset Valuation'!$I$7:$I$1006))),"")} | E17: {=IF(E15<>"",MAX(IF('P2-Asset Valuation'!$E$7:$E$1006=$E$6,IF('P2-Asset Valuation'!$F$7:$F$1006="Integrity",'P2-Asset Valuation'!$I$7:$I$1006))),"")} | F17: {=IF(F15<>"",MAX(IF('P2-Asset Valuation'!$E$7:$E$1006=$F$6,IF('P2-Asset Valuation'!$F$7:$F$1006="Integrity",'P2-Asset Valuation'!$I$7:$I$1006))),"")} | G17: {=IF(G15<>"",MAX(IF('P2-Asset Valuation'!$E$7:$E$1006=$G$6,IF('P2-Asset Valuation'!$F$7:$F$1006="Integrity",'P2-Asset Valuation'!$I$7:$I$1006))),"")} | H17: {=IF(H15<>"",MAX(IF('P2-Asset Valuation'!$E$7:$E$1006=$H$6,IF('P2-Asset Valuation'!$F$7:$F$1006="Integrity",'P2-Asset Valuation'!$I$7:$I$1006))),"")} | I17: {=IF(I15<>"",MAX(IF('P2-Asset Valuation'!$E$7:$E$1006=$I$6,IF('P2-Asset Valuation'!$F$7:$F$1006="Integrity",'P2-Asset Valuation'!$I$7:$I$1006))),"")} | J17: {=IF(J15<>"",MAX(IF('P2-Asset Valuation'!$E$7:$E$1006=$J$6,IF('P2-Asset Valuation'!$F$7:$F$1006="Integrity",'P2-Asset Valuation'!$I$7:$I$1006))),"")} | K17: {=IF(K15<>"",MAX(IF('P2-Asset Valuation'!$E$7:$E$1006=$K$6,IF('P2-Asset Valuation'!$F$7:$F$1006="Integrity",'P2-Asset Valuation'!$I$7:$I$1006))),"")} | L17: {=IF(L15<>"",MAX(IF('P2-Asset Valuation'!$E$7:$E$1006=$L$6,IF('P2-Asset Valuation'!$F$7:$F$1006="Integrity",'P2-Asset Valuation'!$I$7:$I$1006))),"")} | M17: {=IF(M15<>"",MAX(IF('P2-Asset Valuation'!$E$7:$E$1006=$M$6,IF('P2-Asset Valuation'!$F$7:$F$1006="Integrity",'P2-Asset Valuation'!$I$7:$I$1006))),"")} -> 0 | N17: I | O17: =SUM(D17:M17) -> 0
C18: A | D18: {=IF(D15<>"",MAX(IF('P2-Asset Valuation'!$E$7:$E$1006=$D$6,IF('P2-Asset Valuation'!$F$7:$F$1006="Availability",'P2-Asset Valuation'!$I$7:$I$1006))),"")} | E18: {=IF(E15<>"",MAX(IF('P2-Asset Valuation'!$E$7:$E$1006=$E$6,IF('P2-Asset Valuation'!$F$7:$F$1006="Availability",'P2-Asset Valuation'!$I$7:$I$1006))),"")} | F18: {=IF(F15<>"",MAX(IF('P2-Asset Valuation'!$E$7:$E$1006=$F$6,IF('P2-Asset Valuation'!$F$7:$F$1006="Availability",'P2-Asset Valuation'!$I$7:$I$1006))),"")} | G18: {=IF(G15<>"",MAX(IF('P2-Asset Valuation'!$E$7:$E$1006=$G$6,IF('P2-Asset Valuation'!$F$7:$F$1006="Availability",'P2-Asset Valuation'!$I$7:$I$1006))),"")} | H18: {=IF(H15<>"",MAX(IF('P2-Asset Valuation'!$E$7:$E$1006=$H$6,IF('P2-Asset Valuation'!$F$7:$F$1006="Availability",'P2-Asset Valuation'!$I$7:$I$1006))),"")} | I18: {=IF(I15<>"",MAX(IF('P2-Asset Valuation'!$E$7:$E$1006=$I$6,IF('P2-Asset Valuation'!$F$7:$F$1006="Availability",'P2-Asset Valuation'!$I$7:$I$1006))),"")} | J18: {=IF(J15<>"",MAX(IF('P2-Asset Valuation'!$E$7:$E$1006=$J$6,IF('P2-Asset Valuation'!$F$7:$F$1006="Availability",'P2-Asset Valuation'!$I$7:$I$1006))),"")} | K18: {=IF(K15<>"",MAX(IF('P2-Asset Valuation'!$E$7:$E$1006=$K$6,IF('P2-Asset Valuation'!$F$7:$F$1006="Availability",'P2-Asset Valuation'!$I$7:$I$1006))),"")} | L18: {=IF(L15<>"",MAX(IF('P2-Asset Valuation'!$E$7:$E$1006=$L$6,IF('P2-Asset Valuation'!$F$7:$F$1006="Availability",'P2-Asset Valuation'!$I$7:$I$1006))),"")} | M18: {=IF(M15<>"",MAX(IF('P2-Asset Valuation'!$E$7:$E$1006=$M$6,IF('P2-Asset Valuation'!$F$7:$F$1006="Availability",'P2-Asset Valuation'!$I$7:$I$1006))),"")} -> 0 | N18: A | O18: =SUM(D18:M18) -> 0
B19: Sup4 | C19: Dimension | E19: X | G19: X | N19: Dimension | O19: Value
C20: C | D20: {=IF(D19<>"",MAX(IF('P2-Asset Valuation'!$E$7:$E$1006=$D$6,IF('P2-Asset Valuation'!$F$7:$F$1006="Confidentiality",'P2-Asset Valuation'!$I$7:$I$1006))),"")} | E20: {=IF(E19<>"",MAX(IF('P2-Asset Valuation'!$E$7:$E$1006=$E$6,IF('P2-Asset Valuation'!$F$7:$F$1006="Confidentiality",'P2-Asset Valuation'!$I$7:$I$1006))),"")} -> 0 | F20: {=IF(F19<>"",MAX(IF('P2-Asset Valuation'!$E$7:$E$1006=$F$6,IF('P2-Asset Valuation'!$F$7:$F$1006="Confidentiality",'P2-Asset Valuation'!$I$7:$I$1006))),"")} | G20: {=IF(G19<>"",MAX(IF('P2-Asset Valuation'!$E$7:$E$1006=$G$6,IF('P2-Asset Valuation'!$F$7:$F$1006="Confidentiality",'P2-Asset Valuation'!$I$7:$I$1006))),"")} -> 0 | H20: {=IF(H19<>"",MAX(IF('P2-Asset Valuation'!$E$7:$E$1006=$H$6,IF('P2-Asset Valuation'!$F$7:$F$1006="Confidentiality",'P2-Asset Valuation'!$I$7:$I$1006))),"")} | I20: {=IF(I19<>"",MAX(IF('P2-Asset Valuation'!$E$7:$E$1006=$I$6,IF('P2-Asset Valuation'!$F$7:$F$1006="Confidentiality",'P2-Asset Valuation'!$I$7:$I$1006))),"")} | J20: {=IF(J19<>"",MAX(IF('P2-Asset Valuation'!$E$7:$E$1006=$J$6,IF('P2-Asset Valuation'!$F$7:$F$1006="Confidentiality",'P2-Asset Valuation'!$I$7:$I$1006))),"")} | K20: {=IF(K19<>"",MAX(IF('P2-Asset Valuation'!$E$7:$E$1006=$K$6,IF('P2-Asset Valuation'!$F$7:$F$1006="Confidentiality",'P2-Asset Valuation'!$I$7:$I$1006))),"")} | L20: {=IF(L19<>"",MAX(IF('P2-Asset Valuation'!$E$7:$E$1006=$L$6,IF('P2-Asset Valuation'!$F$7:$F$1006="Confidentiality",'P2-Asset Valuation'!$I$7:$I$1006))),"")} | M20: {=IF(M19<>"",MAX(IF('P2-Asset Valuation'!$E$7:$E$1006=$M$6,IF('P2-Asset Valuation'!$F$7:$F$1006="Confidentiality",'P2-Asset Valuation'!$I$7:$I$1006))),"")} | N20: C | O20: =SUM(D20:M20) -> 0
C21: I | D21: {=IF(D19<>"",MAX(IF('P2-Asset Valuation'!$E$7:$E$1006=$D$6,IF('P2-Asset Valuation'!$F$7:$F$1006="Integrity",'P2-Asset Valuation'!$I$7:$I$1006))),"")} | E21: {=IF(E19<>"",MAX(IF('P2-Asset Valuation'!$E$7:$E$1006=$E$6,IF('P2-Asset Valuation'!$F$7:$F$1006="Integrity",'P2-Asset Valuation'!$I$7:$I$1006))),"")} -> 0 | F21: {=IF(F19<>"",MAX(IF('P2-Asset Valuation'!$E$7:$E$1006=$F$6,IF('P2-Asset Valuation'!$F$7:$F$1006="Integrity",'P2-Asset Valuation'!$I$7:$I$1006))),"")} | G21: {=IF(G19<>"",MAX(IF('P2-Asset Valuation'!$E$7:$E$1006=$G$6,IF('P2-Asset Valuation'!$F$7:$F$1006="Integrity",'P2-Asset Valuation'!$I$7:$I$1006))),"")} -> 0 | H21: {=IF(H19<>"",MAX(IF('P2-Asset Valuation'!$E$7:$E$1006=$H$6,IF('P2-Asset Valuation'!$F$7:$F$1006="Integrity",'P2-Asset Valuation'!$I$7:$I$1006))),"")} | I21: {=IF(I19<>"",MAX(IF('P2-Asset Valuation'!$E$7:$E$1006=$I$6,IF('P2-Asset Valuation'!$F$7:$F$1006="Integrity",'P2-Asset Valuation'!$I$7:$I$1006))),"")} | J21: {=IF(J19<>"",MAX(IF('P2-Asset Valuation'!$E$7:$E$1006=$J$6,IF('P2-Asset Valuation'!$F$7:$F$1006="Integrity",'P2-Asset Valuation'!$I$7:$I$1006))),"")} | K21: {=IF(K19<>"",MAX(IF('P2-Asset Valuation'!$E$7:$E$1006=$K$6,IF('P2-Asset Valuation'!$F$7:$F$1006="Integrity",'P2-Asset Valuation'!$I$7:$I$1006))),"")} | L21: {=IF(L19<>"",MAX(IF('P2-Asset Valuation'!$E$7:$E$1006=$L$6,IF('P2-Asset Valuation'!$F$7:$F$1006="Integrity",'P2-Asset Valuation'!$I$7:$I$1006))),"")} | M21: {=IF(M19<>"",MAX(IF('P2-Asset Valuation'!$E$7:$E$1006=$M$6,IF('P2-Asset Valuation'!$F$7:$F$1006="Integrity",'P2-Asset Valuation'!$I$7:$I$1006))),"")} | N21: I | O21: =SUM(D21:M21) -> 0
C22: A | D22: {=IF(D19<>"",MAX(IF('P2-Asset Valuation'!$E$7:$E$1006=$D$6,IF('P2-Asset Valuation'!$F$7:$F$1006="Availability",'P2-Asset Valuation'!$I$7:$I$1006))),"")} | E22: {=IF(E19<>"",MAX(IF('P2-Asset Valuation'!$E$7:$E$1006=$E$6,IF('P2-Asset Valuation'!$F$7:$F$1006="Availability",'P2-Asset Valuation'!$I$7:$I$1006))),"")} -> 0 | F22: {=IF(F19<>"",MAX(IF('P2-Asset Valuation'!$E$7:$E$1006=$F$6,IF('P2-Asset Valuation'!$F$7:$F$1006="Availability",'P2-Asset Valuation'!$I$7:$I$1006))),"")} | G22: {=IF(G19<>"",MAX(IF('P2-Asset Valuation'!$E$7:$E$1006=$G$6,IF('P2-Asset Valuation'!$F$7:$F$1006="Availability",'P2-Asset Valuation'!$I$7:$I$1006))),"")} -> 0 | H22: {=IF(H19<>"",MAX(IF('P2-Asset Valuation'!$E$7:$E$1006=$H$6,IF('P2-Asset Valuation'!$F$7:$F$1006="Availability",'P2-Asset Valuation'!$I$7:$I$1006))),"")} | I22: {=IF(I19<>"",MAX(IF('P2-Asset Valuation'!$E$7:$E$1006=$I$6,IF('P2-Asset Valuation'!$F$7:$F$1006="Availability",'P2-Asset Valuation'!$I$7:$I$1006))),"")} | J22: {=IF(J19<>"",MAX(IF('P2-Asset Valuation'!$E$7:$E$1006=$J$6,IF('P2-Asset Valuation'!$F$7:$F$1006="Availability",'P2-Asset Valuation'!$I$7:$I$1006))),"")} | K22: {=IF(K19<>"",MAX(IF('P2-Asset Valuation'!$E$7:$E$1006=$K$6,IF('P2-Asset Valuation'!$F$7:$F$1006="Availability",'P2-Asset Valuation'!$I$7:$I$1006))),"")} | L22: {=IF(L19<>"",MAX(IF('P2-Asset Valuation'!$E$7:$E$1006=$L$6,IF('P2-Asset Valuation'!$F$7:$F$1006="Availability",'P2-Asset Valuation'!$I$7:$I$1006))),"")} | M22: {=IF(M19<>"",MAX(IF('P2-Asset Valuation'!$E$7:$E$1006=$M$6,IF('P2-Asset Valuation'!$F$7:$F$1006="Availability",'P2-Asset Valuation'!$I$7:$I$1006))),"")} | N22: A | O22: =SUM(D22:M22) -> 0
B23: Sup5 | C23: Dimension | F23: X | M23: X | N23: Dimension | O23: Value
C24: C | D24: {=IF(D23<>"",MAX(IF('P2-Asset Valuation'!$E$7:$E$1006=$D$6,IF('P2-Asset Valuation'!$F$7:$F$1006="Confidentiality",'P2-Asset Valuation'!$I$7:$I$1006))),"")} | E24: {=IF(E23<>"",MAX(IF('P2-Asset Valuation'!$E$7:$E$1006=$E$6,IF('P2-Asset Valuation'!$F$7:$F$1006="Confidentiality",'P2-Asset Valuation'!$I$7:$I$1006))),"")} | F24: {=IF(F23<>"",MAX(IF('P2-Asset Valuation'!$E$7:$E$1006=$F$6,IF('P2-Asset Valuation'!$F$7:$F$1006="Confidentiality",'P2-Asset Valuation'!$I$7:$I$1006))),"")} -> 0 | G24: {=IF(G23<>"",MAX(IF('P2-Asset Valuation'!$E$7:$E$1006=$G$6,IF('P2-Asset Valuation'!$F$7:$F$1006="Confidentiality",'P2-Asset Valuation'!$I$7:$I$1006))),"")} | H24: {=IF(H23<>"",MAX(IF('P2-Asset Valuation'!$E$7:$E$1006=$H$6,IF('P2-Asset Valuation'!$F$7:$F$1006="Confidentiality",'P2-Asset Valuation'!$I$7:$I$1006))),"")} | I24: {=IF(I23<>"",MAX(IF('P2-Asset Valuation'!$E$7:$E$1006=$I$6,IF('P2-Asset Valuation'!$F$7:$F$1006="Confidentiality",'P2-Asset Valuation'!$I$7:$I$1006))),"")} | J24: {=IF(J23<>"",MAX(IF('P2-Asset Valuation'!$E$7:$E$1006=$J$6,IF('P2-Asset Valuation'!$F$7:$F$1006="Confidentiality",'P2-Asset Valuation'!$I$7:$I$1006))),"")} | K24: {=IF(K23<>"",MAX(IF('P2-Asset Valuation'!$E$7:$E$1006=$K$6,IF('P2-Asset Valuation'!$F$7:$F$1006="Confidentiality",'P2-Asset Valuation'!$I$7:$I$1006))),"")} | L24: {=IF(L23<>"",MAX(IF('P2-Asset Valuation'!$E$7:$E$1006=$L$6,IF('P2-Asset Valuation'!$F$7:$F$1006="Confidentiality",'P2-Asset Valuation'!$I$7:$I$1006))),"")} | M24: {=IF(M23<>"",MAX(IF('P2-Asset Valuation'!$E$7:$E$1006=$M$6,IF('P2-Asset Valuation'!$F$7:$F$1006="Confidentiality",'P2-Asset Valuation'!$I$7:$I$1006))),"")} -> 0 | N24: C | O24: =SUM(D24:M24) -> 0
C25: I | D25: {=IF(D23<>"",MAX(IF('P2-Asset Valuation'!$E$7:$E$1006=$D$6,IF('P2-Asset Valuation'!$F$7:$F$1006="Integrity",'P2-Asset Valuation'!$I$7:$I$1006))),"")} | E25: {=IF(E23<>"",MAX(IF('P2-Asset Valuation'!$E$7:$E$1006=$E$6,IF('P2-Asset Valuation'!$F$7:$F$1006="Integrity",'P2-Asset Valuation'!$I$7:$I$1006))),"")} | F25: {=IF(F23<>"",MAX(IF('P2-Asset Valuation'!$E$7:$E$1006=$F$6,IF('P2-Asset Valuation'!$F$7:$F$1006="Integrity",'P2-Asset Valuation'!$I$7:$I$1006))),"")} -> 0 | G25: {=IF(G23<>"",MAX(IF('P2-Asset Valuation'!$E$7:$E$1006=$G$6,IF('P2-Asset Valuation'!$F$7:$F$1006="Integrity",'P2-Asset Valuation'!$I$7:$I$1006))),"")} | H25: {=IF(H23<>"",MAX(IF('P2-Asset Valuation'!$E$7:$E$1006=$H$6,IF('P2-Asset Valuation'!$F$7:$F$1006="Integrity",'P2-Asset Valuation'!$I$7:$I$1006))),"")} | I25: {=IF(I23<>"",MAX(IF('P2-Asset Valuation'!$E$7:$E$1006=$I$6,IF('P2-Asset Valuation'!$F$7:$F$1006="Integrity",'P2-Asset Valuation'!$I$7:$I$1006))),"")} | J25: {=IF(J23<>"",MAX(IF('P2-Asset Valuation'!$E$7:$E$1006=$J$6,IF('P2-Asset Valuation'!$F$7:$F$1006="Integrity",'P2-Asset Valuation'!$I$7:$I$1006))),"")} | K25: {=IF(K23<>"",MAX(IF('P2-Asset Valuation'!$E$7:$E$1006=$K$6,IF('P2-Asset Valuation'!$F$7:$F$1006="Integrity",'P2-Asset Valuation'!$I$7:$I$1006))),"")} | L25: {=IF(L23<>"",MAX(IF('P2-Asset Valuation'!$E$7:$E$1006=$L$6,IF('P2-Asset Valuation'!$F$7:$F$1006="Integrity",'P2-Asset Valuation'!$I$7:$I$1006))),"")} | M25: {=IF(M23<>"",MAX(IF('P2-Asset Valuation'!$E$7:$E$1006=$M$6,IF('P2-Asset Valuation'!$F$7:$F$1006="Integrity",'P2-Asset Valuation'!$I$7:$I$1006))),"")} -> 0 | N25: I | O25: =SUM(D25:M25) -> 0
C26: A | D26: {=IF(D23<>"",MAX(IF('P2-Asset Valuation'!$E$7:$E$1006=$D$6,IF('P2-Asset Valuation'!$F$7:$F$1006="Availability",'P2-Asset Valuation'!$I$7:$I$1006))),"")} | E26: {=IF(E23<>"",MAX(IF('P2-Asset Valuation'!$E$7:$E$1006=$E$6,IF('P2-Asset Valuation'!$F$7:$F$1006="Availability",'P2-Asset Valuation'!$I$7:$I$1006))),"")} | F26: {=IF(F23<>"",MAX(IF('P2-Asset Valuation'!$E$7:$E$1006=$F$6,IF('P2-Asset Valuation'!$F$7:$F$1006="Availability",'P2-Asset Valuation'!$I$7:$I$1006))),"")} -> 0 | G26: {=IF(G23<>"",MAX(IF('P2-Asset Valuation'!$E$7:$E$1006=$G$6,IF('P2-Asset Valuation'!$F$7:$F$1006="Availability",'P2-Asset Valuation'!$I$7:$I$1006))),"")} | H26: {=IF(H23<>"",MAX(IF('P2-Asset Valuation'!$E$7:$E$1006=$H$6,IF('P2-Asset Valuation'!$F$7:$F$1006="Availability",'P2-Asset Valuation'!$I$7:$I$1006))),"")} | I26: {=IF(I23<>"",MAX(IF('P2-Asset Valuation'!$E$7:$E$1006=$I$6,IF('P2-Asset Valuation'!$F$7:$F$1006="Availability",'P2-Asset Valuation'!$I$7:$I$1006))),"")} | J26: {=IF(J23<>"",MAX(IF('P2-Asset Valuation'!$E$7:$E$1006=$J$6,IF('P2-Asset Valuation'!$F$7:$F$1006="Availability",'P2-Asset Valuation'!$I$7:$I$1006))),"")} | K26: {=IF(K23<>"",MAX(IF('P2-Asset Valuation'!$E$7:$E$1006=$K$6,IF('P2-Asset Valuation'!$F$7:$F$1006="Availability",'P2-Asset Valuation'!$I$7:$I$1006))),"")} | L26: {=IF(L23<>"",MAX(IF('P2-Asset Valuation'!$E$7:$E$1006=$L$6,IF('P2-Asset Valuation'!$F$7:$F$1006="Availability",'P2-Asset Valuation'!$I$7:$I$1006))),"")} | M26: {=IF(M23<>"",MAX(IF('P2-Asset Valuation'!$E$7:$E$1006=$M$6,IF('P2-Asset Valuation'!$F$7:$F$1006="Availability",'P2-Asset Valuation'!$I$7:$I$1006))),"")} -> 0 | N26: A | O26: =SUM(D26:M26) -> 0
B27: Sup6 | C27: Dimension | D27: X | M27: X | N27: Dimension | O27: Value
C28: C | D28: {=IF(D27<>"",MAX(IF('P2-Asset Valuation'!$E$7:$E$1006=$D$6,IF('P2-Asset Valuation'!$F$7:$F$1006="Confidentiality",'P2-Asset Valuation'!$I$7:$I$1006))),"")} -> 0 | E28: {=IF(E27<>"",MAX(IF('P2-Asset Valuation'!$E$7:$E$1006=$E$6,IF('P2-Asset Valuation'!$F$7:$F$1006="Confidentiality",'P2-Asset Valuation'!$I$7:$I$1006))),"")} | F28: {=IF(F27<>"",MAX(IF('P2-Asset Valuation'!$E$7:$E$1006=$F$6,IF('P2-Asset Valuation'!$F$7:$F$1006="Confidentiality",'P2-Asset Valuation'!$I$7:$I$1006))),"")} | G28: {=IF(G27<>"",MAX(IF('P2-Asset Valuation'!$E$7:$E$1006=$G$6,IF('P2-Asset Valuation'!$F$7:$F$1006="Confidentiality",'P2-Asset Valuation'!$I$7:$I$1006))),"")} | H28: {=IF(H27<>"",MAX(IF('P2-Asset Valuation'!$E$7:$E$1006=$H$6,IF('P2-Asset Valuation'!$F$7:$F$1006="Confidentiality",'P2-Asset Valuation'!$I$7:$I$1006))),"")} | I28: {=IF(I27<>"",MAX(IF('P2-Asset Valuation'!$E$7:$E$1006=$I$6,IF('P2-Asset Valuation'!$F$7:$F$1006="Confidentiality",'P2-Asset Valuation'!$I$7:$I$1006))),"")} | J28: {=IF(J27<>"",MAX(IF('P2-Asset Valuation'!$E$7:$E$1006=$J$6,IF('P2-Asset Valuation'!$F$7:$F$1006="Confidentiality",'P2-Asset Valuation'!$I$7:$I$1006))),"")} | K28: {=IF(K27<>"",MAX(IF('P2-Asset Valuation'!$E$7:$E$1006=$K$6,IF('P2-Asset Valuation'!$F$7:$F$1006="Confidentiality",'P2-Asset Valuation'!$I$7:$I$1006))),"")} | L28: {=IF(L27<>"",MAX(IF('P2-Asset Valuation'!$E$7:$E$1006=$L$6,IF('P2-Asset Valuation'!$F$7:$F$1006="Confidentiality",'P2-Asset Valuation'!$I$7:$I$1006))),"")} | M28: {=IF(M27<>"",MAX(IF('P2-Asset Valuation'!$E$7:$E$1006=$M$6,IF('P2-Asset Valuation'!$F$7:$F$1006="Confidentiality",'P2-Asset Valuation'!$I$7:$I$1006))),"")} -> 0 | N28: C | O28: =SUM(D28:M28) -> 0
C29: I | D29: {=IF(D27<>"",MAX(IF('P2-Asset Valuation'!$E$7:$E$1006=$D$6,IF('P2-Asset Valuation'!$F$7:$F$1006="Integrity",'P2-Asset Valuation'!$I$7:$I$1006))),"")} -> 0 | E29: {=IF(E27<>"",MAX(IF('P2-Asset Valuation'!$E$7:$E$1006=$E$6,IF('P2-Asset Valuation'!$F$7:$F$1006="Integrity",'P2-Asset Valuation'!$I$7:$I$1006))),"")} | F29: {=IF(F27<>"",MAX(IF('P2-Asset Valuation'!$E$7:$E$1006=$F$6,IF('P2-Asset Valuation'!$F$7:$F$1006="Integrity",'P2-Asset Valuation'!$I$7:$I$1006))),"")} | G29: {=IF(G27<>"",MAX(IF('P2-Asset Valuation'!$E$7:$E$1006=$G$6,IF('P2-Asset Valuation'!$F$7:$F$1006="Integrity",'P2-Asset Valuation'!$I$7:$I$1006))),"")} | H29: {=IF(H27<>"",MAX(IF('P2-Asset Valuation'!$E$7:$E$1006=$H$6,IF('P2-Asset Valuation'!$F$7:$F$1006="Integrity",'P2-Asset Valuation'!$I$7:$I$1006))),"")} | I29: {=IF(I27<>"",MAX(IF('P2-Asset Valuation'!$E$7:$E$1006=$I$6,IF('P2-Asset Valuation'!$F$7:$F$1006="Integrity",'P2-Asset Valuation'!$I$7:$I$1006))),"")} | J29: {=IF(J27<>"",MAX(IF('P2-Asset Valuation'!$E$7:$E$1006=$J$6,IF('P2-Asset Valuation'!$F$7:$F$1006="Integrity",'P2-Asset Valuation'!$I$7:$I$1006))),"")} | K29: {=IF(K27<>"",MAX(IF('P2-Asset Valuation'!$E$7:$E$1006=$K$6,IF('P2-Asset Valuation'!$F$7:$F$1006="Integrity",'P2-Asset Valuation'!$I$7:$I$1006))),"")} | L29: {=IF(L27<>"",MAX(IF('P2-Asset Valuation'!$E$7:$E$1006=$L$6,IF('P2-Asset Valuation'!$F$7:$F$1006="Integrity",'P2-Asset Valuation'!$I$7:$I$1006))),"")} | M29: {=IF(M27<>"",MAX(IF('P2-Asset Valuation'!$E$7:$E$1006=$M$6,IF('P2-Asset Valuation'!$F$7:$F$1006="Integrity",'P2-Asset Valuation'!$I$7:$I$1006))),"")} -> 0 | N29: I | O29: =SUM(D29:M29) -> 0
C30: A | D30: {=IF(D27<>"",MAX(IF('P2-Asset Valuation'!$E$7:$E$1006=$D$6,IF('P2-Asset Valuation'!$F$7:$F$1006="Availability",'P2-Asset Valuation'!$I$7:$I$1006))),"")} -> 0 | E30: {=IF(E27<>"",MAX(IF('P2-Asset Valuation'!$E$7:$E$1006=$E$6,IF('P2-Asset Valuation'!$F$7:$F$1006="Availability",'P2-Asset Valuation'!$I$7:$I$1006))),"")} | F30: {=IF(F27<>"",MAX(IF('P2-Asset Valuation'!$E$7:$E$1006=$F$6,IF('P2-Asset Valuation'!$F$7:$F$1006="Availability",'P2-Asset Valuation'!$I$7:$I$1006))),"")} | G30: {=IF(G27<>"",MAX(IF('P2-Asset Valuation'!$E$7:$E$1006=$G$6,IF('P2-Asset Valuation'!$F$7:$F$1006="Availability",'P2-Asset Valuation'!$I$7:$I$1006))),"")} | H30: {=IF(H27<>"",MAX(IF('P2-Asset Valuation'!$E$7:$E$1006=$H$6,IF('P2-Asset Valuation'!$F$7:$F$1006="Availability",'P2-Asset Valuation'!$I$7:$I$1006))),"")} | I30: {=IF(I27<>"",MAX(IF('P2-Asset Valuation'!$E$7:$E$1006=$I$6,IF('P2-Asset Valuation'!$F$7:$F$1006="Availability",'P2-Asset Valuation'!$I$7:$I$1006))),"")} | J30: {=IF(J27<>"",MAX(IF('P2-Asset Valuation'!$E$7:$E$1006=$J$6,IF('P2-Asset Valuation'!$F$7:$F$1006="Availability",'P2-Asset Valuation'!$I$7:$I$1006))),"")} | K30: {=IF(K27<>"",MAX(IF('P2-Asset Valuation'!$E$7:$E$1006=$K$6,IF('P2-Asset Valuation'!$F$7:$F$1006="Availability",'P2-Asset Valuation'!$I$7:$I$1006))),"")} | L30: {=IF(L27<>"",MAX(IF('P2-Asset Valuation'!$E$7:$E$1006=$L$6,IF('P2-Asset Valuation'!$F$7:$F$1006="Availability",'P2-Asset Valuation'!$I$7:$I$1006))),"")} | M30: {=IF(M27<>"",MAX(IF('P2-Asset Valuation'!$E$7:$E$1006=$M$6,IF('P2-Asset Valuation'!$F$7:$F$1006="Availability",'P2-Asset Valuation'!$I$7:$I$1006))),"")} -> 0 | N30: A | O30: =SUM(D30:M30) -> 0
B31: Sup7 | C31: Dimension | E31: X | L31: X | N31: Dimension | O31: Value
C32: C | D32: {=IF(D31<>"",MAX(IF('P2-Asset Valuation'!$E$7:$E$1006=$D$6,IF('P2-Asset Valuation'!$F$7:$F$1006="Confidentiality",'P2-Asset Valuation'!$I$7:$I$1006))),"")} | E32: {=IF(E31<>"",MAX(IF('P2-Asset Valuation'!$E$7:$E$1006=$E$6,IF('P2-Asset Valuation'!$F$7:$F$1006="Confidentiality",'P2-Asset Valuation'!$I$7:$I$1006))),"")} -> 0 | F32: {=IF(F31<>"",MAX(IF('P2-Asset Valuation'!$E$7:$E$1006=$F$6,IF('P2-Asset Valuation'!$F$7:$F$1006="Confidentiality",'P2-Asset Valuation'!$I$7:$I$1006))),"")} | G32: {=IF(G31<>"",MAX(IF('P2-Asset Valuation'!$E$7:$E$1006=$G$6,IF('P2-Asset Valuation'!$F$7:$F$1006="Confidentiality",'P2-Asset Valuation'!$I$7:$I$1006))),"")} | H32: {=IF(H31<>"",MAX(IF('P2-Asset Valuation'!$E$7:$E$1006=$H$6,IF('P2-Asset Valuation'!$F$7:$F$1006="Confidentiality",'P2-Asset Valuation'!$I$7:$I$1006))),"")} | I32: {=IF(I31<>"",MAX(IF('P2-Asset Valuation'!$E$7:$E$1006=$I$6,IF('P2-Asset Valuation'!$F$7:$F$1006="Confidentiality",'P2-Asset Valuation'!$I$7:$I$1006))),"")} | J32: {=IF(J31<>"",MAX(IF('P2-Asset Valuation'!$E$7:$E$1006=$J$6,IF('P2-Asset Valuation'!$F$7:$F$1006="Confidentiality",'P2-Asset Valuation'!$I$7:$I$1006))),"")} | K32: {=IF(K31<>"",MAX(IF('P2-Asset Valuation'!$E$7:$E$1006=$K$6,IF('P2-Asset Valuation'!$F$7:$F$1006="Confidentiality",'P2-Asset Valuation'!$I$7:$I$1006))),"")} | L32: {=IF(L31<>"",MAX(IF('P2-Asset Valuation'!$E$7:$E$1006=$L$6,IF('P2-Asset Valuation'!$F$7:$F$1006="Confidentiality",'P2-Asset Valuation'!$I$7:$I$1006))),"")} -> 0 | M32: {=IF(M31<>"",MAX(IF('P2-Asset Valuation'!$E$7:$E$1006=$M$6,IF('P2-Asset Valuation'!$F$7:$F$1006="Confidentiality",'P2-Asset Valuation'!$I$7:$I$1006))),"")} | N32: C | O32: =SUM(D32:M32) -> 0
C33: I | D33: {=IF(D31<>"",MAX(IF('P2-Asset Valuation'!$E$7:$E$1006=$D$6,IF('P2-Asset Valuation'!$F$7:$F$1006="Integrity",'P2-Asset Valuation'!$I$7:$I$1006))),"")} | E33: {=IF(E31<>"",MAX(IF('P2-Asset Valuation'!$E$7:$E$1006=$E$6,IF('P2-Asset Valuation'!$F$7:$F$1006="Integrity",'P2-Asset Valuation'!$I$7:$I$1006))),"")} -> 0 | F33: {=IF(F31<>"",MAX(IF('P2-Asset Valuation'!$E$7:$E$1006=$F$6,IF('P2-Asset Valuation'!$F$7:$F$1006="Integrity",'P2-Asset Valuation'!$I$7:$I$1006))),"")} | G33: {=IF(G31<>"",MAX(IF('P2-Asset Valuation'!$E$7:$E$1006=$G$6,IF('P2-Asset Valuation'!$F$7:$F$1006="Integrity",'P2-Asset Valuation'!$I$7:$I$1006))),"")} | H33: {=IF(H31<>"",MAX(IF('P2-Asset Valuation'!$E$7:$E$1006=$H$6,IF('P2-Asset Valuation'!$F$7:$F$1006="Integrity",'P2-Asset Valuation'!$I$7:$I$1006))),"")} | I33: {=IF(I31<>"",MAX(IF('P2-Asset Valuation'!$E$7:$E$1006=$I$6,IF('P2-Asset Valuation'!$F$7:$F$1006="Integrity",'P2-Asset Valuation'!$I$7:$I$1006))),"")} | J33: {=IF(J31<>"",MAX(IF('P2-Asset Valuation'!$E$7:$E$1006=$J$6,IF('P2-Asset Valuation'!$F$7:$F$1006="Integrity",'P2-Asset Valuation'!$I$7:$I$1006))),"")} | K33: {=IF(K31<>"",MAX(IF('P2-Asset Valuation'!$E$7:$E$1006=$K$6,IF('P2-Asset Valuation'!$F$7:$F$1006="Integrity",'P2-Asset Valuation'!$I$7:$I$1006))),"")} | L33: {=IF(L31<>"",MAX(IF('P2-Asset Valuation'!$E$7:$E$1006=$L$6,IF('P2-Asset Valuation'!$F$7:$F$1006="Integrity",'P2-Asset Valuation'!$I$7:$I$1006))),"")} -> 0 | M33: {=IF(M31<>"",MAX(IF('P2-Asset Valuation'!$E$7:$E$1006=$M$6,IF('P2-Asset Valuation'!$F$7:$F$1006="Integrity",'P2-Asset Valuation'!$I$7:$I$1006))),"")} | N33: I | O33: =SUM(D33:M33) -> 0
C34: A | D34: {=IF(D31<>"",MAX(IF('P2-Asset Valuation'!$E$7:$E$1006=$D$6,IF('P2-Asset Valuation'!$F$7:$F$1006="Availability",'P2-Asset Valuation'!$I$7:$I$1006))),"")} | E34: {=IF(E31<>"",MAX(IF('P2-Asset Valuation'!$E$7:$E$1006=$E$6,IF('P2-Asset Valuation'!$F$7:$F$1006="Availability",'P2-Asset Valuation'!$I$7:$I$1006))),"")} -> 0 | F34: {=IF(F31<>"",MAX(IF('P2-Asset Valuation'!$E$7:$E$1006=$F$6,IF('P2-Asset Valuation'!$F$7:$F$1006="Availability",'P2-Asset Valuation'!$I$7:$I$1006))),"")} | G34: {=IF(G31<>"",MAX(IF('P2-Asset Valuation'!$E$7:$E$1006=$G$6,IF('P2-Asset Valuation'!$F$7:$F$1006="Availability",'P2-Asset Valuation'!$I$7:$I$1006))),"")} | H34: {=IF(H31<>"",MAX(IF('P2-Asset Valuation'!$E$7:$E$1006=$H$6,IF('P2-Asset Valuation'!$F$7:$F$1006="Availability",'P2-Asset Valuation'!$I$7:$I$1006))),"")} | I34: {=IF(I31<>"",MAX(IF('P2-Asset Valuation'!$E$7:$E$1006=$I$6,IF('P2-Asset Valuation'!$F$7:$F$1006="Availability",'P2-Asset Valuation'!$I$7:$I$1006))),"")} | J34: {=IF(J31<>"",MAX(IF('P2-Asset Valuation'!$E$7:$E$1006=$J$6,IF('P2-Asset Valuation'!$F$7:$F$1006="Availability",'P2-Asset Valuation'!$I$7:$I$1006))),"")} | K34: {=IF(K31<>"",MAX(IF('P2-Asset Valuation'!$E$7:$E$1006=$K$6,IF('P2-Asset Valuation'!$F$7:$F$1006="Availability",'P2-Asset Valuation'!$I$7:$I$1006))),"")} | L34: {=IF(L31<>"",MAX(IF('P2-Asset Valuation'!$E$7:$E$1006=$L$6,IF('P2-Asset Valuation'!$F$7:$F$1006="Availability",'P2-Asset Valuation'!$I$7:$I$1006))),"")} -> 0 | M34: {=IF(M31<>"",MAX(IF('P2-Asset Valuation'!$E$7:$E$1006=$M$6,IF('P2-Asset Valuation'!$F$7:$F$1006="Availability",'P2-Asset Valuation'!$I$7:$I$1006))),"")} | N34: A | O34: =SUM(D34:M34) -> 0
B35: Sup8 | C35: Dimension | F35: X | K35: X | N35: Dimension | O35: Value
C36: C | D36: {=IF(D35<>"",MAX(IF('P2-Asset Valuation'!$E$7:$E$1006=$D$6,IF('P2-Asset Valuation'!$F$7:$F$1006="Confidentiality",'P2-Asset Valuation'!$I$7:$I$1006))),"")} | E36: {=IF(E35<>"",MAX(IF('P2-Asset Valuation'!$E$7:$E$1006=$E$6,IF('P2-Asset Valuation'!$F$7:$F$1006="Confidentiality",'P2-Asset Valuation'!$I$7:$I$1006))),"")} | F36: {=IF(F35<>"",MAX(IF('P2-Asset Valuation'!$E$7:$E$1006=$F$6,IF('P2-Asset Valuation'!$F$7:$F$1006="Confidentiality",'P2-Asset Valuation'!$I$7:$I$1006))),"")} -> 0 | G36: {=IF(G35<>"",MAX(IF('P2-Asset Valuation'!$E$7:$E$1006=$G$6,IF('P2-Asset Valuation'!$F$7:$F$1006="Confidentiality",'P2-Asset Valuation'!$I$7:$I$1006))),"")} | H36: {=IF(H35<>"",MAX(IF('P2-Asset Valuation'!$E$7:$E$1006=$H$6,IF('P2-Asset Valuation'!$F$7:$F$1006="Confidentiality",'P2-Asset Valuation'!$I$7:$I$1006))),"")} | I36: {=IF(I35<>"",MAX(IF('P2-Asset Valuation'!$E$7:$E$1006=$I$6,IF('P2-Asset Valuation'!$F$7:$F$1006="Confidentiality",'P2-Asset Valuation'!$I$7:$I$1006))),"")} | J36: {=IF(J35<>"",MAX(IF('P2-Asset Valuation'!$E$7:$E$1006=$J$6,IF('P2-Asset Valuation'!$F$7:$F$1006="Confidentiality",'P2-Asset Valuation'!$I$7:$I$1006))),"")} | K36: {=IF(K35<>"",MAX(IF('P2-Asset Valuation'!$E$7:$E$1006=$K$6,IF('P2-Asset Valuation'!$F$7:$F$1006="Confidentiality",'P2-Asset Valuation'!$I$7:$I$1006))),"")} -> 0 | L36: {=IF(L35<>"",MAX(IF('P2-Asset Valuation'!$E$7:$E$1006=$L$6,IF('P2-Asset Valuation'!$F$7:$F$1006="Confidentiality",'P2-Asset Valuation'!$I$7:$I$1006))),"")} | M36: {=IF(M35<>"",MAX(IF('P2-Asset Valuation'!$E$7:$E$1006=$M$6,IF('P2-Asset Valuation'!$F$7:$F$1006="Confidentiality",'P2-Asset Valuation'!$I$7:$I$1006))),"")} | N36: C | O36: =SUM(D36:M36) -> 0
C37: I | D37: {=IF(D35<>"",MAX(IF('P2-Asset Valuation'!$E$7:$E$1006=$D$6,IF('P2-Asset Valuation'!$F$7:$F$1006="Integrity",'P2-Asset Valuation'!$I$7:$I$1006))),"")} | E37: {=IF(E35<>"",MAX(IF('P2-Asset Valuation'!$E$7:$E$1006=$E$6,IF('P2-Asset Valuation'!$F$7:$F$1006="Integrity",'P2-Asset Valuation'!$I$7:$I$1006))),"")} | F37: {=IF(F35<>"",MAX(IF('P2-Asset Valuation'!$E$7:$E$1006=$F$6,IF('P2-Asset Valuation'!$F$7:$F$1006="Integrity",'P2-Asset Valuation'!$I$7:$I$1006))),"")} -> 0 | G37: {=IF(G35<>"",MAX(IF('P2-Asset Valuation'!$E$7:$E$1006=$G$6,IF('P2-Asset Valuation'!$F$7:$F$1006="Integrity",'P2-Asset Valuation'!$I$7:$I$1006))),"")} | H37: {=IF(H35<>"",MAX(IF('P2-Asset Valuation'!$E$7:$E$1006=$H$6,IF('P2-Asset Valuation'!$F$7:$F$1006="Integrity",'P2-Asset Valuation'!$I$7:$I$1006))),"")} | I37: {=IF(I35<>"",MAX(IF('P2-Asset Valuation'!$E$7:$E$1006=$I$6,IF('P2-Asset Valuation'!$F$7:$F$1006="Integrity",'P2-Asset Valuation'!$I$7:$I$1006))),"")} | J37: {=IF(J35<>"",MAX(IF('P2-Asset Valuation'!$E$7:$E$1006=$J$6,IF('P2-Asset Valuation'!$F$7:$F$1006="Integrity",'P2-Asset Valuation'!$I$7:$I$1006))),"")} | K37: {=IF(K35<>"",MAX(IF('P2-Asset Valuation'!$E$7:$E$1006=$K$6,IF('P2-Asset Valuation'!$F$7:$F$1006="Integrity",'P2-Asset Valuation'!$I$7:$I$1006))),"")} -> 0 | L37: {=IF(L35<>"",MAX(IF('P2-Asset Valuation'!$E$7:$E$1006=$L$6,IF('P2-Asset Valuation'!$F$7:$F$1006="Integrity",'P2-Asset Valuation'!$I$7:$I$1006))),"")} | M37: {=IF(M35<>"",MAX(IF('P2-Asset Valuation'!$E$7:$E$1006=$M$6,IF('P2-Asset Valuation'!$F$7:$F$1006="Integrity",'P2-Asset Valuation'!$I$7:$I$1006))),"")} | N37: I | O37: =SUM(D37:M37) -> 0
C38: A | D38: {=IF(D35<>"",MAX(IF('P2-Asset Valuation'!$E$7:$E$1006=$D$6,IF('P2-Asset Valuation'!$F$7:$F$1006="Availability",'P2-Asset Valuation'!$I$7:$I$1006))),"")} | E38: {=IF(E35<>"",MAX(IF('P2-Asset Valuation'!$E$7:$E$1006=$E$6,IF('P2-Asset Valuation'!$F$7:$F$1006="Availability",'P2-Asset Valuation'!$I$7:$I$1006))),"")} | F38: {=IF(F35<>"",MAX(IF('P2-Asset Valuation'!$E$7:$E$1006=$F$6,IF('P2-Asset Valuation'!$F$7:$F$1006="Availability",'P2-Asset Valuation'!$I$7:$I$1006))),"")} -> 0 | G38: {=IF(G35<>"",MAX(IF('P2-Asset Valuation'!$E$7:$E$1006=$G$6,IF('P2-Asset Valuation'!$F$7:$F$1006="Availability",'P2-Asset Valuation'!$I$7:$I$1006))),"")} | H38: {=IF(H35<>"",MAX(IF('P2-Asset Valuation'!$E$7:$E$1006=$H$6,IF('P2-Asset Valuation'!$F$7:$F$1006="Availability",'P2-Asset Valuation'!$I$7:$I$1006))),"")} | I38: {=IF(I35<>"",MAX(IF('P2-Asset Valuation'!$E$7:$E$1006=$I$6,IF('P2-Asset Valuation'!$F$7:$F$1006="Availability",'P2-Asset Valuation'!$I$7:$I$1006))),"")} | J38: {=IF(J35<>"",MAX(IF('P2-Asset Valuation'!$E$7:$E$1006=$J$6,IF('P2-Asset Valuation'!$F$7:$F$1006="Availability",'P2-Asset Valuation'!$I$7:$I$1006))),"")} | K38: {=IF(K35<>"",MAX(IF('P2-Asset Valuation'!$E$7:$E$1006=$K$6,IF('P2-Asset Valuation'!$F$7:$F$1006="Availability",'P2-Asset Valuation'!$I$7:$I$1006))),"")} -> 0 | L38: {=IF(L35<>"",MAX(IF('P2-Asset Valuation'!$E$7:$E$1006=$L$6,IF('P2-Asset Valuation'!$F$7:$F$1006="Availability",'P2-Asset Valuation'!$I$7:$I$1006))),"")} | M38: {=IF(M35<>"",MAX(IF('P2-Asset Valuation'!$E$7:$E$1006=$M$6,IF('P2-Asset Valuation'!$F$7:$F$1006="Availability",'P2-Asset Valuation'!$I$7:$I$1006))),"")} | N38: A | O38: =SUM(D38:M38) -> 0
B39: Sup9 | C39: Dimension | G39: X | J39: X | N39: Dimension | O39: Value
C40: C | D40: {=IF(D39<>"",MAX(IF('P2-Asset Valuation'!$E$7:$E$1006=$D$6,IF('P2-Asset Valuation'!$F$7:$F$1006="Confidentiality",'P2-Asset Valuation'!$I$7:$I$1006))),"")} | E40: {=IF(E39<>"",MAX(IF('P2-Asset Valuation'!$E$7:$E$1006=$E$6,IF('P2-Asset Valuation'!$F$7:$F$1006="Confidentiality",'P2-Asset Valuation'!$I$7:$I$1006))),"")} | F40: {=IF(F39<>"",MAX(IF('P2-Asset Valuation'!$E$7:$E$1006=$F$6,IF('P2-Asset Valuation'!$F$7:$F$1006="Confidentiality",'P2-Asset Valuation'!$I$7:$I$1006))),"")} | G40: {=IF(G39<>"",MAX(IF('P2-Asset Valuation'!$E$7:$E$1006=$G$6,IF('P2-Asset Valuation'!$F$7:$F$1006="Confidentiality",'P2-Asset Valuation'!$I$7:$I$1006))),"")} -> 0 | H40: {=IF(H39<>"",MAX(IF('P2-Asset Valuation'!$E$7:$E$1006=$H$6,IF('P2-Asset Valuation'!$F$7:$F$1006="Confidentiality",'P2-Asset Valuation'!$I$7:$I$1006))),"")} | I40: {=IF(I39<>"",MAX(IF('P2-Asset Valuation'!$E$7:$E$1006=$I$6,IF('P2-Asset Valuation'!$F$7:$F$1006="Confidentiality",'P2-Asset Valuation'!$I$7:$I$1006))),"")} | J40: {=IF(J39<>"",MAX(IF('P2-Asset Valuation'!$E$7:$E$1006=$J$6,IF('P2-Asset Valuation'!$F$7:$F$1006="Confidentiality",'P2-Asset Valuation'!$I$7:$I$1006))),"")} -> 0 | K40: {=IF(K39<>"",MAX(IF('P2-Asset Valuation'!$E$7:$E$1006=$K$6,IF('P2-Asset Valuation'!$F$7:$F$1006="Confidentiality",'P2-Asset Valuation'!$I$7:$I$1006))),"")} | L40: {=IF(L39<>"",MAX(IF('P2-Asset Valuation'!$E$7:$E$1006=$L$6,IF('P2-Asset Valuation'!$F$7:$F$1006="Confidentiality",'P2-Asset Valuation'!$I$7:$I$1006))),"")} | M40: {=IF(M39<>"",MAX(IF('P2-Asset Valuation'!$E$7:$E$1006=$M$6,IF('P2-Asset Valuation'!$F$7:$F$1006="Confidentiality",'P2-Asset Valuation'!$I$7:$I$1006))),"")} | N40: C | O40: =SUM(D40:M40) -> 0
C41: I | D41: {=IF(D39<>"",MAX(IF('P2-Asset Valuation'!$E$7:$E$1006=$D$6,IF('P2-Asset Valuation'!$F$7:$F$1006="Integrity",'P2-Asset Valuation'!$I$7:$I$1006))),"")} | E41: {=IF(E39<>"",MAX(IF('P2-Asset Valuation'!$E$7:$E$1006=$E$6,IF('P2-Asset Valuation'!$F$7:$F$1006="Integrity",'P2-Asset Valuation'!$I$7:$I$1006))),"")} | F41: {=IF(F39<>"",MAX(IF('P2-Asset Valuation'!$E$7:$E$1006=$F$6,IF('P2-Asset Valuation'!$F$7:$F$1006="Integrity",'P2-Asset Valuation'!$I$7:$I$1006))),"")} | G41: {=IF(G39<>"",MAX(IF('P2-Asset Valuation'!$E$7:$E$1006=$G$6,IF('P2-Asset Valuation'!$F$7:$F$1006="Integrity",'P2-Asset Valuation'!$I$7:$I$1006))),"")} -> 0 | H41: {=IF(H39<>"",MAX(IF('P2-Asset Valuation'!$E$7:$E$1006=$H$6,IF('P2-Asset Valuation'!$F$7:$F$1006="Integrity",'P2-Asset Valuation'!$I$7:$I$1006))),"")} | I41: {=IF(I39<>"",MAX(IF('P2-Asset Valuation'!$E$7:$E$1006=$I$6,IF('P2-Asset Valuation'!$F$7:$F$1006="Integrity",'P2-Asset Valuation'!$I$7:$I$1006))),"")} | J41: {=IF(J39<>"",MAX(IF('P2-Asset Valuation'!$E$7:$E$1006=$J$6,IF('P2-Asset Valuation'!$F$7:$F$1006="Integrity",'P2-Asset Valuation'!$I$7:$I$1006))),"")} -> 0 | K41: {=IF(K39<>"",MAX(IF('P2-Asset Valuation'!$E$7:$E$1006=$K$6,IF('P2-Asset Valuation'!$F$7:$F$1006="Integrity",'P2-Asset Valuation'!$I$7:$I$1006))),"")} | L41: {=IF(L39<>"",MAX(IF('P2-Asset Valuation'!$E$7:$E$1006=$L$6,IF('P2-Asset Valuation'!$F$7:$F$1006="Integrity",'P2-Asset Valuation'!$I$7:$I$1006))),"")} | M41: {=IF(M39<>"",MAX(IF('P2-Asset Valuation'!$E$7:$E$1006=$M$6,IF('P2-Asset Valuation'!$F$7:$F$1006="Integrity",'P2-Asset Valuation'!$I$7:$I$1006))),"")} | N41: I | O41: =SUM(D41:M41) -> 0
C42: A | D42: {=IF(D39<>"",MAX(IF('P2-Asset Valuation'!$E$7:$E$1006=$D$6,IF('P2-Asset Valuation'!$F$7:$F$1006="Availability",'P2-Asset Valuation'!$I$7:$I$1006))),"")} | E42: {=IF(E39<>"",MAX(IF('P2-Asset Valuation'!$E$7:$E$1006=$E$6,IF('P2-Asset Valuation'!$F$7:$F$1006="Availability",'P2-Asset Valuation'!$I$7:$I$1006))),"")} | F42: {=IF(F39<>"",MAX(IF('P2-Asset Valuation'!$E$7:$E$1006=$F$6,IF('P2-Asset Valuation'!$F$7:$F$1006="Availability",'P2-Asset Valuation'!$I$7:$I$1006))),"")} | G42: {=IF(G39<>"",MAX(IF('P2-Asset Valuation'!$E$7:$E$1006=$G$6,IF('P2-Asset Valuation'!$F$7:$F$1006="Availability",'P2-Asset Valuation'!$I$7:$I$1006))),"")} -> 0 | H42: {=IF(H39<>"",MAX(IF('P2-Asset Valuation'!$E$7:$E$1006=$H$6,IF('P2-Asset Valuation'!$F$7:$F$1006="Availability",'P2-Asset Valuation'!$I$7:$I$1006))),"")} | I42: {=IF(I39<>"",MAX(IF('P2-Asset Valuation'!$E$7:$E$1006=$I$6,IF('P2-Asset Valuation'!$F$7:$F$1006="Availability",'P2-Asset Valuation'!$I$7:$I$1006))),"")} | J42: {=IF(J39<>"",MAX(IF('P2-Asset Valuation'!$E$7:$E$1006=$J$6,IF('P2-Asset Valuation'!$F$7:$F$1006="Availability",'P2-Asset Valuation'!$I$7:$I$1006))),"")} -> 0 | K42: {=IF(K39<>"",MAX(IF('P2-Asset Valuation'!$E$7:$E$1006=$K$6,IF('P2-Asset Valuation'!$F$7:$F$1006="Availability",'P2-Asset Valuation'!$I$7:$I$1006))),"")} | L42: {=IF(L39<>"",MAX(IF('P2-Asset Valuation'!$E$7:$E$1006=$L$6,IF('P2-Asset Valuation'!$F$7:$F$1006="Availability",'P2-Asset Valuation'!$I$7:$I$1006))),"")} | M42: {=IF(M39<>"",MAX(IF('P2-Asset Valuation'!$E$7:$E$1006=$M$6,IF('P2-Asset Valuation'!$F$7:$F$1006="Availability",'P2-Asset Valuation'!$I$7:$I$1006))),"")} | N42: A | O42: =SUM(D42:M42) -> 0
B43: Sup10 | C43: Dimension | D43: X | E43: X | F43: X | G43: X | H43: X | I43: X | J43: X | K43: X | L43: X | M43: X | N43: Dimension | O43: Value
C44: C | D44: {=IF(D43<>"",MAX(IF('P2-Asset Valuation'!$E$7:$E$1006=$D$6,IF('P2-Asset Valuation'!$F$7:$F$1006="Confidentiality",'P2-Asset Valuation'!$I$7:$I$1006))),"")} -> 0 | E44: {=IF(E43<>"",MAX(IF('P2-Asset Valuation'!$E$7:$E$1006=$E$6,IF('P2-Asset Valuation'!$F$7:$F$1006="Confidentiality",'P2-Asset Valuation'!$I$7:$I$1006))),"")} -> 0 | F44: {=IF(F43<>"",MAX(IF('P2-Asset Valuation'!$E$7:$E$1006=$F$6,IF('P2-Asset Valuation'!$F$7:$F$1006="Confidentiality",'P2-Asset Valuation'!$I$7:$I$1006))),"")} -> 0 | G44: {=IF(G43<>"",MAX(IF('P2-Asset Valuation'!$E$7:$E$1006=$G$6,IF('P2-Asset Valuation'!$F$7:$F$1006="Confidentiality",'P2-Asset Valuation'!$I$7:$I$1006))),"")} -> 0 | H44: {=IF(H43<>"",MAX(IF('P2-Asset Valuation'!$E$7:$E$1006=$H$6,IF('P2-Asset Valuation'!$F$7:$F$1006="Confidentiality",'P2-Asset Valuation'!$I$7:$I$1006))),"")} -> 0 | I44: {=IF(I43<>"",MAX(IF('P2-Asset Valuation'!$E$7:$E$1006=$I$6,IF('P2-Asset Valuation'!$F$7:$F$1006="Confidentiality",'P2-Asset Valuation'!$I$7:$I$1006))),"")} -> 0 | J44: {=IF(J43<>"",MAX(IF('P2-Asset Valuation'!$E$7:$E$1006=$J$6,IF('P2-Asset Valuation'!$F$7:$F$1006="Confidentiality",'P2-Asset Valuation'!$I$7:$I$1006))),"")} -> 0 | K44: {=IF(K43<>"",MAX(IF('P2-Asset Valuation'!$E$7:$E$1006=$K$6,IF('P2-Asset Valuation'!$F$7:$F$1006="Confidentiality",'P2-Asset Valuation'!$I$7:$I$1006))),"")} -> 0 | L44: {=IF(L43<>"",MAX(IF('P2-Asset Valuation'!$E$7:$E$1006=$L$6,IF('P2-Asset Valuation'!$F$7:$F$1006="Confidentiality",'P2-Asset Valuation'!$I$7:$I$1006))),"")} -> 0 | M44: {=IF(M43<>"",MAX(IF('P2-Asset Valuation'!$E$7:$E$1006=$M$6,IF('P2-Asset Valuation'!$F$7:$F$1006="Confidentiality",'P2-Asset Valuation'!$I$7:$I$1006))),"")} -> 0 | N44: C | O44: =SUM(D44:M44) -> 0
C45: I | D45: {=IF(D43<>"",MAX(IF('P2-Asset Valuation'!$E$7:$E$1006=$D$6,IF('P2-Asset Valuation'!$F$7:$F$1006="Integrity",'P2-Asset Valuation'!$I$7:$I$1006))),"")} -> 0 | E45: {=IF(E43<>"",MAX(IF('P2-Asset Valuation'!$E$7:$E$1006=$E$6,IF('P2-Asset Valuation'!$F$7:$F$1006="Integrity",'P2-Asset Valuation'!$I$7:$I$1006))),"")} -> 0 | F45: {=IF(F43<>"",MAX(IF('P2-Asset Valuation'!$E$7:$E$1006=$F$6,IF('P2-Asset Valuation'!$F$7:$F$1006="Integrity",'P2-Asset Valuation'!$I$7:$I$1006))),"")} -> 0 | G45: {=IF(G43<>"",MAX(IF('P2-Asset Valuation'!$E$7:$E$1006=$G$6,IF('P2-Asset Valuation'!$F$7:$F$1006="Integrity",'P2-Asset Valuation'!$I$7:$I$1006))),"")} -> 0 | H45: {=IF(H43<>"",MAX(IF('P2-Asset Valuation'!$E$7:$E$1006=$H$6,IF('P2-Asset Valuation'!$F$7:$F$1006="Integrity",'P2-Asset Valuation'!$I$7:$I$1006))),"")} -> 0 | I45: {=IF(I43<>"",MAX(IF('P2-Asset Valuation'!$E$7:$E$1006=$I$6,IF('P2-Asset Valuation'!$F$7:$F$1006="Integrity",'P2-Asset Valuation'!$I$7:$I$1006))),"")} -> 0 | J45: {=IF(J43<>"",MAX(IF('P2-Asset Valuation'!$E$7:$E$1006=$J$6,IF('P2-Asset Valuation'!$F$7:$F$1006="Integrity",'P2-Asset Valuation'!$I$7:$I$1006))),"")} -> 0 | K45: {=IF(K43<>"",MAX(IF('P2-Asset Valuation'!$E$7:$E$1006=$K$6,IF('P2-Asset Valuation'!$F$7:$F$1006="Integrity",'P2-Asset Valuation'!$I$7:$I$1006))),"")} -> 0 | L45: {=IF(L43<>"",MAX(IF('P2-Asset Valuation'!$E$7:$E$1006=$L$6,IF('P2-Asset Valuation'!$F$7:$F$1006="Integrity",'P2-Asset Valuation'!$I$7:$I$1006))),"")} -> 0 | M45: {=IF(M43<>"",MAX(IF('P2-Asset Valuation'!$E$7:$E$1006=$M$6,IF('P2-Asset Valuation'!$F$7:$F$1006="Integrity",'P2-Asset Valuation'!$I$7:$I$1006))),"")} -> 0 | N45: I | O45: =SUM(D45:M45) -> 0
C46: A | D46: {=IF(D43<>"",MAX(IF('P2-Asset Valuation'!$E$7:$E$1006=$D$6,IF('P2-Asset Valuation'!$F$7:$F$1006="Availability",'P2-Asset Valuation'!$I$7:$I$1006))),"")} -> 0 | E46: {=IF(E43<>"",MAX(IF('P2-Asset Valuation'!$E$7:$E$1006=$E$6,IF('P2-Asset Valuation'!$F$7:$F$1006="Availability",'P2-Asset Valuation'!$I$7:$I$1006))),"")} -> 0 | F46: {=IF(F43<>"",MAX(IF('P2-Asset Valuation'!$E$7:$E$1006=$F$6,IF('P2-Asset Valuation'!$F$7:$F$1006="Availability",'P2-Asset Valuation'!$I$7:$I$1006))),"")} -> 0 | G46: {=IF(G43<>"",MAX(IF('P2-Asset Valuation'!$E$7:$E$1006=$G$6,IF('P2-Asset Valuation'!$F$7:$F$1006="Availability",'P2-Asset Valuation'!$I$7:$I$1006))),"")} -> 0 | H46: {=IF(H43<>"",MAX(IF('P2-Asset Valuation'!$E$7:$E$1006=$H$6,IF('P2-Asset Valuation'!$F$7:$F$1006="Availability",'P2-Asset Valuation'!$I$7:$I$1006))),"")} -> 0 | I46: {=IF(I43<>"",MAX(IF('P2-Asset Valuation'!$E$7:$E$1006=$I$6,IF('P2-Asset Valuation'!$F$7:$F$1006="Availability",'P2-Asset Valuation'!$I$7:$I$1006))),"")} -> 0 | J46: {=IF(J43<>"",MAX(IF('P2-Asset Valuation'!$E$7:$E$1006=$J$6,IF('P2-Asset Valuation'!$F$7:$F$1006="Availability",'P2-Asset Valuation'!$I$7:$I$1006))),"")} -> 0 | K46: {=IF(K43<>"",MAX(IF('P2-Asset Valuation'!$E$7:$E$1006=$K$6,IF('P2-Asset Valuation'!$F$7:$F$1006="Availability",'P2-Asset Valuation'!$I$7:$I$1006))),"")} -> 0 | L46: {=IF(L43<>"",MAX(IF('P2-Asset Valuation'!$E$7:$E$1006=$L$6,IF('P2-Asset Valuation'!$F$7:$F$1006="Availability",'P2-Asset Valuation'!$I$7:$I$1006))),"")} -> 0 | M46: {=IF(M43<>"",MAX(IF('P2-Asset Valuation'!$E$7:$E$1006=$M$6,IF('P2-Asset Valuation'!$F$7:$F$1006="Availability",'P2-Asset Valuation'!$I$7:$I$1006))),"")} -> 0 | N46: A | O46: =SUM(D46:M46) -> 0
C47: Dimension | N47: Dimension | O47: Value
C48: C | D48: {=IF(D47<>"",MAX(IF('P2-Asset Valuation'!$E$7:$E$1006=$D$6,IF('P2-Asset Valuation'!$F$7:$F$1006="Confidentiality",'P2-Asset Valuation'!$I$7:$I$1006))),"")} | E48: {=IF(E47<>"",MAX(IF('P2-Asset Valuation'!$E$7:$E$1006=$E$6,IF('P2-Asset Valuation'!$F$7:$F$1006="Confidentiality",'P2-Asset Valuation'!$I$7:$I$1006))),"")} | F48: {=IF(F47<>"",MAX(IF('P2-Asset Valuation'!$E$7:$E$1006=$F$6,IF('P2-Asset Valuation'!$F$7:$F$1006="Confidentiality",'P2-Asset Valuation'!$I$7:$I$1006))),"")} | G48: {=IF(G47<>"",MAX(IF('P2-Asset Valuation'!$E$7:$E$1006=$G$6,IF('P2-Asset Valuation'!$F$7:$F$1006="Confidentiality",'P2-Asset Valuation'!$I$7:$I$1006))),"")} | H48: {=IF(H47<>"",MAX(IF('P2-Asset Valuation'!$E$7:$E$1006=$H$6,IF('P2-Asset Valuation'!$F$7:$F$1006="Confidentiality",'P2-Asset Valuation'!$I$7:$I$1006))),"")} | I48: {=IF(I47<>"",MAX(IF('P2-Asset Valuation'!$E$7:$E$1006=$I$6,IF('P2-Asset Valuation'!$F$7:$F$1006="Confidentiality",'P2-Asset Valuation'!$I$7:$I$1006))),"")} | J48: {=IF(J47<>"",MAX(IF('P2-Asset Valuation'!$E$7:$E$1006=$J$6,IF('P2-Asset Valuation'!$F$7:$F$1006="Confidentiality",'P2-Asset Valuation'!$I$7:$I$1006))),"")} | K48: {=IF(K47<>"",MAX(IF('P2-Asset Valuation'!$E$7:$E$1006=$K$6,IF('P2-Asset Valuation'!$F$7:$F$1006="Confidentiality",'P2-Asset Valuation'!$I$7:$I$1006))),"")} | L48: {=IF(L47<>"",MAX(IF('P2-Asset Valuation'!$E$7:$E$1006=$L$6,IF('P2-Asset Valuation'!$F$7:$F$1006="Confidentiality",'P2-Asset Valuation'!$I$7:$I$1006))),"")} | M48: {=IF(M47<>"",MAX(IF('P2-Asset Valuation'!$E$7:$E$1006=$M$6,IF('P2-Asset Valuation'!$F$7:$F$1006="Confidentiality",'P2-Asset Valuation'!$I$7:$I$1006))),"")} | N48: C | O48: =SUM(D48:M48) -> 0
C49: I | D49: {=IF(D47<>"",MAX(IF('P2-Asset Valuation'!$E$7:$E$1006=$D$6,IF('P2-Asset Valuation'!$F$7:$F$1006="Integrity",'P2-Asset Valuation'!$I$7:$I$1006))),"")} | E49: {=IF(E47<>"",MAX(IF('P2-Asset Valuation'!$E$7:$E$1006=$E$6,IF('P2-Asset Valuation'!$F$7:$F$1006="Integrity",'P2-Asset Valuation'!$I$7:$I$1006))),"")} | F49: {=IF(F47<>"",MAX(IF('P2-Asset Valuation'!$E$7:$E$1006=$F$6,IF('P2-Asset Valuation'!$F$7:$F$1006="Integrity",'P2-Asset Valuation'!$I$7:$I$1006))),"")} | G49: {=IF(G47<>"",MAX(IF('P2-Asset Valuation'!$E$7:$E$1006=$G$6,IF('P2-Asset Valuation'!$F$7:$F$1006="Integrity",'P2-Asset Valuation'!$I$7:$I$1006))),"")} | H49: {=IF(H47<>"",MAX(IF('P2-Asset Valuation'!$E$7:$E$1006=$H$6,IF('P2-Asset Valuation'!$F$7:$F$1006="Integrity",'P2-Asset Valuation'!$I$7:$I$1006))),"")} | I49: {=IF(I47<>"",MAX(IF('P2-Asset Valuation'!$E$7:$E$1006=$I$6,IF('P2-Asset Valuation'!$F$7:$F$1006="Integrity",'P2-Asset Valuation'!$I$7:$I$1006))),"")} | J49: {=IF(J47<>"",MAX(IF('P2-Asset Valuation'!$E$7:$E$1006=$J$6,IF('P2-Asset Valuation'!$F$7:$F$1006="Integrity",'P2-Asset Valuation'!$I$7:$I$1006))),"")} | K49: {=IF(K47<>"",MAX(IF('P2-Asset Valuation'!$E$7:$E$1006=$K$6,IF('P2-Asset Valuation'!$F$7:$F$1006="Integrity",'P2-Asset Valuation'!$I$7:$I$1006))),"")} | L49: {=IF(L47<>"",MAX(IF('P2-Asset Valuation'!$E$7:$E$1006=$L$6,IF('P2-Asset Valuation'!$F$7:$F$1006="Integrity",'P2-Asset Valuation'!$I$7:$I$1006))),"")} | M49: {=IF(M47<>"",MAX(IF('P2-Asset Valuation'!$E$7:$E$1006=$M$6,IF('P2-Asset Valuation'!$F$7:$F$1006="Integrity",'P2-Asset Valuation'!$I$7:$I$1006))),"")} | N49: I | O49: =SUM(D49:M49) -> 0
C50: A | D50: {=IF(D47<>"",MAX(IF('P2-Asset Valuation'!$E$7:$E$1006=$D$6,IF('P2-Asset Valuation'!$F$7:$F$1006="Availability",'P2-Asset Valuation'!$I$7:$I$1006))),"")} | E50: {=IF(E47<>"",MAX(IF('P2-Asset Valuation'!$E$7:$E$1006=$E$6,IF('P2-Asset Valuation'!$F$7:$F$1006="Availability",'P2-Asset Valuation'!$I$7:$I$1006))),"")} | F50: {=IF(F47<>"",MAX(IF('P2-Asset Valuation'!$E$7:$E$1006=$F$6,IF('P2-Asset Valuation'!$F$7:$F$1006="Availability",'P2-Asset Valuation'!$I$7:$I$1006))),"")} | G50: {=IF(G47<>"",MAX(IF('P2-Asset Valuation'!$E$7:$E$1006=$G$6,IF('P2-Asset Valuation'!$F$7:$F$1006="Availability",'P2-Asset Valuation'!$I$7:$I$1006))),"")} | H50: {=IF(H47<>"",MAX(IF('P2-Asset Valuation'!$E$7:$E$1006=$H$6,IF('P2-Asset Valuation'!$F$7:$F$1006="Availability",'P2-Asset Valuation'!$I$7:$I$1006))),"")} | I50: {=IF(I47<>"",MAX(IF('P2-Asset Valuation'!$E$7:$E$1006=$I$6,IF('P2-Asset Valuation'!$F$7:$F$1006="Availability",'P2-Asset Valuation'!$I$7:$I$1006))),"")} | J50: {=IF(J47<>"",MAX(IF('P2-Asset Valuation'!$E$7:$E$1006=$J$6,IF('P2-Asset Valuation'!$F$7:$F$1006="Availability",'P2-Asset Valuation'!$I$7:$I$1006))),"")} | K50: {=IF(K47<>"",MAX(IF('P2-Asset Valuation'!$E$7:$E$1006=$K$6,IF('P2-Asset Valuation'!$F$7:$F$1006="Availability",'P2-Asset Valuation'!$I$7:$I$1006))),"")} | L50: {=IF(L47<>"",MAX(IF('P2-Asset Valuation'!$E$7:$E$1006=$L$6,IF('P2-Asset Valuation'!$F$7:$F$1006="Availability",'P2-Asset Valuation'!$I$7:$I$1006))),"")} | M50: {=IF(M47<>"",MAX(IF('P2-Asset Valuation'!$E$7:$E$1006=$M$6,IF('P2-Asset Valuation'!$F$7:$F$1006="Availability",'P2-Asset Valuation'!$I$7:$I$1006))),"")} | N50: A | O50: =SUM(D50:M50) -> 0
C51: Dimension | N51: Dimension | O51: Value
C52: C | D52: {=IF(D51<>"",MAX(IF('P2-Asset Valuation'!$E$7:$E$1006=$D$6,IF('P2-Asset Valuation'!$F$7:$F$1006="Confidentiality",'P2-Asset Valuation'!$I$7:$I$1006))),"")} | E52: {=IF(E51<>"",MAX(IF('P2-Asset Valuation'!$E$7:$E$1006=$E$6,IF('P2-Asset Valuation'!$F$7:$F$1006="Confidentiality",'P2-Asset Valuation'!$I$7:$I$1006))),"")} | F52: {=IF(F51<>"",MAX(IF('P2-Asset Valuation'!$E$7:$E$1006=$F$6,IF('P2-Asset Valuation'!$F$7:$F$1006="Confidentiality",'P2-Asset Valuation'!$I$7:$I$1006))),"")} | G52: {=IF(G51<>"",MAX(IF('P2-Asset Valuation'!$E$7:$E$1006=$G$6,IF('P2-Asset Valuation'!$F$7:$F$1006="Confidentiality",'P2-Asset Valuation'!$I$7:$I$1006))),"")} | H52: {=IF(H51<>"",MAX(IF('P2-Asset Valuation'!$E$7:$E$1006=$H$6,IF('P2-Asset Valuation'!$F$7:$F$1006="Confidentiality",'P2-Asset Valuation'!$I$7:$I$1006))),"")} | I52: {=IF(I51<>"",MAX(IF('P2-Asset Valuation'!$E$7:$E$1006=$I$6,IF('P2-Asset Valuation'!$F$7:$F$1006="Confidentiality",'P2-Asset Valuation'!$I$7:$I$1006))),"")} | J52: {=IF(J51<>"",MAX(IF('P2-Asset Valuation'!$E$7:$E$1006=$J$6,IF('P2-Asset Valuation'!$F$7:$F$1006="Confidentiality",'P2-Asset Valuation'!$I$7:$I$1006))),"")} | K52: {=IF(K51<>"",MAX(IF('P2-Asset Valuation'!$E$7:$E$1006=$K$6,IF('P2-Asset Valuation'!$F$7:$F$1006="Confidentiality",'P2-Asset Valuation'!$I$7:$I$1006))),"")} | L52: {=IF(L51<>"",MAX(IF('P2-Asset Valuation'!$E$7:$E$1006=$L$6,IF('P2-Asset Valuation'!$F$7:$F$1006="Confidentiality",'P2-Asset Valuation'!$I$7:$I$1006))),"")} | M52: {=IF(M51<>"",MAX(IF('P2-Asset Valuation'!$E$7:$E$1006=$M$6,IF('P2-Asset Valuation'!$F$7:$F$1006="Confidentiality",'P2-Asset Valuation'!$I$7:$I$1006))),"")} | N52: C | O52: =SUM(D52:M52) -> 0
C53: I | D53: {=IF(D51<>"",MAX(IF('P2-Asset Valuation'!$E$7:$E$1006=$D$6,IF('P2-Asset Valuation'!$F$7:$F$1006="Integrity",'P2-Asset Valuation'!$I$7:$I$1006))),"")} | E53: {=IF(E51<>"",MAX(IF('P2-Asset Valuation'!$E$7:$E$1006=$E$6,IF('P2-Asset Valuation'!$F$7:$F$1006="Integrity",'P2-Asset Valuation'!$I$7:$I$1006))),"")} | F53: {=IF(F51<>"",MAX(IF('P2-Asset Valuation'!$E$7:$E$1006=$F$6,IF('P2-Asset Valuation'!$F$7:$F$1006="Integrity",'P2-Asset Valuation'!$I$7:$I$1006))),"")} | G53: {=IF(G51<>"",MAX(IF('P2-Asset Valuation'!$E$7:$E$1006=$G$6,IF('P2-Asset Valuation'!$F$7:$F$1006="Integrity",'P2-Asset Valuation'!$I$7:$I$1006))),"")} | H53: {=IF(H51<>"",MAX(IF('P2-Asset Valuation'!$E$7:$E$1006=$H$6,IF('P2-Asset Valuation'!$F$7:$F$1006="Integrity",'P2-Asset Valuation'!$I$7:$I$1006))),"")} | I53: {=IF(I51<>"",MAX(IF('P2-Asset Valuation'!$E$7:$E$1006=$I$6,IF('P2-Asset Valuation'!$F$7:$F$1006="Integrity",'P2-Asset Valuation'!$I$7:$I$1006))),"")} | J53: {=IF(J51<>"",MAX(IF('P2-Asset Valuation'!$E$7:$E$1006=$J$6,IF('P2-Asset Valuation'!$F$7:$F$1006="Integrity",'P2-Asset Valuation'!$I$7:$I$1006))),"")} | K53: {=IF(K51<>"",MAX(IF('P2-Asset Valuation'!$E$7:$E$1006=$K$6,IF('P2-Asset Valuation'!$F$7:$F$1006="Integrity",'P2-Asset Valuation'!$I$7:$I$1006))),"")} | L53: {=IF(L51<>"",MAX(IF('P2-Asset Valuation'!$E$7:$E$1006=$L$6,IF('P2-Asset Valuation'!$F$7:$F$1006="Integrity",'P2-Asset Valuation'!$I$7:$I$1006))),"")} | M53: {=IF(M51<>"",MAX(IF('P2-Asset Valuation'!$E$7:$E$1006=$M$6,IF('P2-Asset Valuation'!$F$7:$F$1006="Integrity",'P2-Asset Valuation'!$I$7:$I$1006))),"")} | N53: I | O53: =SUM(D53:M53) -> 0
C54: A | D54: {=IF(D51<>"",MAX(IF('P2-Asset Valuation'!$E$7:$E$1006=$D$6,IF('P2-Asset Valuation'!$F$7:$F$1006="Availability",'P2-Asset Valuation'!$I$7:$I$1006))),"")} | E54: {=IF(E51<>"",MAX(IF('P2-Asset Valuation'!$E$7:$E$1006=$E$6,IF('P2-Asset Valuation'!$F$7:$F$1006="Availability",'P2-Asset Valuation'!$I$7:$I$1006))),"")} | F54: {=IF(F51<>"",MAX(IF('P2-Asset Valuation'!$E$7:$E$1006=$F$6,IF('P2-Asset Valuation'!$F$7:$F$1006="Availability",'P2-Asset Valuation'!$I$7:$I$1006))),"")} | G54: {=IF(G51<>"",MAX(IF('P2-Asset Valuation'!$E$7:$E$1006=$G$6,IF('P2-Asset Valuation'!$F$7:$F$1006="Availability",'P2-Asset Valuation'!$I$7:$I$1006))),"")} | H54: {=IF(H51<>"",MAX(IF('P2-Asset Valuation'!$E$7:$E$1006=$H$6,IF('P2-Asset Valuation'!$F$7:$F$1006="Availability",'P2-Asset Valuation'!$I$7:$I$1006))),"")} | I54: {=IF(I51<>"",MAX(IF('P2-Asset Valuation'!$E$7:$E$1006=$I$6,IF('P2-Asset Valuation'!$F$7:$F$1006="Availability",'P2-Asset Valuation'!$I$7:$I$1006))),"")} | J54: {=IF(J51<>"",MAX(IF('P2-Asset Valuation'!$E$7:$E$1006=$J$6,IF('P2-Asset Valuation'!$F$7:$F$1006="Availability",'P2-Asset Valuation'!$I$7:$I$1006))),"")} | K54: {=IF(K51<>"",MAX(IF('P2-Asset Valuation'!$E$7:$E$1006=$K$6,IF('P2-Asset Valuation'!$F$7:$F$1006="Availability",'P2-Asset Valuation'!$I$7:$I$1006))),"")} | L54: {=IF(L51<>"",MAX(IF('P2-Asset Valuation'!$E$7:$E$1006=$L$6,IF('P2-Asset Valuation'!$F$7:$F$1006="Availability",'P2-Asset Valuation'!$I$7:$I$1006))),"")} | M54: {=IF(M51<>"",MAX(IF('P2-Asset Valuation'!$E$7:$E$1006=$M$6,IF('P2-Asset Valuation'!$F$7:$F$1006="Availability",'P2-Asset Valuation'!$I$7:$I$1006))),"")} | N54: A | O54: =SUM(D54:M54) -> 0
C55: Dimension | N55: Dimension | O55: Value
C56: C | D56: {=IF(D55<>"",MAX(IF('P2-Asset Valuation'!$E$7:$E$1006=$D$6,IF('P2-Asset Valuation'!$F$7:$F$1006="Confidentiality",'P2-Asset Valuation'!$I$7:$I$1006))),"")} | E56: {=IF(E55<>"",MAX(IF('P2-Asset Valuation'!$E$7:$E$1006=$E$6,IF('P2-Asset Valuation'!$F$7:$F$1006="Confidentiality",'P2-Asset Valuation'!$I$7:$I$1006))),"")} | F56: {=IF(F55<>"",MAX(IF('P2-Asset Valuation'!$E$7:$E$1006=$F$6,IF('P2-Asset Valuation'!$F$7:$F$1006="Confidentiality",'P2-Asset Valuation'!$I$7:$I$1006))),"")} | G56: {=IF(G55<>"",MAX(IF('P2-Asset Valuation'!$E$7:$E$1006=$G$6,IF('P2-Asset Valuation'!$F$7:$F$1006="Confidentiality",'P2-Asset Valuation'!$I$7:$I$1006))),"")} | H56: {=IF(H55<>"",MAX(IF('P2-Asset Valuation'!$E$7:$E$1006=$H$6,IF('P2-Asset Valuation'!$F$7:$F$1006="Confidentiality",'P2-Asset Valuation'!$I$7:$I$1006))),"")} | I56: {=IF(I55<>"",MAX(IF('P2-Asset Valuation'!$E$7:$E$1006=$I$6,IF('P2-Asset Valuation'!$F$7:$F$1006="Confidentiality",'P2-Asset Valuation'!$I$7:$I$1006))),"")} | J56: {=IF(J55<>"",MAX(IF('P2-Asset Valuation'!$E$7:$E$1006=$J$6,IF('P2-Asset Valuation'!$F$7:$F$1006="Confidentiality",'P2-Asset Valuation'!$I$7:$I$1006))),"")} | K56: {=IF(K55<>"",MAX(IF('P2-Asset Valuation'!$E$7:$E$1006=$K$6,IF('P2-Asset Valuation'!$F$7:$F$1006="Confidentiality",'P2-Asset Valuation'!$I$7:$I$1006))),"")} | L56: {=IF(L55<>"",MAX(IF('P2-Asset Valuation'!$E$7:$E$1006=$L$6,IF('P2-Asset Valuation'!$F$7:$F$1006="Confidentiality",'P2-Asset Valuation'!$I$7:$I$1006))),"")} | M56: {=IF(M55<>"",MAX(IF('P2-Asset Valuation'!$E$7:$E$1006=$M$6,IF('P2-Asset Valuation'!$F$7:$F$1006="Confidentiality",'P2-Asset Valuation'!$I$7:$I$1006))),"")} | N56: C | O56: =SUM(D56:M56) -> 0
C57: I | D57: {=IF(D55<>"",MAX(IF('P2-Asset Valuation'!$E$7:$E$1006=$D$6,IF('P2-Asset Valuation'!$F$7:$F$1006="Integrity",'P2-Asset Valuation'!$I$7:$I$1006))),"")} | E57: {=IF(E55<>"",MAX(IF('P2-Asset Valuation'!$E$7:$E$1006=$E$6,IF('P2-Asset Valuation'!$F$7:$F$1006="Integrity",'P2-Asset Valuation'!$I$7:$I$1006))),"")} | F57: {=IF(F55<>"",MAX(IF('P2-Asset Valuation'!$E$7:$E$1006=$F$6,IF('P2-Asset Valuation'!$F$7:$F$1006="Integrity",'P2-Asset Valuation'!$I$7:$I$1006))),"")} | G57: {=IF(G55<>"",MAX(IF('P2-Asset Valuation'!$E$7:$E$1006=$G$6,IF('P2-Asset Valuation'!$F$7:$F$1006="Integrity",'P2-Asset Valuation'!$I$7:$I$1006))),"")} | H57: {=IF(H55<>"",MAX(IF('P2-Asset Valuation'!$E$7:$E$1006=$H$6,IF('P2-Asset Valuation'!$F$7:$F$1006="Integrity",'P2-Asset Valuation'!$I$7:$I$1006))),"")} | I57: {=IF(I55<>"",MAX(IF('P2-Asset Valuation'!$E$7:$E$1006=$I$6,IF('P2-Asset Valuation'!$F$7:$F$1006="Integrity",'P2-Asset Valuation'!$I$7:$I$1006))),"")} | J57: {=IF(J55<>"",MAX(IF('P2-Asset Valuation'!$E$7:$E$1006=$J$6,IF('P2-Asset Valuation'!$F$7:$F$1006="Integrity",'P2-Asset Valuation'!$I$7:$I$1006))),"")} | K57: {=IF(K55<>"",MAX(IF('P2-Asset Valuation'!$E$7:$E$1006=$K$6,IF('P2-Asset Valuation'!$F$7:$F$1006="Integrity",'P2-Asset Valuation'!$I$7:$I$1006))),"")} | L57: {=IF(L55<>"",MAX(IF('P2-Asset Valuation'!$E$7:$E$1006=$L$6,IF('P2-Asset Valuation'!$F$7:$F$1006="Integrity",'P2-Asset Valuation'!$I$7:$I$1006))),"")} | M57: {=IF(M55<>"",MAX(IF('P2-Asset Valuation'!$E$7:$E$1006=$M$6,IF('P2-Asset Valuation'!$F$7:$F$1006="Integrity",'P2-Asset Valuation'!$I$7:$I$1006))),"")} | N57: I | O57: =SUM(D57:M57) -> 0
C58: A | D58: {=IF(D55<>"",MAX(IF('P2-Asset Valuation'!$E$7:$E$1006=$D$6,IF('P2-Asset Valuation'!$F$7:$F$1006="Availability",'P2-Asset Valuation'!$I$7:$I$1006))),"")} | E58: {=IF(E55<>"",MAX(IF('P2-Asset Valuation'!$E$7:$E$1006=$E$6,IF('P2-Asset Valuation'!$F$7:$F$1006="Availability",'P2-Asset Valuation'!$I$7:$I$1006))),"")} | F58: {=IF(F55<>"",MAX(IF('P2-Asset Valuation'!$E$7:$E$1006=$F$6,IF('P2-Asset Valuation'!$F$7:$F$1006="Availability",'P2-Asset Valuation'!$I$7:$I$1006))),"")} | G58: {=IF(G55<>"",MAX(IF('P2-Asset Valuation'!$E$7:$E$1006=$G$6,IF('P2-Asset Valuation'!$F$7:$F$1006="Availability",'P2-Asset Valuation'!$I$7:$I$1006))),"")} | H58: {=IF(H55<>"",MAX(IF('P2-Asset Valuation'!$E$7:$E$1006=$H$6,IF('P2-Asset Valuation'!$F$7:$F$1006="Availability",'P2-Asset Valuation'!$I$7:$I$1006))),"")} | I58: {=IF(I55<>"",MAX(IF('P2-Asset Valuation'!$E$7:$E$1006=$I$6,IF('P2-Asset Valuation'!$F$7:$F$1006="Availability",'P2-Asset Valuation'!$I$7:$I$1006))),"")} | J58: {=IF(J55<>"",MAX(IF('P2-Asset Valuation'!$E$7:$E$1006=$J$6,IF('P2-Asset Valuation'!$F$7:$F$1006="Availability",'P2-Asset Valuation'!$I$7:$I$1006))),"")} | K58: {=IF(K55<>"",MAX(IF('P2-Asset Valuation'!$E$7:$E$1006=$K$6,IF('P2-Asset Valuation'!$F$7:$F$1006="Availability",'P2-Asset Valuation'!$I$7:$I$1006))),"")} | L58: {=IF(L55<>"",MAX(IF('P2-Asset Valuation'!$E$7:$E$1006=$L$6,IF('P2-Asset Valuation'!$F$7:$F$1006="Availability",'P2-Asset Valuation'!$I$7:$I$1006))),"")} | M58: {=IF(M55<>"",MAX(IF('P2-Asset Valuation'!$E$7:$E$1006=$M$6,IF('P2-Asset Valuation'!$F$7:$F$1006="Availability",'P2-Asset Valuation'!$I$7:$I$1006))),"")} | N58: A | O58: =SUM(D58:M58) -> 0
C59: Dimension | N59: Dimension | O59: Value
C60: C | D60: {=IF(D59<>"",MAX(IF('P2-Asset Valuation'!$E$7:$E$1006=$D$6,IF('P2-Asset Valuation'!$F$7:$F$1006="Confidentiality",'P2-Asset Valuation'!$I$7:$I$1006))),"")} | E60: {=IF(E59<>"",MAX(IF('P2-Asset Valuation'!$E$7:$E$1006=$E$6,IF('P2-Asset Valuation'!$F$7:$F$1006="Confidentiality",'P2-Asset Valuation'!$I$7:$I$1006))),"")} | F60: {=IF(F59<>"",MAX(IF('P2-Asset Valuation'!$E$7:$E$1006=$F$6,IF('P2-Asset Valuation'!$F$7:$F$1006="Confidentiality",'P2-Asset Valuation'!$I$7:$I$1006))),"")} | G60: {=IF(G59<>"",MAX(IF('P2-Asset Valuation'!$E$7:$E$1006=$G$6,IF('P2-Asset Valuation'!$F$7:$F$1006="Confidentiality",'P2-Asset Valuation'!$I$7:$I$1006))),"")} | H60: {=IF(H59<>"",MAX(IF('P2-Asset Valuation'!$E$7:$E$1006=$H$6,IF('P2-Asset Valuation'!$F$7:$F$1006="Confidentiality",'P2-Asset Valuation'!$I$7:$I$1006))),"")} | I60: {=IF(I59<>"",MAX(IF('P2-Asset Valuation'!$E$7:$E$1006=$I$6,IF('P2-Asset Valuation'!$F$7:$F$1006="Confidentiality",'P2-Asset Valuation'!$I$7:$I$1006))),"")} | J60: {=IF(J59<>"",MAX(IF('P2-Asset Valuation'!$E$7:$E$1006=$J$6,IF('P2-Asset Valuation'!$F$7:$F$1006="Confidentiality",'P2-Asset Valuation'!$I$7:$I$1006))),"")} | K60: {=IF(K59<>"",MAX(IF('P2-Asset Valuation'!$E$7:$E$1006=$K$6,IF('P2-Asset Valuation'!$F$7:$F$1006="Confidentiality",'P2-Asset Valuation'!$I$7:$I$1006))),"")} | L60: {=IF(L59<>"",MAX(IF('P2-Asset Valuation'!$E$7:$E$1006=$L$6,IF('P2-Asset Valuation'!$F$7:$F$1006="Confidentiality",'P2-Asset Valuation'!$I$7:$I$1006))),"")} | M60: {=IF(M59<>"",MAX(IF('P2-Asset Valuation'!$E$7:$E$1006=$M$6,IF('P2-Asset Valuation'!$F$7:$F$1006="Confidentiality",'P2-Asset Valuation'!$I$7:$I$1006))),"")} | N60: C | O60: =SUM(D60:M60) -> 0
C61: I | D61: {=IF(D59<>"",MAX(IF('P2-Asset Valuation'!$E$7:$E$1006=$D$6,IF('P2-Asset Valuation'!$F$7:$F$1006="Integrity",'P2-Asset Valuation'!$I$7:$I$1006))),"")} | E61: {=IF(E59<>"",MAX(IF('P2-Asset Valuation'!$E$7:$E$1006=$E$6,IF('P2-Asset Valuation'!$F$7:$F$1006="Integrity",'P2-Asset Valuation'!$I$7:$I$1006))),"")} | F61: {=IF(F59<>"",MAX(IF('P2-Asset Valuation'!$E$7:$E$1006=$F$6,IF('P2-Asset Valuation'!$F$7:$F$1006="Integrity",'P2-Asset Valuation'!$I$7:$I$1006))),"")} | G61: {=IF(G59<>"",MAX(IF('P2-Asset Valuation'!$E$7:$E$1006=$G$6,IF('P2-Asset Valuation'!$F$7:$F$1006="Integrity",'P2-Asset Valuation'!$I$7:$I$1006))),"")} | H61: {=IF(H59<>"",MAX(IF('P2-Asset Valuation'!$E$7:$E$1006=$H$6,IF('P2-Asset Valuation'!$F$7:$F$1006="Integrity",'P2-Asset Valuation'!$I$7:$I$1006))),"")} | I61: {=IF(I59<>"",MAX(IF('P2-Asset Valuation'!$E$7:$E$1006=$I$6,IF('P2-Asset Valuation'!$F$7:$F$1006="Integrity",'P2-Asset Valuation'!$I$7:$I$1006))),"")} | J61: {=IF(J59<>"",MAX(IF('P2-Asset Valuation'!$E$7:$E$1006=$J$6,IF('P2-Asset Valuation'!$F$7:$F$1006="Integrity",'P2-Asset Valuation'!$I$7:$I$1006))),"")} | K61: {=IF(K59<>"",MAX(IF('P2-Asset Valuation'!$E$7:$E$1006=$K$6,IF('P2-Asset Valuation'!$F$7:$F$1006="Integrity",'P2-Asset Valuation'!$I$7:$I$1006))),"")} | L61: {=IF(L59<>"",MAX(IF('P2-Asset Valuation'!$E$7:$E$1006=$L$6,IF('P2-Asset Valuation'!$F$7:$F$1006="Integrity",'P2-Asset Valuation'!$I$7:$I$1006))),"")} | M61: {=IF(M59<>"",MAX(IF('P2-Asset Valuation'!$E$7:$E$1006=$M$6,IF('P2-Asset Valuation'!$F$7:$F$1006="Integrity",'P2-Asset Valuation'!$I$7:$I$1006))),"")} | N61: I | O61: =SUM(D61:M61) -> 0
C62: A | D62: {=IF(D59<>"",MAX(IF('P2-Asset Valuation'!$E$7:$E$1006=$D$6,IF('P2-Asset Valuation'!$F$7:$F$1006="Availability",'P2-Asset Valuation'!$I$7:$I$1006))),"")} | E62: {=IF(E59<>"",MAX(IF('P2-Asset Valuation'!$E$7:$E$1006=$E$6,IF('P2-Asset Valuation'!$F$7:$F$1006="Availability",'P2-Asset Valuation'!$I$7:$I$1006))),"")} | F62: {=IF(F59<>"",MAX(IF('P2-Asset Valuation'!$E$7:$E$1006=$F$6,IF('P2-Asset Valuation'!$F$7:$F$1006="Availability",'P2-Asset Valuation'!$I$7:$I$1006))),"")} | G62: {=IF(G59<>"",MAX(IF('P2-Asset Valuation'!$E$7:$E$1006=$G$6,IF('P2-Asset Valuation'!$F$7:$F$1006="Availability",'P2-Asset Valuation'!$I$7:$I$1006))),"")} | H62: {=IF(H59<>"",MAX(IF('P2-Asset Valuation'!$E$7:$E$1006=$H$6,IF('P2-Asset Valuation'!$F$7:$F$1006="Availability",'P2-Asset Valuation'!$I$7:$I$1006))),"")} | I62: {=IF(I59<>"",MAX(IF('P2-Asset Valuation'!$E$7:$E$1006=$I$6,IF('P2-Asset Valuation'!$F$7:$F$1006="Availability",'P2-Asset Valuation'!$I$7:$I$1006))),"")} | J62: {=IF(J59<>"",MAX(IF('P2-Asset Valuation'!$E$7:$E$1006=$J$6,IF('P2-Asset Valuation'!$F$7:$F$1006="Availability",'P2-Asset Valuation'!$I$7:$I$1006))),"")} | K62: {=IF(K59<>"",MAX(IF('P2-Asset Valuation'!$E$7:$E$1006=$K$6,IF('P2-Asset Valuation'!$F$7:$F$1006="Availability",'P2-Asset Valuation'!$I$7:$I$1006))),"")} | L62: {=IF(L59<>"",MAX(IF('P2-Asset Valuation'!$E$7:$E$1006=$L$6,IF('P2-Asset Valuation'!$F$7:$F$1006="Availability",'P2-Asset Valuation'!$I$7:$I$1006))),"")} | M62: {=IF(M59<>"",MAX(IF('P2-Asset Valuation'!$E$7:$E$1006=$M$6,IF('P2-Asset Valuation'!$F$7:$F$1006="Availability",'P2-Asset Valuation'!$I$7:$I$1006))),"")} | N62: A | O62: =SUM(D62:M62) -> 0
C63: Dimension | N63: Dimension | O63: Value
C64: C | D64: {=IF(D63<>"",MAX(IF('P2-Asset Valuation'!$E$7:$E$1006=$D$6,IF('P2-Asset Valuation'!$F$7:$F$1006="Confidentiality",'P2-Asset Valuation'!$I$7:$I$1006))),"")} | E64: {=IF(E63<>"",MAX(IF('P2-Asset Valuation'!$E$7:$E$1006=$E$6,IF('P2-Asset Valuation'!$F$7:$F$1006="Confidentiality",'P2-Asset Valuation'!$I$7:$I$1006))),"")} | F64: {=IF(F63<>"",MAX(IF('P2-Asset Valuation'!$E$7:$E$1006=$F$6,IF('P2-Asset Valuation'!$F$7:$F$1006="Confidentiality",'P2-Asset Valuation'!$I$7:$I$1006))),"")} | G64: {=IF(G63<>"",MAX(IF('P2-Asset Valuation'!$E$7:$E$1006=$G$6,IF('P2-Asset Valuation'!$F$7:$F$1006="Confidentiality",'P2-Asset Valuation'!$I$7:$I$1006))),"")} | H64: {=IF(H63<>"",MAX(IF('P2-Asset Valuation'!$E$7:$E$1006=$H$6,IF('P2-Asset Valuation'!$F$7:$F$1006="Confidentiality",'P2-Asset Valuation'!$I$7:$I$1006))),"")} | I64: {=IF(I63<>"",MAX(IF('P2-Asset Valuation'!$E$7:$E$1006=$I$6,IF('P2-Asset Valuation'!$F$7:$F$1006="Confidentiality",'P2-Asset Valuation'!$I$7:$I$1006))),"")} | J64: {=IF(J63<>"",MAX(IF('P2-Asset Valuation'!$E$7:$E$1006=$J$6,IF('P2-Asset Valuation'!$F$7:$F$1006="Confidentiality",'P2-Asset Valuation'!$I$7:$I$1006))),"")} | K64: {=IF(K63<>"",MAX(IF('P2-Asset Valuation'!$E$7:$E$1006=$K$6,IF('P2-Asset Valuation'!$F$7:$F$1006="Confidentiality",'P2-Asset Valuation'!$I$7:$I$1006))),"")} | L64: {=IF(L63<>"",MAX(IF('P2-Asset Valuation'!$E$7:$E$1006=$L$6,IF('P2-Asset Valuation'!$F$7:$F$1006="Confidentiality",'P2-Asset Valuation'!$I$7:$I$1006))),"")} | M64: {=IF(M63<>"",MAX(IF('P2-Asset Valuation'!$E$7:$E$1006=$M$6,IF('P2-Asset Valuation'!$F$7:$F$1006="Confidentiality",'P2-Asset Valuation'!$I$7:$I$1006))),"")} | N64: C | O64: =SUM(D64:M64) -> 0
C65: I | D65: {=IF(D63<>"",MAX(IF('P2-Asset Valuation'!$E$7:$E$1006=$D$6,IF('P2-Asset Valuation'!$F$7:$F$1006="Integrity",'P2-Asset Valuation'!$I$7:$I$1006))),"")} | E65: {=IF(E63<>"",MAX(IF('P2-Asset Valuation'!$E$7:$E$1006=$E$6,IF('P2-Asset Valuation'!$F$7:$F$1006="Integrity",'P2-Asset Valuation'!$I$7:$I$1006))),"")} | F65: {=IF(F63<>"",MAX(IF('P2-Asset Valuation'!$E$7:$E$1006=$F$6,IF('P2-Asset Valuation'!$F$7:$F$1006="Integrity",'P2-Asset Valuation'!$I$7:$I$1006))),"")} | G65: {=IF(G63<>"",MAX(IF('P2-Asset Valuation'!$E$7:$E$1006=$G$6,IF('P2-Asset Valuation'!$F$7:$F$1006="Integrity",'P2-Asset Valuation'!$I$7:$I$1006))),"")} | H65: {=IF(H63<>"",MAX(IF('P2-Asset Valuation'!$E$7:$E$1006=$H$6,IF('P2-Asset Valuation'!$F$7:$F$1006="Integrity",'P2-Asset Valuation'!$I$7:$I$1006))),"")} | I65: {=IF(I63<>"",MAX(IF('P2-Asset Valuation'!$E$7:$E$1006=$I$6,IF('P2-Asset Valuation'!$F$7:$F$1006="Integrity",'P2-Asset Valuation'!$I$7:$I$1006))),"")} | J65: {=IF(J63<>"",MAX(IF('P2-Asset Valuation'!$E$7:$E$1006=$J$6,IF('P2-Asset Valuation'!$F$7:$F$1006="Integrity",'P2-Asset Valuation'!$I$7:$I$1006))),"")} | K65: {=IF(K63<>"",MAX(IF('P2-Asset Valuation'!$E$7:$E$1006=$K$6,IF('P2-Asset Valuation'!$F$7:$F$1006="Integrity",'P2-Asset Valuation'!$I$7:$I$1006))),"")} | L65: {=IF(L63<>"",MAX(IF('P2-Asset Valuation'!$E$7:$E$1006=$L$6,IF('P2-Asset Valuation'!$F$7:$F$1006="Integrity",'P2-Asset Valuation'!$I$7:$I$1006))),"")} | M65: {=IF(M63<>"",MAX(IF('P2-Asset Valuation'!$E$7:$E$1006=$M$6,IF('P2-Asset Valuation'!$F$7:$F$1006="Integrity",'P2-Asset Valuation'!$I$7:$I$1006))),"")} | N65: I | O65: =SUM(D65:M65) -> 0
C66: A | D66: {=IF(D63<>"",MAX(IF('P2-Asset Valuation'!$E$7:$E$1006=$D$6,IF('P2-Asset Valuation'!$F$7:$F$1006="Availability",'P2-Asset Valuation'!$I$7:$I$1006))),"")} | E66: {=IF(E63<>"",MAX(IF('P2-Asset Valuation'!$E$7:$E$1006=$E$6,IF('P2-Asset Valuation'!$F$7:$F$1006="Availability",'P2-Asset Valuation'!$I$7:$I$1006))),"")} | F66: {=IF(F63<>"",MAX(IF('P2-Asset Valuation'!$E$7:$E$1006=$F$6,IF('P2-Asset Valuation'!$F$7:$F$1006="Availability",'P2-Asset Valuation'!$I$7:$I$1006))),"")} | G66: {=IF(G63<>"",MAX(IF('P2-Asset Valuation'!$E$7:$E$1006=$G$6,IF('P2-Asset Valuation'!$F$7:$F$1006="Availability",'P2-Asset Valuation'!$I$7:$I$1006))),"")} | H66: {=IF(H63<>"",MAX(IF('P2-Asset Valuation'!$E$7:$E$1006=$H$6,IF('P2-Asset Valuation'!$F$7:$F$1006="Availability",'P2-Asset Valuation'!$I$7:$I$1006))),"")} | I66: {=IF(I63<>"",MAX(IF('P2-Asset Valuation'!$E$7:$E$1006=$I$6,IF('P2-Asset Valuation'!$F$7:$F$1006="Availability",'P2-Asset Valuation'!$I$7:$I$1006))),"")} | J66: {=IF(J63<>"",MAX(IF('P2-Asset Valuation'!$E$7:$E$1006=$J$6,IF('P2-Asset Valuation'!$F$7:$F$1006="Availability",'P2-Asset Valuation'!$I$7:$I$1006))),"")} | K66: {=IF(K63<>"",MAX(IF('P2-Asset Valuation'!$E$7:$E$1006=$K$6,IF('P2-Asset Valuation'!$F$7:$F$1006="Availability",'P2-Asset Valuation'!$I$7:$I$1006))),"")} | L66: {=IF(L63<>"",MAX(IF('P2-Asset Valuation'!$E$7:$E$1006=$L$6,IF('P2-Asset Valuation'!$F$7:$F$1006="Availability",'P2-Asset Valuation'!$I$7:$I$1006))),"")} | M66: {=IF(M63<>"",MAX(IF('P2-Asset Valuation'!$E$7:$E$1006=$M$6,IF('P2-Asset Valuation'!$F$7:$F$1006="Availability",'P2-Asset Valuation'!$I$7:$I$1006))),"")} | N66: A | O66: =SUM(D66:M66) -> 0
C67: Dimension | N67: Dimension | O67: Value
C68: C | D68: {=IF(D67<>"",MAX(IF('P2-Asset Valuation'!$E$7:$E$1006=$D$6,IF('P2-Asset Valuation'!$F$7:$F$1006="Confidentiality",'P2-Asset Valuation'!$I$7:$I$1006))),"")} | E68: {=IF(E67<>"",MAX(IF('P2-Asset Valuation'!$E$7:$E$1006=$E$6,IF('P2-Asset Valuation'!$F$7:$F$1006="Confidentiality",'P2-Asset Valuation'!$I$7:$I$1006))),"")} | F68: {=IF(F67<>"",MAX(IF('P2-Asset Valuation'!$E$7:$E$1006=$F$6,IF('P2-Asset Valuation'!$F$7:$F$1006="Confidentiality",'P2-Asset Valuation'!$I$7:$I$1006))),"")} | G68: {=IF(G67<>"",MAX(IF('P2-Asset Valuation'!$E$7:$E$1006=$G$6,IF('P2-Asset Valuation'!$F$7:$F$1006="Confidentiality",'P2-Asset Valuation'!$I$7:$I$1006))),"")} | H68: {=IF(H67<>"",MAX(IF('P2-Asset Valuation'!$E$7:$E$1006=$H$6,IF('P2-Asset Valuation'!$F$7:$F$1006="Confidentiality",'P2-Asset Valuation'!$I$7:$I$1006))),"")} | I68: {=IF(I67<>"",MAX(IF('P2-Asset Valuation'!$E$7:$E$1006=$I$6,IF('P2-Asset Valuation'!$F$7:$F$1006="Confidentiality",'P2-Asset Valuation'!$I$7:$I$1006))),"")} | J68: {=IF(J67<>"",MAX(IF('P2-Asset Valuation'!$E$7:$E$1006=$J$6,IF('P2-Asset Valuation'!$F$7:$F$1006="Confidentiality",'P2-Asset Valuation'!$I$7:$I$1006))),"")} | K68: {=IF(K67<>"",MAX(IF('P2-Asset Valuation'!$E$7:$E$1006=$K$6,IF('P2-Asset Valuation'!$F$7:$F$1006="Confidentiality",'P2-Asset Valuation'!$I$7:$I$1006))),"")} | L68: {=IF(L67<>"",MAX(IF('P2-Asset Valuation'!$E$7:$E$1006=$L$6,IF('P2-Asset Valuation'!$F$7:$F$1006="Confidentiality",'P2-Asset Valuation'!$I$7:$I$1006))),"")} | M68: {=IF(M67<>"",MAX(IF('P2-Asset Valuation'!$E$7:$E$1006=$M$6,IF('P2-Asset Valuation'!$F$7:$F$1006="Confidentiality",'P2-Asset Valuation'!$I$7:$I$1006))),"")} | N68: C | O68: =SUM(D68:M68) -> 0
C69: I | D69: {=IF(D67<>"",MAX(IF('P2-Asset Valuation'!$E$7:$E$1006=$D$6,IF('P2-Asset Valuation'!$F$7:$F$1006="Integrity",'P2-Asset Valuation'!$I$7:$I$1006))),"")} | E69: {=IF(E67<>"",MAX(IF('P2-Asset Valuation'!$E$7:$E$1006=$E$6,IF('P2-Asset Valuation'!$F$7:$F$1006="Integrity",'P2-Asset Valuation'!$I$7:$I$1006))),"")} | F69: {=IF(F67<>"",MAX(IF('P2-Asset Valuation'!$E$7:$E$1006=$F$6,IF('P2-Asset Valuation'!$F$7:$F$1006="Integrity",'P2-Asset Valuation'!$I$7:$I$1006))),"")} | G69: {=IF(G67<>"",MAX(IF('P2-Asset Valuation'!$E$7:$E$1006=$G$6,IF('P2-Asset Valuation'!$F$7:$F$1006="Integrity",'P2-Asset Valuation'!$I$7:$I$1006))),"")} | H69: {=IF(H67<>"",MAX(IF('P2-Asset Valuation'!$E$7:$E$1006=$H$6,IF('P2-Asset Valuation'!$F$7:$F$1006="Integrity",'P2-Asset Valuation'!$I$7:$I$1006))),"")} | I69: {=IF(I67<>"",MAX(IF('P2-Asset Valuation'!$E$7:$E$1006=$I$6,IF('P2-Asset Valuation'!$F$7:$F$1006="Integrity",'P2-Asset Valuation'!$I$7:$I$1006))),"")} | J69: {=IF(J67<>"",MAX(IF('P2-Asset Valuation'!$E$7:$E$1006=$J$6,IF('P2-Asset Valuation'!$F$7:$F$1006="Integrity",'P2-Asset Valuation'!$I$7:$I$1006))),"")} | K69: {=IF(K67<>"",MAX(IF('P2-Asset Valuation'!$E$7:$E$1006=$K$6,IF('P2-Asset Valuation'!$F$7:$F$1006="Integrity",'P2-Asset Valuation'!$I$7:$I$1006))),"")} | L69: {=IF(L67<>"",MAX(IF('P2-Asset Valuation'!$E$7:$E$1006=$L$6,IF('P2-Asset Valuation'!$F$7:$F$1006="Integrity",'P2-Asset Valuation'!$I$7:$I$1006))),"")} | M69: {=IF(M67<>"",MAX(IF('P2-Asset Valuation'!$E$7:$E$1006=$M$6,IF('P2-Asset Valuation'!$F$7:$F$1006="Integrity",'P2-Asset Valuation'!$I$7:$I$1006))),"")} | N69: I | O69: =SUM(D69:M69) -> 0
C70: A | D70: {=IF(D67<>"",MAX(IF('P2-Asset Valuation'!$E$7:$E$1006=$D$6,IF('P2-Asset Valuation'!$F$7:$F$1006="Availability",'P2-Asset Valuation'!$I$7:$I$1006))),"")} | E70: {=IF(E67<>"",MAX(IF('P2-Asset Valuation'!$E$7:$E$1006=$E$6,IF('P2-Asset Valuation'!$F$7:$F$1006="Availability",'P2-Asset Valuation'!$I$7:$I$1006))),"")} | F70: {=IF(F67<>"",MAX(IF('P2-Asset Valuation'!$E$7:$E$1006=$F$6,IF('P2-Asset Valuation'!$F$7:$F$1006="Availability",'P2-Asset Valuation'!$I$7:$I$1006))),"")} | G70: {=IF(G67<>"",MAX(IF('P2-Asset Valuation'!$E$7:$E$1006=$G$6,IF('P2-Asset Valuation'!$F$7:$F$1006="Availability",'P2-Asset Valuation'!$I$7:$I$1006))),"")} | H70: {=IF(H67<>"",MAX(IF('P2-Asset Valuation'!$E$7:$E$1006=$H$6,IF('P2-Asset Valuation'!$F$7:$F$1006="Availability",'P2-Asset Valuation'!$I$7:$I$1006))),"")} | I70: {=IF(I67<>"",MAX(IF('P2-Asset Valuation'!$E$7:$E$1006=$I$6,IF('P2-Asset Valuation'!$F$7:$F$1006="Availability",'P2-Asset Valuation'!$I$7:$I$1006))),"")} | J70: {=IF(J67<>"",MAX(IF('P2-Asset Valuation'!$E$7:$E$1006=$J$6,IF('P2-Asset Valuation'!$F$7:$F$1006="Availability",'P2-Asset Valuation'!$I$7:$I$1006))),"")} | K70: {=IF(K67<>"",MAX(IF('P2-Asset Valuation'!$E$7:$E$1006=$K$6,IF('P2-Asset Valuation'!$F$7:$F$1006="Availability",'P2-Asset Valuation'!$I$7:$I$1006))),"")} | L70: {=IF(L67<>"",MAX(IF('P2-Asset Valuation'!$E$7:$E$1006=$L$6,IF('P2-Asset Valuation'!$F$7:$F$1006="Availability",'P2-Asset Valuation'!$I$7:$I$1006))),"")} | M70: {=IF(M67<>"",MAX(IF('P2-Asset Valuation'!$E$7:$E$1006=$M$6,IF('P2-Asset Valuation'!$F$7:$F$1006="Availability",'P2-Asset Valuation'!$I$7:$I$1006))),"")} | N70: A | O70: =SUM(D70:M70) -> 0
C71: Dimension | N71: Dimension | O71: Value
C72: C | D72: {=IF(D71<>"",MAX(IF('P2-Asset Valuation'!$E$7:$E$1006=$D$6,IF('P2-Asset Valuation'!$F$7:$F$1006="Confidentiality",'P2-Asset Valuation'!$I$7:$I$1006))),"")} | E72: {=IF(E71<>"",MAX(IF('P2-Asset Valuation'!$E$7:$E$1006=$E$6,IF('P2-Asset Valuation'!$F$7:$F$1006="Confidentiality",'P2-Asset Valuation'!$I$7:$I$1006))),"")} | F72: {=IF(F71<>"",MAX(IF('P2-Asset Valuation'!$E$7:$E$1006=$F$6,IF('P2-Asset Valuation'!$F$7:$F$1006="Confidentiality",'P2-Asset Valuation'!$I$7:$I$1006))),"")} | G72: {=IF(G71<>"",MAX(IF('P2-Asset Valuation'!$E$7:$E$1006=$G$6,IF('P2-Asset Valuation'!$F$7:$F$1006="Confidentiality",'P2-Asset Valuation'!$I$7:$I$1006))),"")} | H72: {=IF(H71<>"",MAX(IF('P2-Asset Valuation'!$E$7:$E$1006=$H$6,IF('P2-Asset Valuation'!$F$7:$F$1006="Confidentiality",'P2-Asset Valuation'!$I$7:$I$1006))),"")} | I72: {=IF(I71<>"",MAX(IF('P2-Asset Valuation'!$E$7:$E$1006=$I$6,IF('P2-Asset Valuation'!$F$7:$F$1006="Confidentiality",'P2-Asset Valuation'!$I$7:$I$1006))),"")} | J72: {=IF(J71<>"",MAX(IF('P2-Asset Valuation'!$E$7:$E$1006=$J$6,IF('P2-Asset Valuation'!$F$7:$F$1006="Confidentiality",'P2-Asset Valuation'!$I$7:$I$1006))),"")} | K72: {=IF(K71<>"",MAX(IF('P2-Asset Valuation'!$E$7:$E$1006=$K$6,IF('P2-Asset Valuation'!$F$7:$F$1006="Confidentiality",'P2-Asset Valuation'!$I$7:$I$1006))),"")} | L72: {=IF(L71<>"",MAX(IF('P2-Asset Valuation'!$E$7:$E$1006=$L$6,IF('P2-Asset Valuation'!$F$7:$F$1006="Confidentiality",'P2-Asset Valuation'!$I$7:$I$1006))),"")} | M72: {=IF(M71<>"",MAX(IF('P2-Asset Valuation'!$E$7:$E$1006=$M$6,IF('P2-Asset Valuation'!$F$7:$F$1006="Confidentiality",'P2-Asset Valuation'!$I$7:$I$1006))),"")} | N72: C | O72: =SUM(D72:M72) -> 0
C73: I | D73: {=IF(D71<>"",MAX(IF('P2-Asset Valuation'!$E$7:$E$1006=$D$6,IF('P2-Asset Valuation'!$F$7:$F$1006="Integrity",'P2-Asset Valuation'!$I$7:$I$1006))),"")} | E73: {=IF(E71<>"",MAX(IF('P2-Asset Valuation'!$E$7:$E$1006=$E$6,IF('P2-Asset Valuation'!$F$7:$F$1006="Integrity",'P2-Asset Valuation'!$I$7:$I$1006))),"")} | F73: {=IF(F71<>"",MAX(IF('P2-Asset Valuation'!$E$7:$E$1006=$F$6,IF('P2-Asset Valuation'!$F$7:$F$1006="Integrity",'P2-Asset Valuation'!$I$7:$I$1006))),"")} | G73: {=IF(G71<>"",MAX(IF('P2-Asset Valuation'!$E$7:$E$1006=$G$6,IF('P2-Asset Valuation'!$F$7:$F$1006="Integrity",'P2-Asset Valuation'!$I$7:$I$1006))),"")} | H73: {=IF(H71<>"",MAX(IF('P2-Asset Valuation'!$E$7:$E$1006=$H$6,IF('P2-Asset Valuation'!$F$7:$F$1006="Integrity",'P2-Asset Valuation'!$I$7:$I$1006))),"")} | I73: {=IF(I71<>"",MAX(IF('P2-Asset Valuation'!$E$7:$E$1006=$I$6,IF('P2-Asset Valuation'!$F$7:$F$1006="Integrity",'P2-Asset Valuation'!$I$7:$I$1006))),"")} | J73: {=IF(J71<>"",MAX(IF('P2-Asset Valuation'!$E$7:$E$1006=$J$6,IF('P2-Asset Valuation'!$F$7:$F$1006="Integrity",'P2-Asset Valuation'!$I$7:$I$1006))),"")} | K73: {=IF(K71<>"",MAX(IF('P2-Asset Valuation'!$E$7:$E$1006=$K$6,IF('P2-Asset Valuation'!$F$7:$F$1006="Integrity",'P2-Asset Valuation'!$I$7:$I$1006))),"")} | L73: {=IF(L71<>"",MAX(IF('P2-Asset Valuation'!$E$7:$E$1006=$L$6,IF('P2-Asset Valuation'!$F$7:$F$1006="Integrity",'P2-Asset Valuation'!$I$7:$I$1006))),"")} | M73: {=IF(M71<>"",MAX(IF('P2-Asset Valuation'!$E$7:$E$1006=$M$6,IF('P2-Asset Valuation'!$F$7:$F$1006="Integrity",'P2-Asset Valuation'!$I$7:$I$1006))),"")} | N73: I | O73: =SUM(D73:M73) -> 0
C74: A | D74: {=IF(D71<>"",MAX(IF('P2-Asset Valuation'!$E$7:$E$1006=$D$6,IF('P2-Asset Valuation'!$F$7:$F$1006="Availability",'P2-Asset Valuation'!$I$7:$I$1006))),"")} | E74: {=IF(E71<>"",MAX(IF('P2-Asset Valuation'!$E$7:$E$1006=$E$6,IF('P2-Asset Valuation'!$F$7:$F$1006="Availability",'P2-Asset Valuation'!$I$7:$I$1006))),"")} | F74: {=IF(F71<>"",MAX(IF('P2-Asset Valuation'!$E$7:$E$1006=$F$6,IF('P2-Asset Valuation'!$F$7:$F$1006="Availability",'P2-Asset Valuation'!$I$7:$I$1006))),"")} | G74: {=IF(G71<>"",MAX(IF('P2-Asset Valuation'!$E$7:$E$1006=$G$6,IF('P2-Asset Valuation'!$F$7:$F$1006="Availability",'P2-Asset Valuation'!$I$7:$I$1006))),"")} | H74: {=IF(H71<>"",MAX(IF('P2-Asset Valuation'!$E$7:$E$1006=$H$6,IF('P2-Asset Valuation'!$F$7:$F$1006="Availability",'P2-Asset Valuation'!$I$7:$I$1006))),"")} | I74: {=IF(I71<>"",MAX(IF('P2-Asset Valuation'!$E$7:$E$1006=$I$6,IF('P2-Asset Valuation'!$F$7:$F$1006="Availability",'P2-Asset Valuation'!$I$7:$I$1006))),"")} | J74: {=IF(J71<>"",MAX(IF('P2-Asset Valuation'!$E$7:$E$1006=$J$6,IF('P2-Asset Valuation'!$F$7:$F$1006="Availability",'P2-Asset Valuation'!$I$7:$I$1006))),"")} | K74: {=IF(K71<>"",MAX(IF('P2-Asset Valuation'!$E$7:$E$1006=$K$6,IF('P2-Asset Valuation'!$F$7:$F$1006="Availability",'P2-Asset Valuation'!$I$7:$I$1006))),"")} | L74: {=IF(L71<>"",MAX(IF('P2-Asset Valuation'!$E$7:$E$1006=$L$6,IF('P2-Asset Valuation'!$F$7:$F$1006="Availability",'P2-Asset Valuation'!$I$7:$I$1006))),"")} | M74: {=IF(M71<>"",MAX(IF('P2-Asset Valuation'!$E$7:$E$1006=$M$6,IF('P2-Asset Valuation'!$F$7:$F$1006="Availability",'P2-Asset Valuation'!$I$7:$I$1006))),"")} | N74: A | O74: =SUM(D74:M74) -> 0
C75: Dimension | N75: Dimension | O75: Value
C76: C | D76: {=IF(D75<>"",MAX(IF('P2-Asset Valuation'!$E$7:$E$1006=$D$6,IF('P2-Asset Valuation'!$F$7:$F$1006="Confidentiality",'P2-Asset Valuation'!$I$7:$I$1006))),"")} | E76: {=IF(E75<>"",MAX(IF('P2-Asset Valuation'!$E$7:$E$1006=$E$6,IF('P2-Asset Valuation'!$F$7:$F$1006="Confidentiality",'P2-Asset Valuation'!$I$7:$I$1006))),"")} | F76: {=IF(F75<>"",MAX(IF('P2-Asset Valuation'!$E$7:$E$1006=$F$6,IF('P2-Asset Valuation'!$F$7:$F$1006="Confidentiality",'P2-Asset Valuation'!$I$7:$I$1006))),"")} | G76: {=IF(G75<>"",MAX(IF('P2-Asset Valuation'!$E$7:$E$1006=$G$6,IF('P2-Asset Valuation'!$F$7:$F$1006="Confidentiality",'P2-Asset Valuation'!$I$7:$I$1006))),"")} | H76: {=IF(H75<>"",MAX(IF('P2-Asset Valuation'!$E$7:$E$1006=$H$6,IF('P2-Asset Valuation'!$F$7:$F$1006="Confidentiality",'P2-Asset Valuation'!$I$7:$I$1006))),"")} | I76: {=IF(I75<>"",MAX(IF('P2-Asset Valuation'!$E$7:$E$1006=$I$6,IF('P2-Asset Valuation'!$F$7:$F$1006="Confidentiality",'P2-Asset Valuation'!$I$7:$I$1006))),"")} | J76: {=IF(J75<>"",MAX(IF('P2-Asset Valuation'!$E$7:$E$1006=$J$6,IF('P2-Asset Valuation'!$F$7:$F$1006="Confidentiality",'P2-Asset Valuation'!$I$7:$I$1006))),"")} | K76: {=IF(K75<>"",MAX(IF('P2-Asset Valuation'!$E$7:$E$1006=$K$6,IF('P2-Asset Valuation'!$F$7:$F$1006="Confidentiality",'P2-Asset Valuation'!$I$7:$I$1006))),"")} | L76: {=IF(L75<>"",MAX(IF('P2-Asset Valuation'!$E$7:$E$1006=$L$6,IF('P2-Asset Valuation'!$F$7:$F$1006="Confidentiality",'P2-Asset Valuation'!$I$7:$I$1006))),"")} | M76: {=IF(M75<>"",MAX(IF('P2-Asset Valuation'!$E$7:$E$1006=$M$6,IF('P2-Asset Valuation'!$F$7:$F$1006="Confidentiality",'P2-Asset Valuation'!$I$7:$I$1006))),"")} | N76: C | O76: =SUM(D76:M76) -> 0
C77: I | D77: {=IF(D75<>"",MAX(IF('P2-Asset Valuation'!$E$7:$E$1006=$D$6,IF('P2-Asset Valuation'!$F$7:$F$1006="Integrity",'P2-Asset Valuation'!$I$7:$I$1006))),"")} | E77: {=IF(E75<>"",MAX(IF('P2-Asset Valuation'!$E$7:$E$1006=$E$6,IF('P2-Asset Valuation'!$F$7:$F$1006="Integrity",'P2-Asset Valuation'!$I$7:$I$1006))),"")} | F77: {=IF(F75<>"",MAX(IF('P2-Asset Valuation'!$E$7:$E$1006=$F$6,IF('P2-Asset Valuation'!$F$7:$F$1006="Integrity",'P2-Asset Valuation'!$I$7:$I$1006))),"")} | G77: {=IF(G75<>"",MAX(IF('P2-Asset Valuation'!$E$7:$E$1006=$G$6,IF('P2-Asset Valuation'!$F$7:$F$1006="Integrity",'P2-Asset Valuation'!$I$7:$I$1006))),"")} | H77: {=IF(H75<>"",MAX(IF('P2-Asset Valuation'!$E$7:$E$1006=$H$6,IF('P2-Asset Valuation'!$F$7:$F$1006="Integrity",'P2-Asset Valuation'!$I$7:$I$1006))),"")} | I77: {=IF(I75<>"",MAX(IF('P2-Asset Valuation'!$E$7:$E$1006=$I$6,IF('P2-Asset Valuation'!$F$7:$F$1006="Integrity",'P2-Asset Valuation'!$I$7:$I$1006))),"")} | J77: {=IF(J75<>"",MAX(IF('P2-Asset Valuation'!$E$7:$E$1006=$J$6,IF('P2-Asset Valuation'!$F$7:$F$1006="Integrity",'P2-Asset Valuation'!$I$7:$I$1006))),"")} | K77: {=IF(K75<>"",MAX(IF('P2-Asset Valuation'!$E$7:$E$1006=$K$6,IF('P2-Asset Valuation'!$F$7:$F$1006="Integrity",'P2-Asset Valuation'!$I$7:$I$1006))),"")} | L77: {=IF(L75<>"",MAX(IF('P2-Asset Valuation'!$E$7:$E$1006=$L$6,IF('P2-Asset Valuation'!$F$7:$F$1006="Integrity",'P2-Asset Valuation'!$I$7:$I$1006))),"")} | M77: {=IF(M75<>"",MAX(IF('P2-Asset Valuation'!$E$7:$E$1006=$M$6,IF('P2-Asset Valuation'!$F$7:$F$1006="Integrity",'P2-Asset Valuation'!$I$7:$I$1006))),"")} | N77: I | O77: =SUM(D77:M77) -> 0
C78: A | D78: {=IF(D75<>"",MAX(IF('P2-Asset Valuation'!$E$7:$E$1006=$D$6,IF('P2-Asset Valuation'!$F$7:$F$1006="Availability",'P2-Asset Valuation'!$I$7:$I$1006))),"")} | E78: {=IF(E75<>"",MAX(IF('P2-Asset Valuation'!$E$7:$E$1006=$E$6,IF('P2-Asset Valuation'!$F$7:$F$1006="Availability",'P2-Asset Valuation'!$I$7:$I$1006))),"")} | F78: {=IF(F75<>"",MAX(IF('P2-Asset Valuation'!$E$7:$E$1006=$F$6,IF('P2-Asset Valuation'!$F$7:$F$1006="Availability",'P2-Asset Valuation'!$I$7:$I$1006))),"")} | G78: {=IF(G75<>"",MAX(IF('P2-Asset Valuation'!$E$7:$E$1006=$G$6,IF('P2-Asset Valuation'!$F$7:$F$1006="Availability",'P2-Asset Valuation'!$I$7:$I$1006))),"")} | H78: {=IF(H75<>"",MAX(IF('P2-Asset Valuation'!$E$7:$E$1006=$H$6,IF('P2-Asset Valuation'!$F$7:$F$1006="Availability",'P2-Asset Valuation'!$I$7:$I$1006))),"")} | I78: {=IF(I75<>"",MAX(IF('P2-Asset Valuation'!$E$7:$E$1006=$I$6,IF('P2-Asset Valuation'!$F$7:$F$1006="Availability",'P2-Asset Valuation'!$I$7:$I$1006))),"")} | J78: {=IF(J75<>"",MAX(IF('P2-Asset Valuation'!$E$7:$E$1006=$J$6,IF('P2-Asset Valuation'!$F$7:$F$1006="Availability",'P2-Asset Valuation'!$I$7:$I$1006))),"")} | K78: {=IF(K75<>"",MAX(IF('P2-Asset Valuation'!$E$7:$E$1006=$K$6,IF('P2-Asset Valuation'!$F$7:$F$1006="Availability",'P2-Asset Valuation'!$I$7:$I$1006))),"")} | L78: {=IF(L75<>"",MAX(IF('P2-Asset Valuation'!$E$7:$E$1006=$L$6,IF('P2-Asset Valuation'!$F$7:$F$1006="Availability",'P2-Asset Valuation'!$I$7:$I$1006))),"")} | M78: {=IF(M75<>"",MAX(IF('P2-Asset Valuation'!$E$7:$E$1006=$M$6,IF('P2-Asset Valuation'!$F$7:$F$1006="Availability",'P2-Asset Valuation'!$I$7:$I$1006))),"")} | N78: A | O78: =SUM(D78:M78) -> 0
C79: Dimension | N79: Dimension | O79: Value
C80: C | D80: {=IF(D79<>"",MAX(IF('P2-Asset Valuation'!$E$7:$E$1006=$D$6,IF('P2-Asset Valuation'!$F$7:$F$1006="Confidentiality",'P2-Asset Valuation'!$I$7:$I$1006))),"")} | E80: {=IF(E79<>"",MAX(IF('P2-Asset Valuation'!$E$7:$E$1006=$E$6,IF('P2-Asset Valuation'!$F$7:$F$1006="Confidentiality",'P2-Asset Valuation'!$I$7:$I$1006))),"")} | F80: {=IF(F79<>"",MAX(IF('P2-Asset Valuation'!$E$7:$E$1006=$F$6,IF('P2-Asset Valuation'!$F$7:$F$1006="Confidentiality",'P2-Asset Valuation'!$I$7:$I$1006))),"")} | G80: {=IF(G79<>"",MAX(IF('P2-Asset Valuation'!$E$7:$E$1006=$G$6,IF('P2-Asset Valuation'!$F$7:$F$1006="Confidentiality",'P2-Asset Valuation'!$I$7:$I$1006))),"")} | H80: {=IF(H79<>"",MAX(IF('P2-Asset Valuation'!$E$7:$E$1006=$H$6,IF('P2-Asset Valuation'!$F$7:$F$1006="Confidentiality",'P2-Asset Valuation'!$I$7:$I$1006))),"")} | I80: {=IF(I79<>"",MAX(IF('P2-Asset Valuation'!$E$7:$E$1006=$I$6,IF('P2-Asset Valuation'!$F$7:$F$1006="Confidentiality",'P2-Asset Valuation'!$I$7:$I$1006))),"")} | J80: {=IF(J79<>"",MAX(IF('P2-Asset Valuation'!$E$7:$E$1006=$J$6,IF('P2-Asset Valuation'!$F$7:$F$1006="Confidentiality",'P2-Asset Valuation'!$I$7:$I$1006))),"")} | K80: {=IF(K79<>"",MAX(IF('P2-Asset Valuation'!$E$7:$E$1006=$K$6,IF('P2-Asset Valuation'!$F$7:$F$1006="Confidentiality",'P2-Asset Valuation'!$I$7:$I$1006))),"")} | L80: {=IF(L79<>"",MAX(IF('P2-Asset Valuation'!$E$7:$E$1006=$L$6,IF('P2-Asset Valuation'!$F$7:$F$1006="Confidentiality",'P2-Asset Valuation'!$I$7:$I$1006))),"")} | M80: {=IF(M79<>"",MAX(IF('P2-Asset Valuation'!$E$7:$E$1006=$M$6,IF('P2-Asset Valuation'!$F$7:$F$1006="Confidentiality",'P2-Asset Valuation'!$I$7:$I$1006))),"")} | N80: C | O80: =SUM(D80:M80) -> 0
C81: I | D81: {=IF(D79<>"",MAX(IF('P2-Asset Valuation'!$E$7:$E$1006=$D$6,IF('P2-Asset Valuation'!$F$7:$F$1006="Integrity",'P2-Asset Valuation'!$I$7:$I$1006))),"")} | E81: {=IF(E79<>"",MAX(IF('P2-Asset Valuation'!$E$7:$E$1006=$E$6,IF('P2-Asset Valuation'!$F$7:$F$1006="Integrity",'P2-Asset Valuation'!$I$7:$I$1006))),"")} | F81: {=IF(F79<>"",MAX(IF('P2-Asset Valuation'!$E$7:$E$1006=$F$6,IF('P2-Asset Valuation'!$F$7:$F$1006="Integrity",'P2-Asset Valuation'!$I$7:$I$1006))),"")} | G81: {=IF(G79<>"",MAX(IF('P2-Asset Valuation'!$E$7:$E$1006=$G$6,IF('P2-Asset Valuation'!$F$7:$F$1006="Integrity",'P2-Asset Valuation'!$I$7:$I$1006))),"")} | H81: {=IF(H79<>"",MAX(IF('P2-Asset Valuation'!$E$7:$E$1006=$H$6,IF('P2-Asset Valuation'!$F$7:$F$1006="Integrity",'P2-Asset Valuation'!$I$7:$I$1006))),"")} | I81: {=IF(I79<>"",MAX(IF('P2-Asset Valuation'!$E$7:$E$1006=$I$6,IF('P2-Asset Valuation'!$F$7:$F$1006="Integrity",'P2-Asset Valuation'!$I$7:$I$1006))),"")} | J81: {=IF(J79<>"",MAX(IF('P2-Asset Valuation'!$E$7:$E$1006=$J$6,IF('P2-Asset Valuation'!$F$7:$F$1006="Integrity",'P2-Asset Valuation'!$I$7:$I$1006))),"")} | K81: {=IF(K79<>"",MAX(IF('P2-Asset Valuation'!$E$7:$E$1006=$K$6,IF('P2-Asset Valuation'!$F$7:$F$1006="Integrity",'P2-Asset Valuation'!$I$7:$I$1006))),"")} | L81: {=IF(L79<>"",MAX(IF('P2-Asset Valuation'!$E$7:$E$1006=$L$6,IF('P2-Asset Valuation'!$F$7:$F$1006="Integrity",'P2-Asset Valuation'!$I$7:$I$1006))),"")} | M81: {=IF(M79<>"",MAX(IF('P2-Asset Valuation'!$E$7:$E$1006=$M$6,IF('P2-Asset Valuation'!$F$7:$F$1006="Integrity",'P2-Asset Valuation'!$I$7:$I$1006))),"")} | N81: I | O81: =SUM(D81:M81) -> 0
C82: A | D82: {=IF(D79<>"",MAX(IF('P2-Asset Valuation'!$E$7:$E$1006=$D$6,IF('P2-Asset Valuation'!$F$7:$F$1006="Availability",'P2-Asset Valuation'!$I$7:$I$1006))),"")} | E82: {=IF(E79<>"",MAX(IF('P2-Asset Valuation'!$E$7:$E$1006=$E$6,IF('P2-Asset Valuation'!$F$7:$F$1006="Availability",'P2-Asset Valuation'!$I$7:$I$1006))),"")} | F82: {=IF(F79<>"",MAX(IF('P2-Asset Valuation'!$E$7:$E$1006=$F$6,IF('P2-Asset Valuation'!$F$7:$F$1006="Availability",'P2-Asset Valuation'!$I$7:$I$1006))),"")} | G82: {=IF(G79<>"",MAX(IF('P2-Asset Valuation'!$E$7:$E$1006=$G$6,IF('P2-Asset Valuation'!$F$7:$F$1006="Availability",'P2-Asset Valuation'!$I$7:$I$1006))),"")} | H82: {=IF(H79<>"",MAX(IF('P2-Asset Valuation'!$E$7:$E$1006=$H$6,IF('P2-Asset Valuation'!$F$7:$F$1006="Availability",'P2-Asset Valuation'!$I$7:$I$1006))),"")} | I82: {=IF(I79<>"",MAX(IF('P2-Asset Valuation'!$E$7:$E$1006=$I$6,IF('P2-Asset Valuation'!$F$7:$F$1006="Availability",'P2-Asset Valuation'!$I$7:$I$1006))),"")} | J82: {=IF(J79<>"",MAX(IF('P2-Asset Valuation'!$E$7:$E$1006=$J$6,IF('P2-Asset Valuation'!$F$7:$F$1006="Availability",'P2-Asset Valuation'!$I$7:$I$1006))),"")} | K82: {=IF(K79<>"",MAX(IF('P2-Asset Valuation'!$E$7:$E$1006=$K$6,IF('P2-Asset Valuation'!$F$7:$F$1006="Availability",'P2-Asset Valuation'!$I$7:$I$1006))),"")} | L82: {=IF(L79<>"",MAX(IF('P2-Asset Valuation'!$E$7:$E$1006=$L$6,IF('P2-Asset Valuation'!$F$7:$F$1006="Availability",'P2-Asset Valuation'!$I$7:$I$1006))),"")} | M82: {=IF(M79<>"",MAX(IF('P2-Asset Valuation'!$E$7:$E$1006=$M$6,IF('P2-Asset Valuation'!$F$7:$F$1006="Availability",'P2-Asset Valuation'!$I$7:$I$1006))),"")} | N82: A | O82: =SUM(D82:M82) -> 0
C83: Dimension | N83: Dimension | O83: Value
C84: C | D84: {=IF(D83<>"",MAX(IF('P2-Asset Valuation'!$E$7:$E$1006=$D$6,IF('P2-Asset Valuation'!$F$7:$F$1006="Confidentiality",'P2-Asset Valuation'!$I$7:$I$1006))),"")} | E84: {=IF(E83<>"",MAX(IF('P2-Asset Valuation'!$E$7:$E$1006=$E$6,IF('P2-Asset Valuation'!$F$7:$F$1006="Confidentiality",'P2-Asset Valuation'!$I$7:$I$1006))),"")} | F84: {=IF(F83<>"",MAX(IF('P2-Asset Valuation'!$E$7:$E$1006=$F$6,IF('P2-Asset Valuation'!$F$7:$F$1006="Confidentiality",'P2-Asset Valuation'!$I$7:$I$1006))),"")} | G84: {=IF(G83<>"",MAX(IF('P2-Asset Valuation'!$E$7:$E$1006=$G$6,IF('P2-Asset Valuation'!$F$7:$F$1006="Confidentiality",'P2-Asset Valuation'!$I$7:$I$1006))),"")} | H84: {=IF(H83<>"",MAX(IF('P2-Asset Valuation'!$E$7:$E$1006=$H$6,IF('P2-Asset Valuation'!$F$7:$F$1006="Confidentiality",'P2-Asset Valuation'!$I$7:$I$1006))),"")} | I84: {=IF(I83<>"",MAX(IF('P2-Asset Valuation'!$E$7:$E$1006=$I$6,IF('P2-Asset Valuation'!$F$7:$F$1006="Confidentiality",'P2-Asset Valuation'!$I$7:$I$1006))),"")} | J84: {=IF(J83<>"",MAX(IF('P2-Asset Valuation'!$E$7:$E$1006=$J$6,IF('P2-Asset Valuation'!$F$7:$F$1006="Confidentiality",'P2-Asset Valuation'!$I$7:$I$1006))),"")} | K84: {=IF(K83<>"",MAX(IF('P2-Asset Valuation'!$E$7:$E$1006=$K$6,IF('P2-Asset Valuation'!$F$7:$F$1006="Confidentiality",'P2-Asset Valuation'!$I$7:$I$1006))),"")} | L84: {=IF(L83<>"",MAX(IF('P2-Asset Valuation'!$E$7:$E$1006=$L$6,IF('P2-Asset Valuation'!$F$7:$F$1006="Confidentiality",'P2-Asset Valuation'!$I$7:$I$1006))),"")} | M84: {=IF(M83<>"",MAX(IF('P2-Asset Valuation'!$E$7:$E$1006=$M$6,IF('P2-Asset Valuation'!$F$7:$F$1006="Confidentiality",'P2-Asset Valuation'!$I$7:$I$1006))),"")} | N84: C | O84: =SUM(D84:M84) -> 0
C85: I | D85: {=IF(D83<>"",MAX(IF('P2-Asset Valuation'!$E$7:$E$1006=$D$6,IF('P2-Asset Valuation'!$F$7:$F$1006="Integrity",'P2-Asset Valuation'!$I$7:$I$1006))),"")} | E85: {=IF(E83<>"",MAX(IF('P2-Asset Valuation'!$E$7:$E$1006=$E$6,IF('P2-Asset Valuation'!$F$7:$F$1006="Integrity",'P2-Asset Valuation'!$I$7:$I$1006))),"")} | F85: {=IF(F83<>"",MAX(IF('P2-Asset Valuation'!$E$7:$E$1006=$F$6,IF('P2-Asset Valuation'!$F$7:$F$1006="Integrity",'P2-Asset Valuation'!$I$7:$I$1006))),"")} | G85: {=IF(G83<>"",MAX(IF('P2-Asset Valuation'!$E$7:$E$1006=$G$6,IF('P2-Asset Valuation'!$F$7:$F$1006="Integrity",'P2-Asset Valuation'!$I$7:$I$1006))),"")} | H85: {=IF(H83<>"",MAX(IF('P2-Asset Valuation'!$E$7:$E$1006=$H$6,IF('P2-Asset Valuation'!$F$7:$F$1006="Integrity",'P2-Asset Valuation'!$I$7:$I$1006))),"")} | I85: {=IF(I83<>"",MAX(IF('P2-Asset Valuation'!$E$7:$E$1006=$I$6,IF('P2-Asset Valuation'!$F$7:$F$1006="Integrity",'P2-Asset Valuation'!$I$7:$I$1006))),"")} | J85: {=IF(J83<>"",MAX(IF('P2-Asset Valuation'!$E$7:$E$1006=$J$6,IF('P2-Asset Valuation'!$F$7:$F$1006="Integrity",'P2-Asset Valuation'!$I$7:$I$1006))),"")} | K85: {=IF(K83<>"",MAX(IF('P2-Asset Valuation'!$E$7:$E$1006=$K$6,IF('P2-Asset Valuation'!$F$7:$F$1006="Integrity",'P2-Asset Valuation'!$I$7:$I$1006))),"")} | L85: {=IF(L83<>"",MAX(IF('P2-Asset Valuation'!$E$7:$E$1006=$L$6,IF('P2-Asset Valuation'!$F$7:$F$1006="Integrity",'P2-Asset Valuation'!$I$7:$I$1006))),"")} | M85: {=IF(M83<>"",MAX(IF('P2-Asset Valuation'!$E$7:$E$1006=$M$6,IF('P2-Asset Valuation'!$F$7:$F$1006="Integrity",'P2-Asset Valuation'!$I$7:$I$1006))),"")} | N85: I | O85: =SUM(D85:M85) -> 0
C86: A | D86: {=IF(D83<>"",MAX(IF('P2-Asset Valuation'!$E$7:$E$1006=$D$6,IF('P2-Asset Valuation'!$F$7:$F$1006="Availability",'P2-Asset Valuation'!$I$7:$I$1006))),"")} | E86: {=IF(E83<>"",MAX(IF('P2-Asset Valuation'!$E$7:$E$1006=$E$6,IF('P2-Asset Valuation'!$F$7:$F$1006="Availability",'P2-Asset Valuation'!$I$7:$I$1006))),"")} | F86: {=IF(F83<>"",MAX(IF('P2-Asset Valuation'!$E$7:$E$1006=$F$6,IF('P2-Asset Valuation'!$F$7:$F$1006="Availability",'P2-Asset Valuation'!$I$7:$I$1006))),"")} | G86: {=IF(G83<>"",MAX(IF('P2-Asset Valuation'!$E$7:$E$1006=$G$6,IF('P2-Asset Valuation'!$F$7:$F$1006="Availability",'P2-Asset Valuation'!$I$7:$I$1006))),"")} | H86: {=IF(H83<>"",MAX(IF('P2-Asset Valuation'!$E$7:$E$1006=$H$6,IF('P2-Asset Valuation'!$F$7:$F$1006="Availability",'P2-Asset Valuation'!$I$7:$I$1006))),"")} | I86: {=IF(I83<>"",MAX(IF('P2-Asset Valuation'!$E$7:$E$1006=$I$6,IF('P2-Asset Valuation'!$F$7:$F$1006="Availability",'P2-Asset Valuation'!$I$7:$I$1006))),"")} | J86: {=IF(J83<>"",MAX(IF('P2-Asset Valuation'!$E$7:$E$1006=$J$6,IF('P2-Asset Valuation'!$F$7:$F$1006="Availability",'P2-Asset Valuation'!$I$7:$I$1006))),"")} | K86: {=IF(K83<>"",MAX(IF('P2-Asset Valuation'!$E$7:$E$1006=$K$6,IF('P2-Asset Valuation'!$F$7:$F$1006="Availability",'P2-Asset Valuation'!$I$7:$I$1006))),"")} | L86: {=IF(L83<>"",MAX(IF('P2-Asset Valuation'!$E$7:$E$1006=$L$6,IF('P2-Asset Valuation'!$F$7:$F$1006="Availability",'P2-Asset Valuation'!$I$7:$I$1006))),"")} | M86: {=IF(M83<>"",MAX(IF('P2-Asset Valuation'!$E$7:$E$1006=$M$6,IF('P2-Asset Valuation'!$F$7:$F$1006="Availability",'P2-Asset Valuation'!$I$7:$I$1006))),"")} | N86: A | O86: =SUM(D86:M86) -> 0
C87: Dimension | N87: Dimension | O87: Value
C88: C | D88: {=IF(D87<>"",MAX(IF('P2-Asset Valuation'!$E$7:$E$1006=$D$6,IF('P2-Asset Valuation'!$F$7:$F$1006="Confidentiality",'P2-Asset Valuation'!$I$7:$I$1006))),"")} | E88: {=IF(E87<>"",MAX(IF('P2-Asset Valuation'!$E$7:$E$1006=$E$6,IF('P2-Asset Valuation'!$F$7:$F$1006="Confidentiality",'P2-Asset Valuation'!$I$7:$I$1006))),"")} | F88: {=IF(F87<>"",MAX(IF('P2-Asset Valuation'!$E$7:$E$1006=$F$6,IF('P2-Asset Valuation'!$F$7:$F$1006="Confidentiality",'P2-Asset Valuation'!$I$7:$I$1006))),"")} | G88: {=IF(G87<>"",MAX(IF('P2-Asset Valuation'!$E$7:$E$1006=$G$6,IF('P2-Asset Valuation'!$F$7:$F$1006="Confidentiality",'P2-Asset Valuation'!$I$7:$I$1006))),"")} | H88: {=IF(H87<>"",MAX(IF('P2-Asset Valuation'!$E$7:$E$1006=$H$6,IF('P2-Asset Valuation'!$F$7:$F$1006="Confidentiality",'P2-Asset Valuation'!$I$7:$I$1006))),"")} | I88: {=IF(I87<>"",MAX(IF('P2-Asset Valuation'!$E$7:$E$1006=$I$6,IF('P2-Asset Valuation'!$F$7:$F$1006="Confidentiality",'P2-Asset Valuation'!$I$7:$I$1006))),"")} | J88: {=IF(J87<>"",MAX(IF('P2-Asset Valuation'!$E$7:$E$1006=$J$6,IF('P2-Asset Valuation'!$F$7:$F$1006="Confidentiality",'P2-Asset Valuation'!$I$7:$I$1006))),"")} | K88: {=IF(K87<>"",MAX(IF('P2-Asset Valuation'!$E$7:$E$1006=$K$6,IF('P2-Asset Valuation'!$F$7:$F$1006="Confidentiality",'P2-Asset Valuation'!$I$7:$I$1006))),"")} | L88: {=IF(L87<>"",MAX(IF('P2-Asset Valuation'!$E$7:$E$1006=$L$6,IF('P2-Asset Valuation'!$F$7:$F$1006="Confidentiality",'P2-Asset Valuation'!$I$7:$I$1006))),"")} | M88: {=IF(M87<>"",MAX(IF('P2-Asset Valuation'!$E$7:$E$1006=$M$6,IF('P2-Asset Valuation'!$F$7:$F$1006="Confidentiality",'P2-Asset Valuation'!$I$7:$I$1006))),"")} | N88: C | O88: =SUM(D88:M88) -> 0
C89: I | D89: {=IF(D87<>"",MAX(IF('P2-Asset Valuation'!$E$7:$E$1006=$D$6,IF('P2-Asset Valuation'!$F$7:$F$1006="Integrity",'P2-Asset Valuation'!$I$7:$I$1006))),"")} | E89: {=IF(E87<>"",MAX(IF('P2-Asset Valuation'!$E$7:$E$1006=$E$6,IF('P2-Asset Valuation'!$F$7:$F$1006="Integrity",'P2-Asset Valuation'!$I$7:$I$1006))),"")} | F89: {=IF(F87<>"",MAX(IF('P2-Asset Valuation'!$E$7:$E$1006=$F$6,IF('P2-Asset Valuation'!$F$7:$F$1006="Integrity",'P2-Asset Valuation'!$I$7:$I$1006))),"")} | G89: {=IF(G87<>"",MAX(IF('P2-Asset Valuation'!$E$7:$E$1006=$G$6,IF('P2-Asset Valuation'!$F$7:$F$1006="Integrity",'P2-Asset Valuation'!$I$7:$I$1006))),"")} | H89: {=IF(H87<>"",MAX(IF('P2-Asset Valuation'!$E$7:$E$1006=$H$6,IF('P2-Asset Valuation'!$F$7:$F$1006="Integrity",'P2-Asset Valuation'!$I$7:$I$1006))),"")} | I89: {=IF(I87<>"",MAX(IF('P2-Asset Valuation'!$E$7:$E$1006=$I$6,IF('P2-Asset Valuation'!$F$7:$F$1006="Integrity",'P2-Asset Valuation'!$I$7:$I$1006))),"")} | J89: {=IF(J87<>"",MAX(IF('P2-Asset Valuation'!$E$7:$E$1006=$J$6,IF('P2-Asset Valuation'!$F$7:$F$1006="Integrity",'P2-Asset Valuation'!$I$7:$I$1006))),"")} | K89: {=IF(K87<>"",MAX(IF('P2-Asset Valuation'!$E$7:$E$1006=$K$6,IF('P2-Asset Valuation'!$F$7:$F$1006="Integrity",'P2-Asset Valuation'!$I$7:$I$1006))),"")} | L89: {=IF(L87<>"",MAX(IF('P2-Asset Valuation'!$E$7:$E$1006=$L$6,IF('P2-Asset Valuation'!$F$7:$F$1006="Integrity",'P2-Asset Valuation'!$I$7:$I$1006))),"")} | M89: {=IF(M87<>"",MAX(IF('P2-Asset Valuation'!$E$7:$E$1006=$M$6,IF('P2-Asset Valuation'!$F$7:$F$1006="Integrity",'P2-Asset Valuation'!$I$7:$I$1006))),"")} | N89: I | O89: =SUM(D89:M89) -> 0
C90: A | D90: {=IF(D87<>"",MAX(IF('P2-Asset Valuation'!$E$7:$E$1006=$D$6,IF('P2-Asset Valuation'!$F$7:$F$1006="Availability",'P2-Asset Valuation'!$I$7:$I$1006))),"")} | E90: {=IF(E87<>"",MAX(IF('P2-Asset Valuation'!$E$7:$E$1006=$E$6,IF('P2-Asset Valuation'!$F$7:$F$1006="Availability",'P2-Asset Valuation'!$I$7:$I$1006))),"")} | F90: {=IF(F87<>"",MAX(IF('P2-Asset Valuation'!$E$7:$E$1006=$F$6,IF('P2-Asset Valuation'!$F$7:$F$1006="Availability",'P2-Asset Valuation'!$I$7:$I$1006))),"")} | G90: {=IF(G87<>"",MAX(IF('P2-Asset Valuation'!$E$7:$E$1006=$G$6,IF('P2-Asset Valuation'!$F$7:$F$1006="Availability",'P2-Asset Valuation'!$I$7:$I$1006))),"")} | H90: {=IF(H87<>"",MAX(IF('P2-Asset Valuation'!$E$7:$E$1006=$H$6,IF('P2-Asset Valuation'!$F$7:$F$1006="Availability",'P2-Asset Valuation'!$I$7:$I$1006))),"")} | I90: {=IF(I87<>"",MAX(IF('P2-Asset Valuation'!$E$7:$E$1006=$I$6,IF('P2-Asset Valuation'!$F$7:$F$1006="Availability",'P2-Asset Valuation'!$I$7:$I$1006))),"")} | J90: {=IF(J87<>"",MAX(IF('P2-Asset Valuation'!$E$7:$E$1006=$J$6,IF('P2-Asset Valuation'!$F$7:$F$1006="Availability",'P2-Asset Valuation'!$I$7:$I$1006))),"")} | K90: {=IF(K87<>"",MAX(IF('P2-Asset Valuation'!$E$7:$E$1006=$K$6,IF('P2-Asset Valuation'!$F$7:$F$1006="Availability",'P2-Asset Valuation'!$I$7:$I$1006))),"")} | L90: {=IF(L87<>"",MAX(IF('P2-Asset Valuation'!$E$7:$E$1006=$L$6,IF('P2-Asset Valuation'!$F$7:$F$1006="Availability",'P2-Asset Valuation'!$I$7:$I$1006))),"")} | M90: {=IF(M87<>"",MAX(IF('P2-Asset Valuation'!$E$7:$E$1006=$M$6,IF('P2-Asset Valuation'!$F$7:$F$1006="Availability",'P2-Asset Valuation'!$I$7:$I$1006))),"")} | N90: A | O90: =SUM(D90:M90) -> 0
C91: Dimension | N91: Dimension | O91: Value
C92: C | D92: {=IF(D91<>"",MAX(IF('P2-Asset Valuation'!$E$7:$E$1006=$D$6,IF('P2-Asset Valuation'!$F$7:$F$1006="Confidentiality",'P2-Asset Valuation'!$I$7:$I$1006))),"")} | E92: {=IF(E91<>"",MAX(IF('P2-Asset Valuation'!$E$7:$E$1006=$E$6,IF('P2-Asset Valuation'!$F$7:$F$1006="Confidentiality",'P2-Asset Valuation'!$I$7:$I$1006))),"")} | F92: {=IF(F91<>"",MAX(IF('P2-Asset Valuation'!$E$7:$E$1006=$F$6,IF('P2-Asset Valuation'!$F$7:$F$1006="Confidentiality",'P2-Asset Valuation'!$I$7:$I$1006))),"")} | G92: {=IF(G91<>"",MAX(IF('P2-Asset Valuation'!$E$7:$E$1006=$G$6,IF('P2-Asset Valuation'!$F$7:$F$1006="Confidentiality",'P2-Asset Valuation'!$I$7:$I$1006))),"")} | H92: {=IF(H91<>"",MAX(IF('P2-Asset Valuation'!$E$7:$E$1006=$H$6,IF('P2-Asset Valuation'!$F$7:$F$1006="Confidentiality",'P2-Asset Valuation'!$I$7:$I$1006))),"")} | I92: {=IF(I91<>"",MAX(IF('P2-Asset Valuation'!$E$7:$E$1006=$I$6,IF('P2-Asset Valuation'!$F$7:$F$1006="Confidentiality",'P2-Asset Valuation'!$I$7:$I$1006))),"")} | J92: {=IF(J91<>"",MAX(IF('P2-Asset Valuation'!$E$7:$E$1006=$J$6,IF('P2-Asset Valuation'!$F$7:$F$1006="Confidentiality",'P2-Asset Valuation'!$I$7:$I$1006))),"")} | K92: {=IF(K91<>"",MAX(IF('P2-Asset Valuation'!$E$7:$E$1006=$K$6,IF('P2-Asset Valuation'!$F$7:$F$1006="Confidentiality",'P2-Asset Valuation'!$I$7:$I$1006))),"")} | L92: {=IF(L91<>"",MAX(IF('P2-Asset Valuation'!$E$7:$E$1006=$L$6,IF('P2-Asset Valuation'!$F$7:$F$1006="Confidentiality",'P2-Asset Valuation'!$I$7:$I$1006))),"")} | M92: {=IF(M91<>"",MAX(IF('P2-Asset Valuation'!$E$7:$E$1006=$M$6,IF('P2-Asset Valuation'!$F$7:$F$1006="Confidentiality",'P2-Asset Valuation'!$I$7:$I$1006))),"")} | N92: C | O92: =SUM(D92:M92) -> 0
C93: I | D93: {=IF(D91<>"",MAX(IF('P2-Asset Valuation'!$E$7:$E$1006=$D$6,IF('P2-Asset Valuation'!$F$7:$F$1006="Integrity",'P2-Asset Valuation'!$I$7:$I$1006))),"")} | E93: {=IF(E91<>"",MAX(IF('P2-Asset Valuation'!$E$7:$E$1006=$E$6,IF('P2-Asset Valuation'!$F$7:$F$1006="Integrity",'P2-Asset Valuation'!$I$7:$I$1006))),"")} | F93: {=IF(F91<>"",MAX(IF('P2-Asset Valuation'!$E$7:$E$1006=$F$6,IF('P2-Asset Valuation'!$F$7:$F$1006="Integrity",'P2-Asset Valuation'!$I$7:$I$1006))),"")} | G93: {=IF(G91<>"",MAX(IF('P2-Asset Valuation'!$E$7:$E$1006=$G$6,IF('P2-Asset Valuation'!$F$7:$F$1006="Integrity",'P2-Asset Valuation'!$I$7:$I$1006))),"")} | H93: {=IF(H91<>"",MAX(IF('P2-Asset Valuation'!$E$7:$E$1006=$H$6,IF('P2-Asset Valuation'!$F$7:$F$1006="Integrity",'P2-Asset Valuation'!$I$7:$I$1006))),"")} | I93: {=IF(I91<>"",MAX(IF('P2-Asset Valuation'!$E$7:$E$1006=$I$6,IF('P2-Asset Valuation'!$F$7:$F$1006="Integrity",'P2-Asset Valuation'!$I$7:$I$1006))),"")} | J93: {=IF(J91<>"",MAX(IF('P2-Asset Valuation'!$E$7:$E$1006=$J$6,IF('P2-Asset Valuation'!$F$7:$F$1006="Integrity",'P2-Asset Valuation'!$I$7:$I$1006))),"")} | K93: {=IF(K91<>"",MAX(IF('P2-Asset Valuation'!$E$7:$E$1006=$K$6,IF('P2-Asset Valuation'!$F$7:$F$1006="Integrity",'P2-Asset Valuation'!$I$7:$I$1006))),"")} | L93: {=IF(L91<>"",MAX(IF('P2-Asset Valuation'!$E$7:$E$1006=$L$6,IF('P2-Asset Valuation'!$F$7:$F$1006="Integrity",'P2-Asset Valuation'!$I$7:$I$1006))),"")} | M93: {=IF(M91<>"",MAX(IF('P2-Asset Valuation'!$E$7:$E$1006=$M$6,IF('P2-Asset Valuation'!$F$7:$F$1006="Integrity",'P2-Asset Valuation'!$I$7:$I$1006))),"")} | N93: I | O93: =SUM(D93:M93) -> 0
C94: A | D94: {=IF(D91<>"",MAX(IF('P2-Asset Valuation'!$E$7:$E$1006=$D$6,IF('P2-Asset Valuation'!$F$7:$F$1006="Availability",'P2-Asset Valuation'!$I$7:$I$1006))),"")} | E94: {=IF(E91<>"",MAX(IF('P2-Asset Valuation'!$E$7:$E$1006=$E$6,IF('P2-Asset Valuation'!$F$7:$F$1006="Availability",'P2-Asset Valuation'!$I$7:$I$1006))),"")} | F94: {=IF(F91<>"",MAX(IF('P2-Asset Valuation'!$E$7:$E$1006=$F$6,IF('P2-Asset Valuation'!$F$7:$F$1006="Availability",'P2-Asset Valuation'!$I$7:$I$1006))),"")} | G94: {=IF(G91<>"",MAX(IF('P2-Asset Valuation'!$E$7:$E$1006=$G$6,IF('P2-Asset Valuation'!$F$7:$F$1006="Availability",'P2-Asset Valuation'!$I$7:$I$1006))),"")} | H94: {=IF(H91<>"",MAX(IF('P2-Asset Valuation'!$E$7:$E$1006=$H$6,IF('P2-Asset Valuation'!$F$7:$F$1006="Availability",'P2-Asset Valuation'!$I$7:$I$1006))),"")} | I94: {=IF(I91<>"",MAX(IF('P2-Asset Valuation'!$E$7:$E$1006=$I$6,IF('P2-Asset Valuation'!$F$7:$F$1006="Availability",'P2-Asset Valuation'!$I$7:$I$1006))),"")} | J94: {=IF(J91<>"",MAX(IF('P2-Asset Valuation'!$E$7:$E$1006=$J$6,IF('P2-Asset Valuation'!$F$7:$F$1006="Availability",'P2-Asset Valuation'!$I$7:$I$1006))),"")} | K94: {=IF(K91<>"",MAX(IF('P2-Asset Valuation'!$E$7:$E$1006=$K$6,IF('P2-Asset Valuation'!$F$7:$F$1006="Availability",'P2-Asset Valuation'!$I$7:$I$1006))),"")} | L94: {=IF(L91<>"",MAX(IF('P2-Asset Valuation'!$E$7:$E$1006=$L$6,IF('P2-Asset Valuation'!$F$7:$F$1006="Availability",'P2-Asset Valuation'!$I$7:$I$1006))),"")} | M94: {=IF(M91<>"",MAX(IF('P2-Asset Valuation'!$E$7:$E$1006=$M$6,IF('P2-Asset Valuation'!$F$7:$F$1006="Availability",'P2-Asset Valuation'!$I$7:$I$1006))),"")} | N94: A | O94: =SUM(D94:M94) -> 0
C95: Dimension | N95: Dimension | O95: Value
C96: C | D96: {=IF(D95<>"",MAX(IF('P2-Asset Valuation'!$E$7:$E$1006=$D$6,IF('P2-Asset Valuation'!$F$7:$F$1006="Confidentiality",'P2-Asset Valuation'!$I$7:$I$1006))),"")} | E96: {=IF(E95<>"",MAX(IF('P2-Asset Valuation'!$E$7:$E$1006=$E$6,IF('P2-Asset Valuation'!$F$7:$F$1006="Confidentiality",'P2-Asset Valuation'!$I$7:$I$1006))),"")} | F96: {=IF(F95<>"",MAX(IF('P2-Asset Valuation'!$E$7:$E$1006=$F$6,IF('P2-Asset Valuation'!$F$7:$F$1006="Confidentiality",'P2-Asset Valuation'!$I$7:$I$1006))),"")} | G96: {=IF(G95<>"",MAX(IF('P2-Asset Valuation'!$E$7:$E$1006=$G$6,IF('P2-Asset Valuation'!$F$7:$F$1006="Confidentiality",'P2-Asset Valuation'!$I$7:$I$1006))),"")} | H96: {=IF(H95<>"",MAX(IF('P2-Asset Valuation'!$E$7:$E$1006=$H$6,IF('P2-Asset Valuation'!$F$7:$F$1006="Confidentiality",'P2-Asset Valuation'!$I$7:$I$1006))),"")} | I96: {=IF(I95<>"",MAX(IF('P2-Asset Valuation'!$E$7:$E$1006=$I$6,IF('P2-Asset Valuation'!$F$7:$F$1006="Confidentiality",'P2-Asset Valuation'!$I$7:$I$1006))),"")} | J96: {=IF(J95<>"",MAX(IF('P2-Asset Valuation'!$E$7:$E$1006=$J$6,IF('P2-Asset Valuation'!$F$7:$F$1006="Confidentiality",'P2-Asset Valuation'!$I$7:$I$1006))),"")} | K96: {=IF(K95<>"",MAX(IF('P2-Asset Valuation'!$E$7:$E$1006=$K$6,IF('P2-Asset Valuation'!$F$7:$F$1006="Confidentiality",'P2-Asset Valuation'!$I$7:$I$1006))),"")} | L96: {=IF(L95<>"",MAX(IF('P2-Asset Valuation'!$E$7:$E$1006=$L$6,IF('P2-Asset Valuation'!$F$7:$F$1006="Confidentiality",'P2-Asset Valuation'!$I$7:$I$1006))),"")} | M96: {=IF(M95<>"",MAX(IF('P2-Asset Valuation'!$E$7:$E$1006=$M$6,IF('P2-Asset Valuation'!$F$7:$F$1006="Confidentiality",'P2-Asset Valuation'!$I$7:$I$1006))),"")} | N96: C | O96: =SUM(D96:M96) -> 0
C97: I | D97: {=IF(D95<>"",MAX(IF('P2-Asset Valuation'!$E$7:$E$1006=$D$6,IF('P2-Asset Valuation'!$F$7:$F$1006="Integrity",'P2-Asset Valuation'!$I$7:$I$1006))),"")} | E97: {=IF(E95<>"",MAX(IF('P2-Asset Valuation'!$E$7:$E$1006=$E$6,IF('P2-Asset Valuation'!$F$7:$F$1006="Integrity",'P2-Asset Valuation'!$I$7:$I$1006))),"")} | F97: {=IF(F95<>"",MAX(IF('P2-Asset Valuation'!$E$7:$E$1006=$F$6,IF('P2-Asset Valuation'!$F$7:$F$1006="Integrity",'P2-Asset Valuation'!$I$7:$I$1006))),"")} | G97: {=IF(G95<>"",MAX(IF('P2-Asset Valuation'!$E$7:$E$1006=$G$6,IF('P2-Asset Valuation'!$F$7:$F$1006="Integrity",'P2-Asset Valuation'!$I$7:$I$1006))),"")} | H97: {=IF(H95<>"",MAX(IF('P2-Asset Valuation'!$E$7:$E$1006=$H$6,IF('P2-Asset Valuation'!$F$7:$F$1006="Integrity",'P2-Asset Valuation'!$I$7:$I$1006))),"")} | I97: {=IF(I95<>"",MAX(IF('P2-Asset Valuation'!$E$7:$E$1006=$I$6,IF('P2-Asset Valuation'!$F$7:$F$1006="Integrity",'P2-Asset Valuation'!$I$7:$I$1006))),"")} | J97: {=IF(J95<>"",MAX(IF('P2-Asset Valuation'!$E$7:$E$1006=$J$6,IF('P2-Asset Valuation'!$F$7:$F$1006="Integrity",'P2-Asset Valuation'!$I$7:$I$1006))),"")} | K97: {=IF(K95<>"",MAX(IF('P2-Asset Valuation'!$E$7:$E$1006=$K$6,IF('P2-Asset Valuation'!$F$7:$F$1006="Integrity",'P2-Asset Valuation'!$I$7:$I$1006))),"")} | L97: {=IF(L95<>"",MAX(IF('P2-Asset Valuation'!$E$7:$E$1006=$L$6,IF('P2-Asset Valuation'!$F$7:$F$1006="Integrity",'P2-Asset Valuation'!$I$7:$I$1006))),"")} | M97: {=IF(M95<>"",MAX(IF('P2-Asset Valuation'!$E$7:$E$1006=$M$6,IF('P2-Asset Valuation'!$F$7:$F$1006="Integrity",'P2-Asset Valuation'!$I$7:$I$1006))),"")} | N97: I | O97: =SUM(D97:M97) -> 0
C98: A | D98: {=IF(D95<>"",MAX(IF('P2-Asset Valuation'!$E$7:$E$1006=$D$6,IF('P2-Asset Valuation'!$F$7:$F$1006="Availability",'P2-Asset Valuation'!$I$7:$I$1006))),"")} | E98: {=IF(E95<>"",MAX(IF('P2-Asset Valuation'!$E$7:$E$1006=$E$6,IF('P2-Asset Valuation'!$F$7:$F$1006="Availability",'P2-Asset Valuation'!$I$7:$I$1006))),"")} | F98: {=IF(F95<>"",MAX(IF('P2-Asset Valuation'!$E$7:$E$1006=$F$6,IF('P2-Asset Valuation'!$F$7:$F$1006="Availability",'P2-Asset Valuation'!$I$7:$I$1006))),"")} | G98: {=IF(G95<>"",MAX(IF('P2-Asset Valuation'!$E$7:$E$1006=$G$6,IF('P2-Asset Valuation'!$F$7:$F$1006="Availability",'P2-Asset Valuation'!$I$7:$I$1006))),"")} | H98: {=IF(H95<>"",MAX(IF('P2-Asset Valuation'!$E$7:$E$1006=$H$6,IF('P2-Asset Valuation'!$F$7:$F$1006="Availability",'P2-Asset Valuation'!$I$7:$I$1006))),"")} | I98: {=IF(I95<>"",MAX(IF('P2-Asset Valuation'!$E$7:$E$1006=$I$6,IF('P2-Asset Valuation'!$F$7:$F$1006="Availability",'P2-Asset Valuation'!$I$7:$I$1006))),"")} | J98: {=IF(J95<>"",MAX(IF('P2-Asset Valuation'!$E$7:$E$1006=$J$6,IF('P2-Asset Valuation'!$F$7:$F$1006="Availability",'P2-Asset Valuation'!$I$7:$I$1006))),"")} | K98: {=IF(K95<>"",MAX(IF('P2-Asset Valuation'!$E$7:$E$1006=$K$6,IF('P2-Asset Valuation'!$F$7:$F$1006="Availability",'P2-Asset Valuation'!$I$7:$I$1006))),"")} | L98: {=IF(L95<>"",MAX(IF('P2-Asset Valuation'!$E$7:$E$1006=$L$6,IF('P2-Asset Valuation'!$F$7:$F$1006="Availability",'P2-Asset Valuation'!$I$7:$I$1006))),"")} | M98: {=IF(M95<>"",MAX(IF('P2-Asset Valuation'!$E$7:$E$1006=$M$6,IF('P2-Asset Valuation'!$F$7:$F$1006="Availability",'P2-Asset Valuation'!$I$7:$I$1006))),"")} | N98: A | O98: =SUM(D98:M98) -> 0
C99: Dimension | N99: Dimension | O99: Value
C100: C | D100: {=IF(D99<>"",MAX(IF('P2-Asset Valuation'!$E$7:$E$1006=$D$6,IF('P2-Asset Valuation'!$F$7:$F$1006="Confidentiality",'P2-Asset Valuation'!$I$7:$I$1006))),"")} | E100: {=IF(E99<>"",MAX(IF('P2-Asset Valuation'!$E$7:$E$1006=$E$6,IF('P2-Asset Valuation'!$F$7:$F$1006="Confidentiality",'P2-Asset Valuation'!$I$7:$I$1006))),"")} | F100: {=IF(F99<>"",MAX(IF('P2-Asset Valuation'!$E$7:$E$1006=$F$6,IF('P2-Asset Valuation'!$F$7:$F$1006="Confidentiality",'P2-Asset Valuation'!$I$7:$I$1006))),"")} | G100: {=IF(G99<>"",MAX(IF('P2-Asset Valuation'!$E$7:$E$1006=$G$6,IF('P2-Asset Valuation'!$F$7:$F$1006="Confidentiality",'P2-Asset Valuation'!$I$7:$I$1006))),"")} | H100: {=IF(H99<>"",MAX(IF('P2-Asset Valuation'!$E$7:$E$1006=$H$6,IF('P2-Asset Valuation'!$F$7:$F$1006="Confidentiality",'P2-Asset Valuation'!$I$7:$I$1006))),"")} | I100: {=IF(I99<>"",MAX(IF('P2-Asset Valuation'!$E$7:$E$1006=$I$6,IF('P2-Asset Valuation'!$F$7:$F$1006="Confidentiality",'P2-Asset Valuation'!$I$7:$I$1006))),"")} | J100: {=IF(J99<>"",MAX(IF('P2-Asset Valuation'!$E$7:$E$1006=$J$6,IF('P2-Asset Valuation'!$F$7:$F$1006="Confidentiality",'P2-Asset Valuation'!$I$7:$I$1006))),"")} | K100: {=IF(K99<>"",MAX(IF('P2-Asset Valuation'!$E$7:$E$1006=$K$6,IF('P2-Asset Valuation'!$F$7:$F$1006="Confidentiality",'P2-Asset Valuation'!$I$7:$I$1006))),"")} | L100: {=IF(L99<>"",MAX(IF('P2-Asset Valuation'!$E$7:$E$1006=$L$6,IF('P2-Asset Valuation'!$F$7:$F$1006="Confidentiality",'P2-Asset Valuation'!$I$7:$I$1006))),"")} | M100: {=IF(M99<>"",MAX(IF('P2-Asset Valuation'!$E$7:$E$1006=$M$6,IF('P2-Asset Valuation'!$F$7:$F$1006="Confidentiality",'P2-Asset Valuation'!$I$7:$I$1006))),"")} | N100: C | O100: =SUM(D100:M100) -> 0
C101: I | D101: {=IF(D99<>"",MAX(IF('P2-Asset Valuation'!$E$7:$E$1006=$D$6,IF('P2-Asset Valuation'!$F$7:$F$1006="Integrity",'P2-Asset Valuation'!$I$7:$I$1006))),"")} | E101: {=IF(E99<>"",MAX(IF('P2-Asset Valuation'!$E$7:$E$1006=$E$6,IF('P2-Asset Valuation'!$F$7:$F$1006="Integrity",'P2-Asset Valuation'!$I$7:$I$1006))),"")} | F101: {=IF(F99<>"",MAX(IF('P2-Asset Valuation'!$E$7:$E$1006=$F$6,IF('P2-Asset Valuation'!$F$7:$F$1006="Integrity",'P2-Asset Valuation'!$I$7:$I$1006))),"")} | G101: {=IF(G99<>"",MAX(IF('P2-Asset Valuation'!$E$7:$E$1006=$G$6,IF('P2-Asset Valuation'!$F$7:$F$1006="Integrity",'P2-Asset Valuation'!$I$7:$I$1006))),"")} | H101: {=IF(H99<>"",MAX(IF('P2-Asset Valuation'!$E$7:$E$1006=$H$6,IF('P2-Asset Valuation'!$F$7:$F$1006="Integrity",'P2-Asset Valuation'!$I$7:$I$1006))),"")} | I101: {=IF(I99<>"",MAX(IF('P2-Asset Valuation'!$E$7:$E$1006=$I$6,IF('P2-Asset Valuation'!$F$7:$F$1006="Integrity",'P2-Asset Valuation'!$I$7:$I$1006))),"")} | J101: {=IF(J99<>"",MAX(IF('P2-Asset Valuation'!$E$7:$E$1006=$J$6,IF('P2-Asset Valuation'!$F$7:$F$1006="Integrity",'P2-Asset Valuation'!$I$7:$I$1006))),"")} | K101: {=IF(K99<>"",MAX(IF('P2-Asset Valuation'!$E$7:$E$1006=$K$6,IF('P2-Asset Valuation'!$F$7:$F$1006="Integrity",'P2-Asset Valuation'!$I$7:$I$1006))),"")} | L101: {=IF(L99<>"",MAX(IF('P2-Asset Valuation'!$E$7:$E$1006=$L$6,IF('P2-Asset Valuation'!$F$7:$F$1006="Integrity",'P2-Asset Valuation'!$I$7:$I$1006))),"")} | M101: {=IF(M99<>"",MAX(IF('P2-Asset Valuation'!$E$7:$E$1006=$M$6,IF('P2-Asset Valuation'!$F$7:$F$1006="Integrity",'P2-Asset Valuation'!$I$7:$I$1006))),"")} | N101: I | O101: =SUM(D101:M101) -> 0
C102: A | D102: {=IF(D99<>"",MAX(IF('P2-Asset Valuation'!$E$7:$E$1006=$D$6,IF('P2-Asset Valuation'!$F$7:$F$1006="Availability",'P2-Asset Valuation'!$I$7:$I$1006))),"")} | E102: {=IF(E99<>"",MAX(IF('P2-Asset Valuation'!$E$7:$E$1006=$E$6,IF('P2-Asset Valuation'!$F$7:$F$1006="Availability",'P2-Asset Valuation'!$I$7:$I$1006))),"")} | F102: {=IF(F99<>"",MAX(IF('P2-Asset Valuation'!$E$7:$E$1006=$F$6,IF('P2-Asset Valuation'!$F$7:$F$1006="Availability",'P2-Asset Valuation'!$I$7:$I$1006))),"")} | G102: {=IF(G99<>"",MAX(IF('P2-Asset Valuation'!$E$7:$E$1006=$G$6,IF('P2-Asset Valuation'!$F$7:$F$1006="Availability",'P2-Asset Valuation'!$I$7:$I$1006))),"")} | H102: {=IF(H99<>"",MAX(IF('P2-Asset Valuation'!$E$7:$E$1006=$H$6,IF('P2-Asset Valuation'!$F$7:$F$1006="Availability",'P2-Asset Valuation'!$I$7:$I$1006))),"")} | I102: {=IF(I99<>"",MAX(IF('P2-Asset Valuation'!$E$7:$E$1006=$I$6,IF('P2-Asset Valuation'!$F$7:$F$1006="Availability",'P2-Asset Valuation'!$I$7:$I$1006))),"")} | J102: {=IF(J99<>"",MAX(IF('P2-Asset Valuation'!$E$7:$E$1006=$J$6,IF('P2-Asset Valuation'!$F$7:$F$1006="Availability",'P2-Asset Valuation'!$I$7:$I$1006))),"")} | K102: {=IF(K99<>"",MAX(IF('P2-Asset Valuation'!$E$7:$E$1006=$K$6,IF('P2-Asset Valuation'!$F$7:$F$1006="Availability",'P2-Asset Valuation'!$I$7:$I$1006))),"")} | L102: {=IF(L99<>"",MAX(IF('P2-Asset Valuation'!$E$7:$E$1006=$L$6,IF('P2-Asset Valuation'!$F$7:$F$1006="Availability",'P2-Asset Valuation'!$I$7:$I$1006))),"")} | M102: {=IF(M99<>"",MAX(IF('P2-Asset Valuation'!$E$7:$E$1006=$M$6,IF('P2-Asset Valuation'!$F$7:$F$1006="Availability",'P2-Asset Valuation'!$I$7:$I$1006))),"")} | N102: A | O102: =SUM(D102:M102) -> 0
C103: Dimension | N103: Dimension | O103: Value
C104: C | D104: {=IF(D103<>"",MAX(IF('P2-Asset Valuation'!$E$7:$E$1006=$D$6,IF('P2-Asset Valuation'!$F$7:$F$1006="Confidentiality",'P2-Asset Valuation'!$I$7:$I$1006))),"")} | E104: {=IF(E103<>"",MAX(IF('P2-Asset Valuation'!$E$7:$E$1006=$E$6,IF('P2-Asset Valuation'!$F$7:$F$1006="Confidentiality",'P2-Asset Valuation'!$I$7:$I$1006))),"")} | F104: {=IF(F103<>"",MAX(IF('P2-Asset Valuation'!$E$7:$E$1006=$F$6,IF('P2-Asset Valuation'!$F$7:$F$1006="Confidentiality",'P2-Asset Valuation'!$I$7:$I$1006))),"")} | G104: {=IF(G103<>"",MAX(IF('P2-Asset Valuation'!$E$7:$E$1006=$G$6,IF('P2-Asset Valuation'!$F$7:$F$1006="Confidentiality",'P2-Asset Valuation'!$I$7:$I$1006))),"")} | H104: {=IF(H103<>"",MAX(IF('P2-Asset Valuation'!$E$7:$E$1006=$H$6,IF('P2-Asset Valuation'!$F$7:$F$1006="Confidentiality",'P2-Asset Valuation'!$I$7:$I$1006))),"")} | I104: {=IF(I103<>"",MAX(IF('P2-Asset Valuation'!$E$7:$E$1006=$I$6,IF('P2-Asset Valuation'!$F$7:$F$1006="Confidentiality",'P2-Asset Valuation'!$I$7:$I$1006))),"")} | J104: {=IF(J103<>"",MAX(IF('P2-Asset Valuation'!$E$7:$E$1006=$J$6,IF('P2-Asset Valuation'!$F$7:$F$1006="Confidentiality",'P2-Asset Valuation'!$I$7:$I$1006))),"")} | K104: {=IF(K103<>"",MAX(IF('P2-Asset Valuation'!$E$7:$E$1006=$K$6,IF('P2-Asset Valuation'!$F$7:$F$1006="Confidentiality",'P2-Asset Valuation'!$I$7:$I$1006))),"")} | L104: {=IF(L103<>"",MAX(IF('P2-Asset Valuation'!$E$7:$E$1006=$L$6,IF('P2-Asset Valuation'!$F$7:$F$1006="Confidentiality",'P2-Asset Valuation'!$I$7:$I$1006))),"")} | M104: {=IF(M103<>"",MAX(IF('P2-Asset Valuation'!$E$7:$E$1006=$M$6,IF('P2-Asset Valuation'!$F$7:$F$1006="Confidentiality",'P2-Asset Valuation'!$I$7:$I$1006))),"")} | N104: C | O104: =SUM(D104:M104) -> 0
...

Sheet Formulas
B2: Process | C2: Sheet | D2: Formula | E2: Description
B3: P1 | C3: SSC | D3: ---- | E3: ----
B4: P2 | C4: Primary asset identification | D4: =SI(D7<>"";FILA()-6;"") | E4: ID column formula
C5: Asset valuation (BIA) | D5: =SI(E7<>"";CONCATENAR("Imp";TEXTO(FILA()-6;"000");"");"") | E5: ID column formula
D6: =DESREF('P2-Primary asset identification'!$D$6;1;;CONTARA('P2-Primary asset identification'!$D$6:$D$1003)-1;) | E6: Primary assets formula that takes the assets introduced on the identification sheet
D7: ='Auxiliary data'!$B$233:$B$235 | E7: Impact formula, it takes the impacts values from a hidden auxiliary data sheet
D8: =INDIRECTO(H7) | E8: Effect formula
D9: =SI.ERROR(BUSCARV(J7;'Auxiliary data'!$B$6:$C$10;2;0);"") | E9: Impact type formula
C10: Asset valuation (Manual) | D10: =DESREF('P2-Primary asset identification'!$D$6;1;;CONTARA('P2-Primary asset identification'!$D$6:$D$1003)-1;) | E10: Primary assets formula that takes the assets introduced on the identification sheet
D11: ='Auxiliary data'!$B$233:$B$235 | E11: Impact formula, it takes the impacts values from a hidden auxiliary data sheet
C12: PA atractiveness | D12: ='Auxiliary data'!$B$163:$B$176 | E12: Threat agent formula, taken from a hidden auxiliary data sheet
D13: =SI.ERROR(BUSCARV(G7;'Auxiliary data'!$B$163:$C$176;2;0);"") | E13: Power formula
D14: ='Auxiliary data'!$B$14:$B$18 | E14: Interest level formula
C15: Primary asset summary | D15: =SI.ERROR(SI(D7<>"";PROMEDIO('P2-PA Attractiveness'!H7;'P2-PA Attractiveness'!J7);"");"") | E15: Atractiveness formula
B16: P3 | C16: Supporting assets | D16: ---- | E16: ----
C17: Primary-Supporting | D17: =DESREF('P3-Supporting assets'!$D$6;1;;CONTARA('P3-Supporting assets'!$D$6:$D$1007);) | E17: Supporting asset dropwdown formula, it deploys the supporting assets introduced on the supporting assets sheet
B18: P4 | C18: Risk identification | D18: =AuxThreats!$B$2:$B$6 | E18: Threat group formula taking the values from a hidden auxiliary data sheet
D19: =INDIRECTO($I7) | E19: Threat formula
D20: ='Auxiliary data'!$B$163:$B$176 | E20: Threat agent formula, taken from a hidden auxiliary data sheet
C21: Inherent risk | D21: =SI(Y(M7<>"";N7<>"");SI.ERROR(M7*N7;"Not number");"") | E21: Inherent risk calculation formula
C22: Residual risk | D22: =SI(Y(P7<>"";Q7<>"");SI.ERROR('P4-Inherent risk'!M7*(1-'P4-Residual risk'!P7*'P4-Residual risk'!Q7);"Not number");"") | E22: Mitigated likelihood formula
D23: =SI(Y(P7<>"";Q7<>"");SI.ERROR('P4-Inherent risk'!N7*(1-'P4-Residual risk'!P7*'P4-Residual risk'!Q7);"Not number");"") | E23: Mitidated impact formula
D24: =SI(Y(S7<>"";T7<>"");SI.ERROR(S7*T7;"Not number");"") | E24: Residual risk formula

Sheet Risk analysis aux
A1: Access control | B1: The users IDs should be disabled or removed immediately after that users left the organization | C1: The audit records of target system are protected against an individual falsely denying having perfomed actions to be covered by non-repudiation | D1: Authentication process based on public key certificates | E1: Apply cryptographic mechanisms to the information stored on digital media | F1: The organisation requires third-party providers to comply with personnel security policies and procedures established by the organisation | G1: Establishes an target system alternate storage site | H1: Monitor and log priviledge users activities | I1: Implement traffic policy for allowing target system to connect to external systems. | J1: Limits the number of external network connections to the target sytem. | K1: Water protection systems | L1: Security alerts reception from external organisations | M1: Retains records of configuration-controlled changes to the information system
A2: Logging and monitoring | B2: Redundant users IDs should be identified and removed periodically | C2: A policy on the use of cryptographic controls for protection of information should be developed and implemented. | D2: Apply cryptography in transmissions to internal and external networks | E2: Apply cryptography mechanisms to backup information | F2: The organisation modifies access authorization as needed to correspond with any changes in operational need due to reassignment or transfer | G2: Establishes an target system alternate processing site | H2: Review regulary priviledge users activities | I2: Monitors and controls communications at the external boundary of the target system and at key internal boundaries within the system. | J2: Use authenticated proxies to route connections to external systems | K2: Power equipment protection | L2: The patches should be tested and evaluated before they are installed | M2: Audits and reviews activities associated with configuration-controlled changes to the information system.
A3: Policies and procedures | B3: Access rights should not be activated (e.g. by service providers) before authorization procedures are completed | C3: Management mechanisms for keys and certificates in accordance with defined requirements for key generation, distribution, storage, access, and destruction. | E3: Apply cryptography in wireless authentication and transmissions | F3: Information security responsibilities and duties that remain valid after termination or change of employment should be defined,communicated to the employee or contractor and enforced | G3: Track and document security incidents | H3: Monitor remote access connections | I3: Implements subnetworks for publicly accessible system components that are physically or logicall separated from internal organizational networks; and | J3: Monitor traffic | K3: An access control policy should be established, documented and reviewed. | M3: Implement mechanisms to manages excess capacity, bandwidth, or other redundancy
A4: Cryptography | B4: A central record of access rights granted to a user ID to access information systems and services; | C4: Implements cryptographic mechanisms to protect the integrity of audit information and audit tools of the target system | E4: Apply full-device encryption in mobile devices | F4: Provides basic security awareness training to information system users (including managers, senior executives, and contractors) as part of initial training for new users, when required by information system changes . | G4: The use of network services should be monitored | H4: Employs monitoring tools to detect indicators of denial of service attacks | J4: Physical access audit logs | K4: A policy about the use of networks and network services should be established, documented and reviewed. | M4: Malicious code protection mechanisms
A5: Human Resource Security | B5: The user access rights who have left the organization or changed their roles should be immediately removing or blocking | E5: The organisation should screens on all candidates for employment | F5: Identify personnel with specific roles and responsibilities associated with environmental controls requiring specialized training | G5: Monitor and report atypical usage of accounts | H5: Monitor resources of the target system | J5: Physical access monitoring | K5: The organization develops, documents, and disseminates a physical and environmental protection policy | M5: The organisation tests backup information to verify media reliability and information integrity
A6: Information security aspects of business continuity management | B6: The user privileged access rights should be assigned to a user ID different from those used for regular business activitie | E6: The organisation should maintain contractual agreements with employees and contractors that includes their responsabilites for information security | F6: Defines personnel or roles to be notified when a formal employee sanctions process initiated,identifying the individual sanctioned and the reason for the sanction. | H6: Scans for vulnerabilities in the target system | J6: Fire protection systems | K6: The organization enforces physical access controls employs to the entry/exit points of the facility where the target system resides
A7: Information security incident management | B7: The target system enforces the user´s access through secret autentication information | E7: Document rules of behaviour based on roles describing responsibilities and expected behavior with regard to information and target system usage. | F7: Provide incident response training to target system users | H7: Analysis of discoverable information | K7: The organization enforces physical access controls visitor, contractors and external parties
A8: System protection | B8: default vendor secret authentication information should be altered following installation of systems or software. | F8: Develop a target system contingency plan | H8: Identifies, reports, and corrects target system flaws | K8: Physical acess rights should be regularly reviewed and updated, and revoked when necessary
A9: Network security | B9: The access to systems and applications should be controllled by a secure log on designed to minimize the opportunity for unauthorized access. | F9: Coordinates target system contingency planning activities | H9: Vulnerability analysis of the outsourced development | K9: A formal user access provisioning process should be implemented to assign or revoke access rights for all user types
A10: Physical and environmental security | B10: A good log-on procedure should protect against brute force log-on attempts | F10: Provides target system contigency trainning to target sytem users | H10: Maintain records for maintenance procedures | K10: The provisioning process for assigning or revoking access rights granted to user IDs should include obtaining authorization from the owner of the target system or service for the use of the target system
A11: Roles and responsibilities | B11: A good log-on procedure should log unsuccessful and successful attempts; | H11: Flaw remediatin mechanisms | K11: The provisioning process for assigning or revoking access rights granted to user IDs should include verifying that the level of access granted is appropriate to the access policies and is consistent with other requirements such as segregation of duties
A12: Supplier relationships | B12: A good log-on procedure should display a general notice warning that the computer should only be accessed by authorized users; | K12: The user access rights should be reviewed periodically by the owner of the target system
B13: A not display system or application identifiers until the log-on process has been successfully completed | K13: The user privileged access rights should be allocated to users on a need-to-use basis and on an event-byevent basis in line with the access control policy
B14: A password management system should enforce a choice of quality passwords | K14: Specific procedures should be established and maintained in order to avoid the unauthorized use of generic administration user IDs, according to systems’ configuration capabilities;
B15: A password management system force users to change their passwords at the first log-on | K15: The allocation of secret authentication information should be controlled through a formal management process.
B16: The use of utility programs should be limitated to authorized users | K16: The users should be required to sign a statement to keep personal secret authentication information confidential
B17: Access to program source code should be restricted | K17: procedures should be established to verify the identity of a user prior to providing new, replacement or temporary secret authentication information;
B18: The Target System generates audit records for the auditable events identified | K18: temporary secret authentication information should be given to users in a secure manner
B19: Internal system clocks are used to generate time stamps for audit records that can be mapped to Coordinated Universal Time(UTC) or Greenwich Mean Time(GMT) | K19: Incident handling activities for security incidents that includes preparation, detection and analysis, containment, eradication, and recovery are implemented
B20: The Target System audit records are rewied and analyzed | K20: The organization develops, documents, and disseminates to an incident response policy
K21: Define procedures to report situations to be considered for information security incident from employees and contractors
K22: Report security incidents to thirdy parties (authorities and providers)
K23: The incident response plan is developed, updated and distributed
K24: Schedules, performs, documents, and reviews records of maintenance and repairs on target system components
K25: Approves and monitors all maintenance activities
K26: Define procedures and authorisations for removal of target system components
K27: Define maintenance procedures for target system components
K28: Sanitization procedures for target system media
K29: Maintain software updating procedures
K30: All users should be advised to keep secret authentication information confidential
K31: The organization should define and establish the roles and responsibilities associated with technical vulnerability management
K32: Intellingence over suppliers

Sheet P5-P6-P7-Risk Calculation
B4: Inherent risk | M4: Residual risk
G6: ACTIVITY 7 | I6: ACTIVITY 8 | K6: ACTIVITY 9 | M6: ACTIVITY 11 | W6: ACTIVITY 12
M7: ACTIVITY 13, ACTIVITY 14
C8: ID | D8: Primary asset | E8: Dimension | F8: Supporting asset | G8: Threat group | H8: Threat | I8: Likelihood | J8: Consequence | K8: Inherent risk | L8: Threat group Code | M8: Measure Family 1 | N8: Security measure 1 | O8: Mitigation factor 1 | P8: Measure Family 2 | Q8: Security measure 2 | R8: Mitigation factor 2 | S8: Measure Family 3 | T8: Security measure 3 | U8: Mitigation factor 3 | V8: Mitigation factor Total | W8: Residual risk | X8: Measure Group Code1 | Y8: Measure Group Code2 | Z8: Measure Group Code3 | AA8: Threat group Code | AB8: Risk Treatment Requirement (Y/N) | AC8: Comments
C9: =IF(D9<>"",CONCATENATE("IR",TEXT(ROW()-6,"000")),"") -> IR003 | D9: Citizen Data | E9: Confidentiality | F9: New Web Server | G9: Errors and unintentional failures | H9: User errors | I9: 3 | J9: 4 | K9: =IF(AND(I9<>"",J9<>""),IFERROR(I9*J9,"Not number"),"") -> 12 | L9: =IFERROR(VLOOKUP(G9,AuxThreats!$B$2:$C$6,2,0),"") -> TH.ER | M9: Access Control | N9: ACCESS ENFORCEMENT | O9: 0.72 | U9: 0 | V9: =IF(AND(O9<>"",R9<>"", U9<>""),IFERROR((I9*((1-R9)*(1-O9)*(1-U9))),"0"),"") | W9: =K9*(1-O9)*(1-R9)*(1-U9) -> 3.36 | X9: =IFERROR(VLOOKUP(M9,'Measures cat'!$A$2:$B$19,2,0),"") -> ME.AC | Y9: =IFERROR(VLOOKUP(P9,'Measures cat'!$A$2:$B$19,2,0),"") | Z9: =IFERROR(VLOOKUP(S9,'Measures cat'!$A$2:$B$19,2,0),"") | AA9: =IFERROR(VLOOKUP(I9,AuxThreats!$B$2:$C$6,2,0),"")
C10: =IF(D10<>"",CONCATENATE("IR",TEXT(ROW()-6,"000")),"") -> IR004 | D10: Citizen Data | E10: Confidentiality | F10: Application Server | G10: Wilful attacks | H10: Manipulation of the configuration files | I10: 4.66 | J10: 4 | K10: =IF(AND(I10<>"",J10<>""),IFERROR(I10*J10,"Not number"),"") -> 18.64 | L10: =IFERROR(VLOOKUP(G10,AuxThreats!$B$2:$C$6,2,0),"") -> TH.WA | M10: Security Assessment and Authorization | N10: SYSTEM INTERCONNECTIONS | O10: 0.72 | U10: 0 | V10: =IF(AND(O10<>"",R10<>"", U10<>""),IFERROR((I10*((1-R10)*(1-O10)*(1-U10))),"0"),"") | W10: =K10*(1-O10)*(1-R10)*(1-U10) -> 5.2192 | X10: =IFERROR(VLOOKUP(M10,'Measures cat'!$A$2:$B$19,2,0),"") -> ME.SA | Y10: =IFERROR(VLOOKUP(P10,'Measures cat'!$A$2:$B$19,2,0),"") | Z10: =IFERROR(VLOOKUP(S10,'Measures cat'!$A$2:$B$19,2,0),"") | AA10: =IFERROR(VLOOKUP(I10,AuxThreats!$B$2:$C$6,2,0),"")
C11: =IF(D11<>"",CONCATENATE("IR",TEXT(ROW()-6,"000")),"") -> IR005 | D11: Citizen Data | E11: Confidentiality | F11: Web Hosting Services | G11: Wilful attacks | H11: Unauthorised access | I11: 3.33 | J11: 4 | K11: =IF(AND(I11<>"",J11<>""),IFERROR(I11*J11,"Not number"),"") -> 13.32 | L11: =IFERROR(VLOOKUP(G11,AuxThreats!$B$2:$C$6,2,0),"") -> TH.WA | M11: Identification and Authentication | N11: SERVICE IDENTIFICATION AND AUTHENTICATION | O11: 0.72 | U11: 0 | V11: =IF(AND(O11<>"",R11<>"", U11<>""),IFERROR((I11*((1-R11)*(1-O11)*(1-U11))),"0"),"") | W11: =K11*(1-O11)*(1-R11)*(1-U11) -> 3.7296 | X11: =IFERROR(VLOOKUP(M11,'Measures cat'!$A$2:$B$19,2,0),"") -> ME.IA | Y11: =IFERROR(VLOOKUP(P11,'Measures cat'!$A$2:$B$19,2,0),"") | Z11: =IFERROR(VLOOKUP(S11,'Measures cat'!$A$2:$B$19,2,0),"") | AA11: =IFERROR(VLOOKUP(I11,AuxThreats!$B$2:$C$6,2,0),"")
C12: =IF(D12<>"",CONCATENATE("IR",TEXT(ROW()-6,"000")),"") -> IR006 | D12: Citizen Data | E12: Integrity | F12: New Database Server | G12: Wilful attacks | H12: Manipulation of activity records (log) | I12: 5 | J12: 4 | K12: =IF(AND(I12<>"",J12<>""),IFERROR(I12*J12,"Not number"),"") -> 20 | L12: =IFERROR(VLOOKUP(G12,AuxThreats!$B$2:$C$6,2,0),"") -> TH.WA | M12: Risk Assessment | N12: VULNERABILITY SCANNING | O12: 0.72 | R12: 0 | U12: 0 | V12: =IF(AND(O12<>"",R12<>"", U12<>""),IFERROR((I12*((1-R12)*(1-O12)*(1-U12))),"0"),"") -> 1.4 | W12: =K12*(1-O12)*(1-R12)*(1-U12) -> 5.6 | X12: =IFERROR(VLOOKUP(M12,'Measures cat'!$A$2:$B$19,2,0),"") -> ME.RA | Y12: =IFERROR(VLOOKUP(P12,'Measures cat'!$A$2:$B$19,2,0),"") | Z12: =IFERROR(VLOOKUP(S12,'Measures cat'!$A$2:$B$19,2,0),"") | AA12: =IFERROR(VLOOKUP(I12,AuxThreats!$B$2:$C$6,2,0),"")
C13: =IF(D13<>"",CONCATENATE("IR",TEXT(ROW()-6,"000")),"") -> IR007 | D13: Citizen Data | E13: Integrity | F13: New Database Server | G13: Wilful attacks | H13: Deliberate alteration of information | I13: 3.33 | J13: 4 | K13: =IF(AND(I13<>"",J13<>""),IFERROR(I13*J13,"Not number"),"") -> 13.32 | L13: =IFERROR(VLOOKUP(G13,AuxThreats!$B$2:$C$6,2,0),"") -> TH.WA | M13: System and Communications Protection | N13: BOUNDARY PROTECTION | O13: 0.72 | R13: 0 | U13: 0 | V13: =IF(AND(O13<>"",R13<>"", U13<>""),IFERROR((I13*((1-R13)*(1-O13)*(1-U13))),"0"),"") -> 0.9324 | W13: =K13*(1-O13)*(1-R13)*(1-U13) -> 3.7296 | X13: =IFERROR(VLOOKUP(M13,'Measures cat'!$A$2:$B$19,2,0),"") -> ME.SC | Y13: =IFERROR(VLOOKUP(P13,'Measures cat'!$A$2:$B$19,2,0),"") | Z13: =IFERROR(VLOOKUP(S13,'Measures cat'!$A$2:$B$19,2,0),"") | AA13: =IFERROR(VLOOKUP(I13,AuxThreats!$B$2:$C$6,2,0),"")
C14: =IF(D14<>"",CONCATENATE("IR",TEXT(ROW()-6,"000")),"") -> IR008 | D14: Citizen Data | E14: Integrity | F14: Application Server | G14: Errors and unintentional failures | H14: Software vulnerabilities | I14: 3 | J14: 4 | K14: =IF(AND(I14<>"",J14<>""),IFERROR(I14*J14,"Not number"),"") -> 12 | L14: =IFERROR(VLOOKUP(G14,AuxThreats!$B$2:$C$6,2,0),"") -> TH.ER | M14: Security Assessment and Authorization | N14: PENETRATION TESTING | O14: 0.72 | R14: 0 | U14: 0 | V14: =IF(AND(O14<>"",R14<>"", U14<>""),IFERROR((I14*((1-R14)*(1-O14)*(1-U14))),"0"),"") -> 0.84 | W14: =K14*(1-O14)*(1-R14)*(1-U14) -> 3.36 | X14: =IFERROR(VLOOKUP(M14,'Measures cat'!$A$2:$B$19,2,0),"") -> ME.SA | Y14: =IFERROR(VLOOKUP(P14,'Measures cat'!$A$2:$B$19,2,0),"") | Z14: =IFERROR(VLOOKUP(S14,'Measures cat'!$A$2:$B$19,2,0),"") | AA14: =IFERROR(VLOOKUP(I14,AuxThreats!$B$2:$C$6,2,0),"")
C15: =IF(D15<>"",CONCATENATE("IR",TEXT(ROW()-6,"000")),"") -> IR009 | D15: Citizen Data | E15: Availability | F15: External Firewall | G15: Errors and unintentional failures | H15: System failure due to exhaustion of resources | I15: 4 | J15: 4 | K15: =IF(AND(I15<>"",J15<>""),IFERROR(I15*J15,"Not number"),"") -> 16 | L15: =IFERROR(VLOOKUP(G15,AuxThreats!$B$2:$C$6,2,0),"") -> TH.ER | M15: System and Information Integrity | N15: FLAW REMEDIATION | O15: 0.72 | R15: 0 | U15: 0 | V15: =IF(AND(O15<>"",R15<>"", U15<>""),IFERROR((I15*((1-R15)*(1-O15)*(1-U15))),"0"),"") -> 1.12 | W15: =K15*(1-O15)*(1-R15)*(1-U15) -> 4.48 | X15: =IFERROR(VLOOKUP(M15,'Measures cat'!$A$2:$B$19,2,0),"") -> ME.SI | Y15: =IFERROR(VLOOKUP(P15,'Measures cat'!$A$2:$B$19,2,0),"") | Z15: =IFERROR(VLOOKUP(S15,'Measures cat'!$A$2:$B$19,2,0),"") | AA15: =IFERROR(VLOOKUP(I15,AuxThreats!$B$2:$C$6,2,0),"")
C16: =IF(D16<>"",CONCATENATE("IR",TEXT(ROW()-6,"000")),"") -> IR010 | D16: Citizen Data | E16: Availability | F16: Internet Service | G16: Industrial | H16: Communications services failure | I16: 3.33 | J16: 4 | K16: =IF(AND(I16<>"",J16<>""),IFERROR(I16*J16,"Not number"),"") -> 13.32 | L16: =IFERROR(VLOOKUP(G16,AuxThreats!$B$2:$C$6,2,0),"") -> TH.IN | M16: Contingency Planning | N16: ALTERNATE COMMUNICATIONS PROTOCOLS | O16: 0.72 | R16: 0 | U16: 0 | V16: =IF(AND(O16<>"",R16<>"", U16<>""),IFERROR((I16*((1-R16)*(1-O16)*(1-U16))),"0"),"") -> 0.9324 | W16: =K16*(1-O16)*(1-R16)*(1-U16) -> 3.7296 | X16: =IFERROR(VLOOKUP(M16,'Measures cat'!$A$2:$B$19,2,0),"") -> ME.CP | Y16: =IFERROR(VLOOKUP(P16,'Measures cat'!$A$2:$B$19,2,0),"") | Z16: =IFERROR(VLOOKUP(S16,'Measures cat'!$A$2:$B$19,2,0),"") | AA16: =IFERROR(VLOOKUP(I16,AuxThreats!$B$2:$C$6,2,0),"")
C17: =IF(D17<>"",CONCATENATE("IR",TEXT(ROW()-6,"000")),"") -> IR011 | D17: Citizen Data | E17: Availability | F17: Application Server | G17: Natural | H17: Water | I17: 2 | J17: 4 | K17: =IF(AND(I17<>"",J17<>""),IFERROR(I17*J17,"Not number"),"") -> 8 | L17: =IFERROR(VLOOKUP(G17,AuxThreats!$B$2:$C$6,2,0),"") -> TH.NT | M17: Contingency Planning | N17: CONTINGENCY PLAN | O17: 0.04 | R17: 0 | U17: 0 | V17: =IF(AND(O17<>"",R17<>"", U17<>""),IFERROR((I17*((1-R17)*(1-O17)*(1-U17))),"0"),"") -> 1.92 | W17: =K17*(1-O17)*(1-R17)*(1-U17) -> 7.68 | X17: =IFERROR(VLOOKUP(M17,'Measures cat'!$A$2:$B$19,2,0),"") -> ME.CP | Y17: =IFERROR(VLOOKUP(P17,'Measures cat'!$A$2:$B$19,2,0),"") | Z17: =IFERROR(VLOOKUP(S17,'Measures cat'!$A$2:$B$19,2,0),"") | AA17: =IFERROR(VLOOKUP(I17,AuxThreats!$B$2:$C$6,2,0),"")
